Compiled from "Gui.java"
public class net.minecraft.client.gui.Gui {
  private static final net.minecraft.resources.Identifier CROSSHAIR_SPRITE;

  private static final net.minecraft.resources.Identifier CROSSHAIR_ATTACK_INDICATOR_FULL_SPRITE;

  private static final net.minecraft.resources.Identifier CROSSHAIR_ATTACK_INDICATOR_BACKGROUND_SPRITE;

  private static final net.minecraft.resources.Identifier CROSSHAIR_ATTACK_INDICATOR_PROGRESS_SPRITE;

  private static final net.minecraft.resources.Identifier EFFECT_BACKGROUND_AMBIENT_SPRITE;

  private static final net.minecraft.resources.Identifier EFFECT_BACKGROUND_SPRITE;

  private static final net.minecraft.resources.Identifier HOTBAR_SPRITE;

  private static final net.minecraft.resources.Identifier HOTBAR_SELECTION_SPRITE;

  private static final net.minecraft.resources.Identifier HOTBAR_OFFHAND_LEFT_SPRITE;

  private static final net.minecraft.resources.Identifier HOTBAR_OFFHAND_RIGHT_SPRITE;

  private static final net.minecraft.resources.Identifier HOTBAR_ATTACK_INDICATOR_BACKGROUND_SPRITE;

  private static final net.minecraft.resources.Identifier HOTBAR_ATTACK_INDICATOR_PROGRESS_SPRITE;

  private static final net.minecraft.resources.Identifier ARMOR_EMPTY_SPRITE;

  private static final net.minecraft.resources.Identifier ARMOR_HALF_SPRITE;

  private static final net.minecraft.resources.Identifier ARMOR_FULL_SPRITE;

  private static final net.minecraft.resources.Identifier FOOD_EMPTY_HUNGER_SPRITE;

  private static final net.minecraft.resources.Identifier FOOD_HALF_HUNGER_SPRITE;

  private static final net.minecraft.resources.Identifier FOOD_FULL_HUNGER_SPRITE;

  private static final net.minecraft.resources.Identifier FOOD_EMPTY_SPRITE;

  private static final net.minecraft.resources.Identifier FOOD_HALF_SPRITE;

  private static final net.minecraft.resources.Identifier FOOD_FULL_SPRITE;

  private static final net.minecraft.resources.Identifier AIR_SPRITE;

  private static final net.minecraft.resources.Identifier AIR_POPPING_SPRITE;

  private static final net.minecraft.resources.Identifier AIR_EMPTY_SPRITE;

  private static final net.minecraft.resources.Identifier HEART_VEHICLE_CONTAINER_SPRITE;

  private static final net.minecraft.resources.Identifier HEART_VEHICLE_FULL_SPRITE;

  private static final net.minecraft.resources.Identifier HEART_VEHICLE_HALF_SPRITE;

  private static final net.minecraft.resources.Identifier VIGNETTE_LOCATION;

  public static final net.minecraft.resources.Identifier NAUSEA_LOCATION;

  private static final net.minecraft.resources.Identifier SPYGLASS_SCOPE_LOCATION;

  private static final net.minecraft.resources.Identifier POWDER_SNOW_OUTLINE_LOCATION;

  private static final java.util.Comparator<net.minecraft.world.scores.PlayerScoreEntry> SCORE_DISPLAY_ORDER;

  private static final net.minecraft.network.chat.Component DEMO_EXPIRED_TEXT;

  private static final net.minecraft.network.chat.Component SAVING_TEXT;

  private static final float MIN_CROSSHAIR_ATTACK_SPEED;

  private static final int EXPERIENCE_BAR_DISPLAY_TICKS;

  private static final int NUM_HEARTS_PER_ROW;

  private static final int LINE_HEIGHT;

  private static final java.lang.String SPACER;

  private static final float PORTAL_OVERLAY_ALPHA_MIN;

  private static final int HEART_SIZE;

  private static final int HEART_SEPARATION;

  private static final int NUM_AIR_BUBBLES;

  private static final int AIR_BUBBLE_SIZE;

  private static final int AIR_BUBBLE_SEPERATION;

  private static final int AIR_BUBBLE_POPPING_DURATION;

  private static final int EMPTY_AIR_BUBBLE_DELAY_DURATION;

  private static final float AIR_BUBBLE_POP_SOUND_VOLUME_BASE;

  private static final float AIR_BUBBLE_POP_SOUND_VOLUME_INCREMENT;

  private static final float AIR_BUBBLE_POP_SOUND_PITCH_BASE;

  private static final float AIR_BUBBLE_POP_SOUND_PITCH_INCREMENT;

  private static final int NUM_AIR_BUBBLE_POPPED_BEFORE_SOUND_VOLUME_INCREASE;

  private static final int NUM_AIR_BUBBLE_POPPED_BEFORE_SOUND_PITCH_INCREASE;

  private static final float AUTOSAVE_FADE_SPEED_FACTOR;

  private static final int SAVING_INDICATOR_WIDTH_PADDING_RIGHT;

  private static final int SAVING_INDICATOR_HEIGHT_PADDING_BOTTOM;

  private final net.minecraft.util.RandomSource random;

  private final net.minecraft.client.Minecraft minecraft;

  private final net.minecraft.client.gui.components.ChatComponent chat;

  private int tickCount;

  private net.minecraft.network.chat.Component overlayMessageString;

  private int overlayMessageTime;

  private boolean animateOverlayMessageColor;

  public float vignetteBrightness;

  private int toolHighlightTimer;

  private net.minecraft.world.item.ItemStack lastToolHighlight;

  private final net.minecraft.client.gui.components.DebugScreenOverlay debugOverlay;

  private final net.minecraft.client.gui.components.SubtitleOverlay subtitleOverlay;

  private final net.minecraft.client.gui.components.spectator.SpectatorGui spectatorGui;

  private final net.minecraft.client.gui.components.PlayerTabOverlay tabList;

  private final net.minecraft.client.gui.components.BossHealthOverlay bossOverlay;

  private int titleTime;

  private net.minecraft.network.chat.Component title;

  private net.minecraft.network.chat.Component subtitle;

  private int titleFadeInTime;

  private int titleStayTime;

  private int titleFadeOutTime;

  private int lastHealth;

  private int displayHealth;

  private long lastHealthTime;

  private long healthBlinkTime;

  private int lastBubblePopSoundPlayed;

  private java.lang.Runnable deferredSubtitles;

  private float autosaveIndicatorValue;

  private float lastAutosaveIndicatorValue;

  private org.apache.commons.lang3.tuple.Pair<net.minecraft.client.gui.Gui$ContextualInfo, net.minecraft.client.gui.contextualbar.ContextualBarRenderer> contextualInfoBar;

  private final java.util.Map<net.minecraft.client.gui.Gui$ContextualInfo, java.util.function.Supplier<net.minecraft.client.gui.contextualbar.ContextualBarRenderer>> contextualInfoBarRenderers;

  private float scopeScale;

  public net.minecraft.client.gui.Gui(net.minecraft.client.Minecraft);
    Code:
         0: aload_0
         1: invokespecial #5                  // Method java/lang/Object."<init>":()V
         4: aload_0
         5: invokestatic  #11                 // InterfaceMethod net/minecraft/util/RandomSource.create:()Lnet/minecraft/util/RandomSource;
         8: putfield      #17                 // Field random:Lnet/minecraft/util/RandomSource;
        11: aload_0
        12: fconst_1
        13: putfield      #21                 // Field vignetteBrightness:F
        16: aload_0
        17: getstatic     #25                 // Field net/minecraft/world/item/ItemStack.EMPTY:Lnet/minecraft/world/item/ItemStack;
        20: putfield      #31                 // Field lastToolHighlight:Lnet/minecraft/world/item/ItemStack;
        23: aload_0
        24: getstatic     #34                 // Field net/minecraft/client/gui/Gui$ContextualInfo.EMPTY:Lnet/minecraft/client/gui/Gui$ContextualInfo;
        27: getstatic     #39                 // Field net/minecraft/client/gui/contextualbar/ContextualBarRenderer.EMPTY:Lnet/minecraft/client/gui/contextualbar/ContextualBarRenderer;
        30: invokestatic  #44                 // Method org/apache/commons/lang3/tuple/Pair.of:(Ljava/lang/Object;Ljava/lang/Object;)Lorg/apache/commons/lang3/tuple/Pair;
        33: putfield      #50                 // Field contextualInfoBar:Lorg/apache/commons/lang3/tuple/Pair;
        36: aload_0
        37: aload_1
        38: putfield      #54                 // Field minecraft:Lnet/minecraft/client/Minecraft;
        41: aload_0
        42: new           #58                 // class net/minecraft/client/gui/components/DebugScreenOverlay
        45: dup
        46: aload_1
        47: invokespecial #60                 // Method net/minecraft/client/gui/components/DebugScreenOverlay."<init>":(Lnet/minecraft/client/Minecraft;)V
        50: putfield      #63                 // Field debugOverlay:Lnet/minecraft/client/gui/components/DebugScreenOverlay;
        53: aload_0
        54: new           #67                 // class net/minecraft/client/gui/components/spectator/SpectatorGui
        57: dup
        58: aload_1
        59: invokespecial #69                 // Method net/minecraft/client/gui/components/spectator/SpectatorGui."<init>":(Lnet/minecraft/client/Minecraft;)V
        62: putfield      #70                 // Field spectatorGui:Lnet/minecraft/client/gui/components/spectator/SpectatorGui;
        65: aload_0
        66: new           #74                 // class net/minecraft/client/gui/components/ChatComponent
        69: dup
        70: aload_1
        71: invokespecial #76                 // Method net/minecraft/client/gui/components/ChatComponent."<init>":(Lnet/minecraft/client/Minecraft;)V
        74: putfield      #77                 // Field chat:Lnet/minecraft/client/gui/components/ChatComponent;
        77: aload_0
        78: new           #81                 // class net/minecraft/client/gui/components/PlayerTabOverlay
        81: dup
        82: aload_1
        83: aload_0
        84: invokespecial #83                 // Method net/minecraft/client/gui/components/PlayerTabOverlay."<init>":(Lnet/minecraft/client/Minecraft;Lnet/minecraft/client/gui/Gui;)V
        87: putfield      #86                 // Field tabList:Lnet/minecraft/client/gui/components/PlayerTabOverlay;
        90: aload_0
        91: new           #90                 // class net/minecraft/client/gui/components/BossHealthOverlay
        94: dup
        95: aload_1
        96: invokespecial #92                 // Method net/minecraft/client/gui/components/BossHealthOverlay."<init>":(Lnet/minecraft/client/Minecraft;)V
        99: putfield      #93                 // Field bossOverlay:Lnet/minecraft/client/gui/components/BossHealthOverlay;
       102: aload_0
       103: new           #97                 // class net/minecraft/client/gui/components/SubtitleOverlay
       106: dup
       107: aload_1
       108: invokespecial #99                 // Method net/minecraft/client/gui/components/SubtitleOverlay."<init>":(Lnet/minecraft/client/Minecraft;)V
       111: putfield      #100                // Field subtitleOverlay:Lnet/minecraft/client/gui/components/SubtitleOverlay;
       114: aload_0
       115: getstatic     #34                 // Field net/minecraft/client/gui/Gui$ContextualInfo.EMPTY:Lnet/minecraft/client/gui/Gui$ContextualInfo;
       118: invokedynamic #104,  0            // InvokeDynamic #0:get:()Ljava/util/function/Supplier;
       123: getstatic     #108                // Field net/minecraft/client/gui/Gui$ContextualInfo.EXPERIENCE:Lnet/minecraft/client/gui/Gui$ContextualInfo;
       126: aload_1
       127: invokedynamic #111,  0            // InvokeDynamic #1:get:(Lnet/minecraft/client/Minecraft;)Ljava/util/function/Supplier;
       132: getstatic     #114                // Field net/minecraft/client/gui/Gui$ContextualInfo.LOCATOR:Lnet/minecraft/client/gui/Gui$ContextualInfo;
       135: aload_1
       136: invokedynamic #117,  0            // InvokeDynamic #2:get:(Lnet/minecraft/client/Minecraft;)Ljava/util/function/Supplier;
       141: getstatic     #118                // Field net/minecraft/client/gui/Gui$ContextualInfo.JUMPABLE_VEHICLE:Lnet/minecraft/client/gui/Gui$ContextualInfo;
       144: aload_1
       145: invokedynamic #121,  0            // InvokeDynamic #3:get:(Lnet/minecraft/client/Minecraft;)Ljava/util/function/Supplier;
       150: invokestatic  #122                // Method com/google/common/collect/ImmutableMap.of:(Ljava/lang/Object;Ljava/lang/Object;Ljava/lang/Object;Ljava/lang/Object;Ljava/lang/Object;Ljava/lang/Object;Ljava/lang/Object;Ljava/lang/Object;)Lcom/google/common/collect/ImmutableMap;
       153: putfield      #127                // Field contextualInfoBarRenderers:Ljava/util/Map;
       156: aload_0
       157: invokevirtual #131                // Method resetTitleTimes:()V
       160: return

  public void resetTitleTimes();
    Code:
         0: aload_0
         1: bipush        10
         3: putfield      #134                // Field titleFadeInTime:I
         6: aload_0
         7: bipush        70
         9: putfield      #138                // Field titleStayTime:I
        12: aload_0
        13: bipush        20
        15: putfield      #141                // Field titleFadeOutTime:I
        18: return

  public void extractRenderState(net.minecraft.client.gui.GuiGraphicsExtractor, net.minecraft.client.DeltaTracker);
    Code:
         0: aload_0
         1: getfield      #54                 // Field minecraft:Lnet/minecraft/client/Minecraft;
         4: getfield      #144                // Field net/minecraft/client/Minecraft.screen:Lnet/minecraft/client/gui/screens/Screen;
         7: instanceof    #150                // class net/minecraft/client/gui/screens/LevelLoadingScreen
        10: ifeq          14
        13: return
        14: aload_0
        15: getfield      #54                 // Field minecraft:Lnet/minecraft/client/Minecraft;
        18: getfield      #152                // Field net/minecraft/client/Minecraft.options:Lnet/minecraft/client/Options;
        21: getfield      #156                // Field net/minecraft/client/Options.hideGui:Z
        24: ifne          61
        27: aload_0
        28: aload_1
        29: aload_2
        30: invokevirtual #162                // Method extractCameraOverlays:(Lnet/minecraft/client/gui/GuiGraphicsExtractor;Lnet/minecraft/client/DeltaTracker;)V
        33: aload_0
        34: aload_1
        35: aload_2
        36: invokevirtual #166                // Method extractCrosshair:(Lnet/minecraft/client/gui/GuiGraphicsExtractor;Lnet/minecraft/client/DeltaTracker;)V
        39: aload_1
        40: invokevirtual #169                // Method net/minecraft/client/gui/GuiGraphicsExtractor.nextStratum:()V
        43: aload_0
        44: aload_1
        45: aload_2
        46: invokevirtual #174                // Method extractHotbarAndDecorations:(Lnet/minecraft/client/gui/GuiGraphicsExtractor;Lnet/minecraft/client/DeltaTracker;)V
        49: aload_0
        50: aload_1
        51: aload_2
        52: invokevirtual #177                // Method extractEffects:(Lnet/minecraft/client/gui/GuiGraphicsExtractor;Lnet/minecraft/client/DeltaTracker;)V
        55: aload_0
        56: aload_1
        57: aload_2
        58: invokevirtual #180                // Method extractBossOverlay:(Lnet/minecraft/client/gui/GuiGraphicsExtractor;Lnet/minecraft/client/DeltaTracker;)V
        61: aload_0
        62: aload_1
        63: aload_2
        64: invokevirtual #183                // Method extractSleepOverlay:(Lnet/minecraft/client/gui/GuiGraphicsExtractor;Lnet/minecraft/client/DeltaTracker;)V
        67: aload_0
        68: getfield      #54                 // Field minecraft:Lnet/minecraft/client/Minecraft;
        71: getfield      #152                // Field net/minecraft/client/Minecraft.options:Lnet/minecraft/client/Options;
        74: getfield      #156                // Field net/minecraft/client/Options.hideGui:Z
        77: ifne          152
        80: aload_0
        81: aload_1
        82: aload_2
        83: invokevirtual #186                // Method extractDemoOverlay:(Lnet/minecraft/client/gui/GuiGraphicsExtractor;Lnet/minecraft/client/DeltaTracker;)V
        86: aload_0
        87: aload_1
        88: aload_2
        89: invokevirtual #189                // Method extractScoreboardSidebar:(Lnet/minecraft/client/gui/GuiGraphicsExtractor;Lnet/minecraft/client/DeltaTracker;)V
        92: aload_0
        93: aload_1
        94: aload_2
        95: invokevirtual #192                // Method extractOverlayMessage:(Lnet/minecraft/client/gui/GuiGraphicsExtractor;Lnet/minecraft/client/DeltaTracker;)V
        98: aload_0
        99: aload_1
       100: aload_2
       101: invokevirtual #195                // Method extractTitle:(Lnet/minecraft/client/gui/GuiGraphicsExtractor;Lnet/minecraft/client/DeltaTracker;)V
       104: aload_0
       105: aload_1
       106: aload_2
       107: invokevirtual #198                // Method extractChat:(Lnet/minecraft/client/gui/GuiGraphicsExtractor;Lnet/minecraft/client/DeltaTracker;)V
       110: aload_0
       111: aload_1
       112: aload_2
       113: invokevirtual #201                // Method extractTabList:(Lnet/minecraft/client/gui/GuiGraphicsExtractor;Lnet/minecraft/client/DeltaTracker;)V
       116: aload_0
       117: aload_1
       118: aload_0
       119: getfield      #54                 // Field minecraft:Lnet/minecraft/client/Minecraft;
       122: getfield      #144                // Field net/minecraft/client/Minecraft.screen:Lnet/minecraft/client/gui/screens/Screen;
       125: ifnull        141
       128: aload_0
       129: getfield      #54                 // Field minecraft:Lnet/minecraft/client/Minecraft;
       132: getfield      #144                // Field net/minecraft/client/Minecraft.screen:Lnet/minecraft/client/gui/screens/Screen;
       135: invokevirtual #204                // Method net/minecraft/client/gui/screens/Screen.isInGameUi:()Z
       138: ifeq          145
       141: iconst_1
       142: goto          146
       145: iconst_0
       146: invokevirtual #210                // Method extractSubtitleOverlay:(Lnet/minecraft/client/gui/GuiGraphicsExtractor;Z)V
       149: goto          181
       152: aload_0
       153: getfield      #54                 // Field minecraft:Lnet/minecraft/client/Minecraft;
       156: getfield      #144                // Field net/minecraft/client/Minecraft.screen:Lnet/minecraft/client/gui/screens/Screen;
       159: ifnull        181
       162: aload_0
       163: getfield      #54                 // Field minecraft:Lnet/minecraft/client/Minecraft;
       166: getfield      #144                // Field net/minecraft/client/Minecraft.screen:Lnet/minecraft/client/gui/screens/Screen;
       169: invokevirtual #204                // Method net/minecraft/client/gui/screens/Screen.isInGameUi:()Z
       172: ifeq          181
       175: aload_0
       176: aload_1
       177: iconst_1
       178: invokevirtual #210                // Method extractSubtitleOverlay:(Lnet/minecraft/client/gui/GuiGraphicsExtractor;Z)V
       181: return

  private void extractBossOverlay(net.minecraft.client.gui.GuiGraphicsExtractor, net.minecraft.client.DeltaTracker);
    Code:
         0: aload_0
         1: getfield      #93                 // Field bossOverlay:Lnet/minecraft/client/gui/components/BossHealthOverlay;
         4: aload_1
         5: invokevirtual #214                // Method net/minecraft/client/gui/components/BossHealthOverlay.extractRenderState:(Lnet/minecraft/client/gui/GuiGraphicsExtractor;)V
         8: return

  public void extractDebugOverlay(net.minecraft.client.gui.GuiGraphicsExtractor);
    Code:
         0: aload_0
         1: getfield      #63                 // Field debugOverlay:Lnet/minecraft/client/gui/components/DebugScreenOverlay;
         4: aload_1
         5: invokevirtual #218                // Method net/minecraft/client/gui/components/DebugScreenOverlay.extractRenderState:(Lnet/minecraft/client/gui/GuiGraphicsExtractor;)V
         8: return

  private void extractSubtitleOverlay(net.minecraft.client.gui.GuiGraphicsExtractor, boolean);
    Code:
         0: iload_2
         1: ifeq          18
         4: aload_0
         5: aload_0
         6: aload_1
         7: invokedynamic #219,  0            // InvokeDynamic #4:run:(Lnet/minecraft/client/gui/Gui;Lnet/minecraft/client/gui/GuiGraphicsExtractor;)Ljava/lang/Runnable;
        12: putfield      #223                // Field deferredSubtitles:Ljava/lang/Runnable;
        15: goto          31
        18: aload_0
        19: aconst_null
        20: putfield      #223                // Field deferredSubtitles:Ljava/lang/Runnable;
        23: aload_0
        24: getfield      #100                // Field subtitleOverlay:Lnet/minecraft/client/gui/components/SubtitleOverlay;
        27: aload_1
        28: invokevirtual #227                // Method net/minecraft/client/gui/components/SubtitleOverlay.extractRenderState:(Lnet/minecraft/client/gui/GuiGraphicsExtractor;)V
        31: return

  public void extractDeferredSubtitles();
    Code:
         0: aload_0
         1: getfield      #223                // Field deferredSubtitles:Ljava/lang/Runnable;
         4: ifnull        21
         7: aload_0
         8: getfield      #223                // Field deferredSubtitles:Ljava/lang/Runnable;
        11: invokeinterface #228,  1          // InterfaceMethod java/lang/Runnable.run:()V
        16: aload_0
        17: aconst_null
        18: putfield      #223                // Field deferredSubtitles:Ljava/lang/Runnable;
        21: return

  private void extractCameraOverlays(net.minecraft.client.gui.GuiGraphicsExtractor, net.minecraft.client.DeltaTracker);
    Code:
         0: aload_0
         1: getfield      #54                 // Field minecraft:Lnet/minecraft/client/Minecraft;
         4: getfield      #152                // Field net/minecraft/client/Minecraft.options:Lnet/minecraft/client/Options;
         7: invokevirtual #232                // Method net/minecraft/client/Options.vignette:()Lnet/minecraft/client/OptionInstance;
        10: invokevirtual #236                // Method net/minecraft/client/OptionInstance.get:()Ljava/lang/Object;
        13: checkcast     #241                // class java/lang/Boolean
        16: invokevirtual #243                // Method java/lang/Boolean.booleanValue:()Z
        19: ifeq          34
        22: aload_0
        23: aload_1
        24: aload_0
        25: getfield      #54                 // Field minecraft:Lnet/minecraft/client/Minecraft;
        28: invokevirtual #246                // Method net/minecraft/client/Minecraft.getCameraEntity:()Lnet/minecraft/world/entity/Entity;
        31: invokevirtual #250                // Method extractVignette:(Lnet/minecraft/client/gui/GuiGraphicsExtractor;Lnet/minecraft/world/entity/Entity;)V
        34: aload_0
        35: getfield      #54                 // Field minecraft:Lnet/minecraft/client/Minecraft;
        38: getfield      #254                // Field net/minecraft/client/Minecraft.player:Lnet/minecraft/client/player/LocalPlayer;
        41: astore_3
        42: aload_2
        43: invokeinterface #258,  1          // InterfaceMethod net/minecraft/client/DeltaTracker.getGameTimeDeltaTicks:()F
        48: fstore        4
        50: aload_0
        51: ldc_w         #264                // float 0.5f
        54: fload         4
        56: fmul
        57: aload_0
        58: getfield      #265                // Field scopeScale:F
        61: ldc_w         #268                // float 1.125f
        64: invokestatic  #269                // Method net/minecraft/util/Mth.lerp:(FFF)F
        67: putfield      #265                // Field scopeScale:F
        70: aload_0
        71: getfield      #54                 // Field minecraft:Lnet/minecraft/client/Minecraft;
        74: getfield      #152                // Field net/minecraft/client/Minecraft.options:Lnet/minecraft/client/Options;
        77: invokevirtual #275                // Method net/minecraft/client/Options.getCameraType:()Lnet/minecraft/client/CameraType;
        80: invokevirtual #279                // Method net/minecraft/client/CameraType.isFirstPerson:()Z
        83: ifeq          217
        86: aload_3
        87: invokevirtual #284                // Method net/minecraft/client/player/LocalPlayer.isScoping:()Z
        90: ifeq          105
        93: aload_0
        94: aload_1
        95: aload_0
        96: getfield      #265                // Field scopeScale:F
        99: invokevirtual #289                // Method extractSpyglassOverlay:(Lnet/minecraft/client/gui/GuiGraphicsExtractor;F)V
       102: goto          217
       105: aload_0
       106: ldc_w         #264                // float 0.5f
       109: putfield      #265                // Field scopeScale:F
       112: invokestatic  #293                // Method net/minecraft/world/entity/EquipmentSlot.values:()[Lnet/minecraft/world/entity/EquipmentSlot;
       115: astore        5
       117: aload         5
       119: arraylength
       120: istore        6
       122: iconst_0
       123: istore        7
       125: iload         7
       127: iload         6
       129: if_icmpge     217
       132: aload         5
       134: iload         7
       136: aaload
       137: astore        8
       139: aload_3
       140: aload         8
       142: invokevirtual #299                // Method net/minecraft/client/player/LocalPlayer.getItemBySlot:(Lnet/minecraft/world/entity/EquipmentSlot;)Lnet/minecraft/world/item/ItemStack;
       145: astore        9
       147: aload         9
       149: getstatic     #303                // Field net/minecraft/core/component/DataComponents.EQUIPPABLE:Lnet/minecraft/core/component/DataComponentType;
       152: invokevirtual #309                // Method net/minecraft/world/item/ItemStack.get:(Lnet/minecraft/core/component/DataComponentType;)Ljava/lang/Object;
       155: checkcast     #312                // class net/minecraft/world/item/equipment/Equippable
       158: astore        10
       160: aload         10
       162: ifnull        211
       165: aload         10
       167: invokevirtual #314                // Method net/minecraft/world/item/equipment/Equippable.slot:()Lnet/minecraft/world/entity/EquipmentSlot;
       170: aload         8
       172: if_acmpne     211
       175: aload         10
       177: invokevirtual #318                // Method net/minecraft/world/item/equipment/Equippable.cameraOverlay:()Ljava/util/Optional;
       180: invokevirtual #322                // Method java/util/Optional.isPresent:()Z
       183: ifeq          211
       186: aload_0
       187: aload_1
       188: aload         10
       190: invokevirtual #318                // Method net/minecraft/world/item/equipment/Equippable.cameraOverlay:()Ljava/util/Optional;
       193: invokevirtual #327                // Method java/util/Optional.get:()Ljava/lang/Object;
       196: checkcast     #328                // class net/minecraft/resources/Identifier
       199: invokedynamic #330,  0            // InvokeDynamic #5:apply:()Ljava/util/function/UnaryOperator;
       204: invokevirtual #334                // Method net/minecraft/resources/Identifier.withPath:(Ljava/util/function/UnaryOperator;)Lnet/minecraft/resources/Identifier;
       207: fconst_1
       208: invokevirtual #338                // Method extractTextureOverlay:(Lnet/minecraft/client/gui/GuiGraphicsExtractor;Lnet/minecraft/resources/Identifier;F)V
       211: iinc          7, 1
       214: goto          125
       217: aload_3
       218: invokevirtual #342                // Method net/minecraft/client/player/LocalPlayer.getTicksFrozen:()I
       221: ifle          236
       224: aload_0
       225: aload_1
       226: getstatic     #346                // Field POWDER_SNOW_OUTLINE_LOCATION:Lnet/minecraft/resources/Identifier;
       229: aload_3
       230: invokevirtual #350                // Method net/minecraft/client/player/LocalPlayer.getPercentFrozen:()F
       233: invokevirtual #338                // Method extractTextureOverlay:(Lnet/minecraft/client/gui/GuiGraphicsExtractor;Lnet/minecraft/resources/Identifier;F)V
       236: aload_2
       237: iconst_0
       238: invokeinterface #353,  2          // InterfaceMethod net/minecraft/client/DeltaTracker.getGameTimeDeltaPartialTick:(Z)F
       243: fstore        5
       245: fload         5
       247: aload_3
       248: getfield      #357                // Field net/minecraft/client/player/LocalPlayer.oPortalEffectIntensity:F
       251: aload_3
       252: getfield      #360                // Field net/minecraft/client/player/LocalPlayer.portalEffectIntensity:F
       255: invokestatic  #269                // Method net/minecraft/util/Mth.lerp:(FFF)F
       258: fstore        6
       260: aload_3
       261: getstatic     #363                // Field net/minecraft/world/effect/MobEffects.NAUSEA:Lnet/minecraft/core/Holder;
       264: fload         5
       266: invokevirtual #369                // Method net/minecraft/client/player/LocalPlayer.getEffectBlendFactor:(Lnet/minecraft/core/Holder;F)F
       269: fstore        7
       271: fload         6
       273: fconst_0
       274: fcmpl
       275: ifle          288
       278: aload_0
       279: aload_1
       280: fload         6
       282: invokevirtual #373                // Method extractPortalOverlay:(Lnet/minecraft/client/gui/GuiGraphicsExtractor;F)V
       285: goto          339
       288: fload         7
       290: fconst_0
       291: fcmpl
       292: ifle          339
       295: aload_0
       296: getfield      #54                 // Field minecraft:Lnet/minecraft/client/Minecraft;
       299: getfield      #152                // Field net/minecraft/client/Minecraft.options:Lnet/minecraft/client/Options;
       302: invokevirtual #376                // Method net/minecraft/client/Options.screenEffectScale:()Lnet/minecraft/client/OptionInstance;
       305: invokevirtual #236                // Method net/minecraft/client/OptionInstance.get:()Ljava/lang/Object;
       308: checkcast     #379                // class java/lang/Double
       311: invokevirtual #381                // Method java/lang/Double.floatValue:()F
       314: fstore        8
       316: fload         8
       318: fconst_1
       319: fcmpg
       320: ifge          339
       323: fload         7
       325: fconst_1
       326: fload         8
       328: fsub
       329: fmul
       330: fstore        9
       332: aload_0
       333: aload_1
       334: fload         9
       336: invokevirtual #384                // Method extractConfusionOverlay:(Lnet/minecraft/client/gui/GuiGraphicsExtractor;F)V
       339: return

  private void extractSleepOverlay(net.minecraft.client.gui.GuiGraphicsExtractor, net.minecraft.client.DeltaTracker);
    Code:
         0: aload_0
         1: getfield      #54                 // Field minecraft:Lnet/minecraft/client/Minecraft;
         4: getfield      #254                // Field net/minecraft/client/Minecraft.player:Lnet/minecraft/client/player/LocalPlayer;
         7: invokevirtual #387                // Method net/minecraft/client/player/LocalPlayer.getSleepTimer:()I
        10: ifgt          14
        13: return
        14: invokestatic  #390                // Method net/minecraft/util/profiling/Profiler.get:()Lnet/minecraft/util/profiling/ProfilerFiller;
        17: ldc_w         #395                // String sleep
        20: invokeinterface #397,  2          // InterfaceMethod net/minecraft/util/profiling/ProfilerFiller.push:(Ljava/lang/String;)V
        25: aload_1
        26: invokevirtual #169                // Method net/minecraft/client/gui/GuiGraphicsExtractor.nextStratum:()V
        29: aload_0
        30: getfield      #54                 // Field minecraft:Lnet/minecraft/client/Minecraft;
        33: getfield      #254                // Field net/minecraft/client/Minecraft.player:Lnet/minecraft/client/player/LocalPlayer;
        36: invokevirtual #387                // Method net/minecraft/client/player/LocalPlayer.getSleepTimer:()I
        39: i2f
        40: fstore_3
        41: fload_3
        42: ldc_w         #405                // float 100.0f
        45: fdiv
        46: fstore        4
        48: fload         4
        50: fconst_1
        51: fcmpl
        52: ifle          68
        55: fconst_1
        56: fload_3
        57: ldc_w         #405                // float 100.0f
        60: fsub
        61: ldc_w         #406                // float 10.0f
        64: fdiv
        65: fsub
        66: fstore        4
        68: ldc_w         #407                // float 220.0f
        71: fload         4
        73: fmul
        74: f2i
        75: bipush        24
        77: ishl
        78: ldc_w         #408                // int 1052704
        81: ior
        82: istore        5
        84: aload_1
        85: iconst_0
        86: iconst_0
        87: aload_1
        88: invokevirtual #409                // Method net/minecraft/client/gui/GuiGraphicsExtractor.guiWidth:()I
        91: aload_1
        92: invokevirtual #412                // Method net/minecraft/client/gui/GuiGraphicsExtractor.guiHeight:()I
        95: iload         5
        97: invokevirtual #415                // Method net/minecraft/client/gui/GuiGraphicsExtractor.fill:(IIIII)V
       100: invokestatic  #390                // Method net/minecraft/util/profiling/Profiler.get:()Lnet/minecraft/util/profiling/ProfilerFiller;
       103: invokeinterface #419,  1          // InterfaceMethod net/minecraft/util/profiling/ProfilerFiller.pop:()V
       108: return

  private void extractOverlayMessage(net.minecraft.client.gui.GuiGraphicsExtractor, net.minecraft.client.DeltaTracker);
    Code:
         0: aload_0
         1: invokevirtual #422                // Method getFont:()Lnet/minecraft/client/gui/Font;
         4: astore_3
         5: aload_0
         6: getfield      #426                // Field overlayMessageString:Lnet/minecraft/network/chat/Component;
         9: ifnull        19
        12: aload_0
        13: getfield      #430                // Field overlayMessageTime:I
        16: ifgt          20
        19: return
        20: invokestatic  #390                // Method net/minecraft/util/profiling/Profiler.get:()Lnet/minecraft/util/profiling/ProfilerFiller;
        23: ldc_w         #433                // String overlayMessage
        26: invokeinterface #397,  2          // InterfaceMethod net/minecraft/util/profiling/ProfilerFiller.push:(Ljava/lang/String;)V
        31: aload_0
        32: getfield      #430                // Field overlayMessageTime:I
        35: i2f
        36: aload_2
        37: iconst_0
        38: invokeinterface #353,  2          // InterfaceMethod net/minecraft/client/DeltaTracker.getGameTimeDeltaPartialTick:(Z)F
        43: fsub
        44: fstore        4
        46: fload         4
        48: ldc_w         #435                // float 255.0f
        51: fmul
        52: ldc_w         #436                // float 20.0f
        55: fdiv
        56: f2i
        57: istore        5
        59: iload         5
        61: sipush        255
        64: if_icmple     72
        67: sipush        255
        70: istore        5
        72: iload         5
        74: ifle          186
        77: aload_1
        78: invokevirtual #169                // Method net/minecraft/client/gui/GuiGraphicsExtractor.nextStratum:()V
        81: aload_1
        82: invokevirtual #437                // Method net/minecraft/client/gui/GuiGraphicsExtractor.pose:()Lorg/joml/Matrix3x2fStack;
        85: invokevirtual #441                // Method org/joml/Matrix3x2fStack.pushMatrix:()Lorg/joml/Matrix3x2fStack;
        88: pop
        89: aload_1
        90: invokevirtual #437                // Method net/minecraft/client/gui/GuiGraphicsExtractor.pose:()Lorg/joml/Matrix3x2fStack;
        93: aload_1
        94: invokevirtual #409                // Method net/minecraft/client/gui/GuiGraphicsExtractor.guiWidth:()I
        97: iconst_2
        98: idiv
        99: i2f
       100: aload_1
       101: invokevirtual #412                // Method net/minecraft/client/gui/GuiGraphicsExtractor.guiHeight:()I
       104: bipush        68
       106: isub
       107: i2f
       108: invokevirtual #446                // Method org/joml/Matrix3x2fStack.translate:(FF)Lorg/joml/Matrix3x2f;
       111: pop
       112: aload_0
       113: getfield      #450                // Field animateOverlayMessageColor:Z
       116: ifeq          141
       119: fload         4
       121: ldc_w         #453                // float 50.0f
       124: fdiv
       125: ldc_w         #454                // float 0.7f
       128: ldc_w         #455                // float 0.6f
       131: iload         5
       133: invokestatic  #456                // Method net/minecraft/util/Mth.hsvToArgb:(FFFI)I
       136: istore        6
       138: goto          148
       141: iload         5
       143: invokestatic  #460                // Method net/minecraft/util/ARGB.white:(I)I
       146: istore        6
       148: aload_3
       149: aload_0
       150: getfield      #426                // Field overlayMessageString:Lnet/minecraft/network/chat/Component;
       153: invokevirtual #466                // Method net/minecraft/client/gui/Font.width:(Lnet/minecraft/network/chat/FormattedText;)I
       156: istore        7
       158: aload_1
       159: aload_3
       160: aload_0
       161: getfield      #426                // Field overlayMessageString:Lnet/minecraft/network/chat/Component;
       164: iload         7
       166: ineg
       167: iconst_2
       168: idiv
       169: bipush        -4
       171: iload         7
       173: iload         6
       175: invokevirtual #472                // Method net/minecraft/client/gui/GuiGraphicsExtractor.textWithBackdrop:(Lnet/minecraft/client/gui/Font;Lnet/minecraft/network/chat/Component;IIII)V
       178: aload_1
       179: invokevirtual #437                // Method net/minecraft/client/gui/GuiGraphicsExtractor.pose:()Lorg/joml/Matrix3x2fStack;
       182: invokevirtual #476                // Method org/joml/Matrix3x2fStack.popMatrix:()Lorg/joml/Matrix3x2fStack;
       185: pop
       186: invokestatic  #390                // Method net/minecraft/util/profiling/Profiler.get:()Lnet/minecraft/util/profiling/ProfilerFiller;
       189: invokeinterface #419,  1          // InterfaceMethod net/minecraft/util/profiling/ProfilerFiller.pop:()V
       194: return

  private void extractTitle(net.minecraft.client.gui.GuiGraphicsExtractor, net.minecraft.client.DeltaTracker);
    Code:
         0: aload_0
         1: getfield      #479                // Field title:Lnet/minecraft/network/chat/Component;
         4: ifnull        14
         7: aload_0
         8: getfield      #482                // Field titleTime:I
        11: ifgt          15
        14: return
        15: aload_0
        16: invokevirtual #422                // Method getFont:()Lnet/minecraft/client/gui/Font;
        19: astore_3
        20: invokestatic  #390                // Method net/minecraft/util/profiling/Profiler.get:()Lnet/minecraft/util/profiling/ProfilerFiller;
        23: ldc_w         #485                // String titleAndSubtitle
        26: invokeinterface #397,  2          // InterfaceMethod net/minecraft/util/profiling/ProfilerFiller.push:(Ljava/lang/String;)V
        31: aload_0
        32: getfield      #482                // Field titleTime:I
        35: i2f
        36: aload_2
        37: iconst_0
        38: invokeinterface #353,  2          // InterfaceMethod net/minecraft/client/DeltaTracker.getGameTimeDeltaPartialTick:(Z)F
        43: fsub
        44: fstore        4
        46: sipush        255
        49: istore        5
        51: aload_0
        52: getfield      #482                // Field titleTime:I
        55: aload_0
        56: getfield      #141                // Field titleFadeOutTime:I
        59: aload_0
        60: getfield      #138                // Field titleStayTime:I
        63: iadd
        64: if_icmple     102
        67: aload_0
        68: getfield      #134                // Field titleFadeInTime:I
        71: aload_0
        72: getfield      #138                // Field titleStayTime:I
        75: iadd
        76: aload_0
        77: getfield      #141                // Field titleFadeOutTime:I
        80: iadd
        81: i2f
        82: fload         4
        84: fsub
        85: fstore        6
        87: fload         6
        89: ldc_w         #435                // float 255.0f
        92: fmul
        93: aload_0
        94: getfield      #134                // Field titleFadeInTime:I
        97: i2f
        98: fdiv
        99: f2i
       100: istore        5
       102: aload_0
       103: getfield      #482                // Field titleTime:I
       106: aload_0
       107: getfield      #141                // Field titleFadeOutTime:I
       110: if_icmpgt     128
       113: fload         4
       115: ldc_w         #435                // float 255.0f
       118: fmul
       119: aload_0
       120: getfield      #141                // Field titleFadeOutTime:I
       123: i2f
       124: fdiv
       125: f2i
       126: istore        5
       128: iload         5
       130: iconst_0
       131: sipush        255
       134: invokestatic  #487                // Method net/minecraft/util/Mth.clamp:(III)I
       137: istore        5
       139: iload         5
       141: ifle          315
       144: aload_1
       145: invokevirtual #169                // Method net/minecraft/client/gui/GuiGraphicsExtractor.nextStratum:()V
       148: aload_1
       149: invokevirtual #437                // Method net/minecraft/client/gui/GuiGraphicsExtractor.pose:()Lorg/joml/Matrix3x2fStack;
       152: invokevirtual #441                // Method org/joml/Matrix3x2fStack.pushMatrix:()Lorg/joml/Matrix3x2fStack;
       155: pop
       156: aload_1
       157: invokevirtual #437                // Method net/minecraft/client/gui/GuiGraphicsExtractor.pose:()Lorg/joml/Matrix3x2fStack;
       160: aload_1
       161: invokevirtual #409                // Method net/minecraft/client/gui/GuiGraphicsExtractor.guiWidth:()I
       164: iconst_2
       165: idiv
       166: i2f
       167: aload_1
       168: invokevirtual #412                // Method net/minecraft/client/gui/GuiGraphicsExtractor.guiHeight:()I
       171: iconst_2
       172: idiv
       173: i2f
       174: invokevirtual #446                // Method org/joml/Matrix3x2fStack.translate:(FF)Lorg/joml/Matrix3x2f;
       177: pop
       178: aload_1
       179: invokevirtual #437                // Method net/minecraft/client/gui/GuiGraphicsExtractor.pose:()Lorg/joml/Matrix3x2fStack;
       182: invokevirtual #441                // Method org/joml/Matrix3x2fStack.pushMatrix:()Lorg/joml/Matrix3x2fStack;
       185: pop
       186: aload_1
       187: invokevirtual #437                // Method net/minecraft/client/gui/GuiGraphicsExtractor.pose:()Lorg/joml/Matrix3x2fStack;
       190: ldc_w         #491                // float 4.0f
       193: ldc_w         #491                // float 4.0f
       196: invokevirtual #492                // Method org/joml/Matrix3x2fStack.scale:(FF)Lorg/joml/Matrix3x2f;
       199: pop
       200: aload_3
       201: aload_0
       202: getfield      #479                // Field title:Lnet/minecraft/network/chat/Component;
       205: invokevirtual #466                // Method net/minecraft/client/gui/Font.width:(Lnet/minecraft/network/chat/FormattedText;)I
       208: istore        6
       210: iload         5
       212: invokestatic  #460                // Method net/minecraft/util/ARGB.white:(I)I
       215: istore        7
       217: aload_1
       218: aload_3
       219: aload_0
       220: getfield      #479                // Field title:Lnet/minecraft/network/chat/Component;
       223: iload         6
       225: ineg
       226: iconst_2
       227: idiv
       228: bipush        -10
       230: iload         6
       232: iload         7
       234: invokevirtual #472                // Method net/minecraft/client/gui/GuiGraphicsExtractor.textWithBackdrop:(Lnet/minecraft/client/gui/Font;Lnet/minecraft/network/chat/Component;IIII)V
       237: aload_1
       238: invokevirtual #437                // Method net/minecraft/client/gui/GuiGraphicsExtractor.pose:()Lorg/joml/Matrix3x2fStack;
       241: invokevirtual #476                // Method org/joml/Matrix3x2fStack.popMatrix:()Lorg/joml/Matrix3x2fStack;
       244: pop
       245: aload_0
       246: getfield      #495                // Field subtitle:Lnet/minecraft/network/chat/Component;
       249: ifnull        307
       252: aload_1
       253: invokevirtual #437                // Method net/minecraft/client/gui/GuiGraphicsExtractor.pose:()Lorg/joml/Matrix3x2fStack;
       256: invokevirtual #441                // Method org/joml/Matrix3x2fStack.pushMatrix:()Lorg/joml/Matrix3x2fStack;
       259: pop
       260: aload_1
       261: invokevirtual #437                // Method net/minecraft/client/gui/GuiGraphicsExtractor.pose:()Lorg/joml/Matrix3x2fStack;
       264: fconst_2
       265: fconst_2
       266: invokevirtual #492                // Method org/joml/Matrix3x2fStack.scale:(FF)Lorg/joml/Matrix3x2f;
       269: pop
       270: aload_3
       271: aload_0
       272: getfield      #495                // Field subtitle:Lnet/minecraft/network/chat/Component;
       275: invokevirtual #466                // Method net/minecraft/client/gui/Font.width:(Lnet/minecraft/network/chat/FormattedText;)I
       278: istore        8
       280: aload_1
       281: aload_3
       282: aload_0
       283: getfield      #495                // Field subtitle:Lnet/minecraft/network/chat/Component;
       286: iload         8
       288: ineg
       289: iconst_2
       290: idiv
       291: iconst_5
       292: iload         8
       294: iload         7
       296: invokevirtual #472                // Method net/minecraft/client/gui/GuiGraphicsExtractor.textWithBackdrop:(Lnet/minecraft/client/gui/Font;Lnet/minecraft/network/chat/Component;IIII)V
       299: aload_1
       300: invokevirtual #437                // Method net/minecraft/client/gui/GuiGraphicsExtractor.pose:()Lorg/joml/Matrix3x2fStack;
       303: invokevirtual #476                // Method org/joml/Matrix3x2fStack.popMatrix:()Lorg/joml/Matrix3x2fStack;
       306: pop
       307: aload_1
       308: invokevirtual #437                // Method net/minecraft/client/gui/GuiGraphicsExtractor.pose:()Lorg/joml/Matrix3x2fStack;
       311: invokevirtual #476                // Method org/joml/Matrix3x2fStack.popMatrix:()Lorg/joml/Matrix3x2fStack;
       314: pop
       315: invokestatic  #390                // Method net/minecraft/util/profiling/Profiler.get:()Lnet/minecraft/util/profiling/ProfilerFiller;
       318: invokeinterface #419,  1          // InterfaceMethod net/minecraft/util/profiling/ProfilerFiller.pop:()V
       323: return

  private void extractChat(net.minecraft.client.gui.GuiGraphicsExtractor, net.minecraft.client.DeltaTracker);
    Code:
         0: aload_0
         1: getfield      #54                 // Field minecraft:Lnet/minecraft/client/Minecraft;
         4: getfield      #254                // Field net/minecraft/client/Minecraft.player:Lnet/minecraft/client/player/LocalPlayer;
         7: ifnull        88
        10: aload_0
        11: getfield      #77                 // Field chat:Lnet/minecraft/client/gui/components/ChatComponent;
        14: invokevirtual #498                // Method net/minecraft/client/gui/components/ChatComponent.isChatFocused:()Z
        17: ifne          88
        20: aload_0
        21: getfield      #54                 // Field minecraft:Lnet/minecraft/client/Minecraft;
        24: invokevirtual #501                // Method net/minecraft/client/Minecraft.getWindow:()Lcom/mojang/blaze3d/platform/Window;
        27: astore_3
        28: aload_0
        29: getfield      #54                 // Field minecraft:Lnet/minecraft/client/Minecraft;
        32: getfield      #505                // Field net/minecraft/client/Minecraft.mouseHandler:Lnet/minecraft/client/MouseHandler;
        35: aload_3
        36: invokevirtual #509                // Method net/minecraft/client/MouseHandler.getScaledXPos:(Lcom/mojang/blaze3d/platform/Window;)D
        39: invokestatic  #515                // Method net/minecraft/util/Mth.floor:(D)I
        42: istore        4
        44: aload_0
        45: getfield      #54                 // Field minecraft:Lnet/minecraft/client/Minecraft;
        48: getfield      #505                // Field net/minecraft/client/Minecraft.mouseHandler:Lnet/minecraft/client/MouseHandler;
        51: aload_3
        52: invokevirtual #519                // Method net/minecraft/client/MouseHandler.getScaledYPos:(Lcom/mojang/blaze3d/platform/Window;)D
        55: invokestatic  #515                // Method net/minecraft/util/Mth.floor:(D)I
        58: istore        5
        60: aload_1
        61: invokevirtual #169                // Method net/minecraft/client/gui/GuiGraphicsExtractor.nextStratum:()V
        64: aload_0
        65: getfield      #77                 // Field chat:Lnet/minecraft/client/gui/components/ChatComponent;
        68: aload_1
        69: aload_0
        70: invokevirtual #422                // Method getFont:()Lnet/minecraft/client/gui/Font;
        73: aload_0
        74: getfield      #522                // Field tickCount:I
        77: iload         4
        79: iload         5
        81: getstatic     #525                // Field net/minecraft/client/gui/components/ChatComponent$DisplayMode.BACKGROUND:Lnet/minecraft/client/gui/components/ChatComponent$DisplayMode;
        84: iconst_0
        85: invokevirtual #531                // Method net/minecraft/client/gui/components/ChatComponent.extractRenderState:(Lnet/minecraft/client/gui/GuiGraphicsExtractor;Lnet/minecraft/client/gui/Font;IIILnet/minecraft/client/gui/components/ChatComponent$DisplayMode;Z)V
        88: return

  private void extractScoreboardSidebar(net.minecraft.client.gui.GuiGraphicsExtractor, net.minecraft.client.DeltaTracker);
    Code:
         0: aload_0
         1: getfield      #54                 // Field minecraft:Lnet/minecraft/client/Minecraft;
         4: getfield      #534                // Field net/minecraft/client/Minecraft.level:Lnet/minecraft/client/multiplayer/ClientLevel;
         7: invokevirtual #538                // Method net/minecraft/client/multiplayer/ClientLevel.getScoreboard:()Lnet/minecraft/world/scores/Scoreboard;
        10: astore_3
        11: aconst_null
        12: astore        4
        14: aload_3
        15: aload_0
        16: getfield      #54                 // Field minecraft:Lnet/minecraft/client/Minecraft;
        19: getfield      #254                // Field net/minecraft/client/Minecraft.player:Lnet/minecraft/client/player/LocalPlayer;
        22: invokevirtual #544                // Method net/minecraft/client/player/LocalPlayer.getScoreboardName:()Ljava/lang/String;
        25: invokevirtual #548                // Method net/minecraft/world/scores/Scoreboard.getPlayersTeam:(Ljava/lang/String;)Lnet/minecraft/world/scores/PlayerTeam;
        28: astore        5
        30: aload         5
        32: ifnull        58
        35: aload         5
        37: invokevirtual #554                // Method net/minecraft/world/scores/PlayerTeam.getColor:()Lnet/minecraft/ChatFormatting;
        40: invokestatic  #560                // Method net/minecraft/world/scores/DisplaySlot.teamColorToSlot:(Lnet/minecraft/ChatFormatting;)Lnet/minecraft/world/scores/DisplaySlot;
        43: astore        6
        45: aload         6
        47: ifnull        58
        50: aload_3
        51: aload         6
        53: invokevirtual #566                // Method net/minecraft/world/scores/Scoreboard.getDisplayObjective:(Lnet/minecraft/world/scores/DisplaySlot;)Lnet/minecraft/world/scores/Objective;
        56: astore        4
        58: aload         4
        60: ifnull        68
        63: aload         4
        65: goto          75
        68: aload_3
        69: getstatic     #570                // Field net/minecraft/world/scores/DisplaySlot.SIDEBAR:Lnet/minecraft/world/scores/DisplaySlot;
        72: invokevirtual #566                // Method net/minecraft/world/scores/Scoreboard.getDisplayObjective:(Lnet/minecraft/world/scores/DisplaySlot;)Lnet/minecraft/world/scores/Objective;
        75: astore        6
        77: aload         6
        79: ifnull        93
        82: aload_1
        83: invokevirtual #169                // Method net/minecraft/client/gui/GuiGraphicsExtractor.nextStratum:()V
        86: aload_0
        87: aload_1
        88: aload         6
        90: invokevirtual #574                // Method displayScoreboardSidebar:(Lnet/minecraft/client/gui/GuiGraphicsExtractor;Lnet/minecraft/world/scores/Objective;)V
        93: return

  private void extractTabList(net.minecraft.client.gui.GuiGraphicsExtractor, net.minecraft.client.DeltaTracker);
    Code:
         0: aload_0
         1: getfield      #54                 // Field minecraft:Lnet/minecraft/client/Minecraft;
         4: getfield      #534                // Field net/minecraft/client/Minecraft.level:Lnet/minecraft/client/multiplayer/ClientLevel;
         7: invokevirtual #538                // Method net/minecraft/client/multiplayer/ClientLevel.getScoreboard:()Lnet/minecraft/world/scores/Scoreboard;
        10: astore_3
        11: aload_3
        12: getstatic     #578                // Field net/minecraft/world/scores/DisplaySlot.LIST:Lnet/minecraft/world/scores/DisplaySlot;
        15: invokevirtual #566                // Method net/minecraft/world/scores/Scoreboard.getDisplayObjective:(Lnet/minecraft/world/scores/DisplaySlot;)Lnet/minecraft/world/scores/Objective;
        18: astore        4
        20: aload_0
        21: getfield      #54                 // Field minecraft:Lnet/minecraft/client/Minecraft;
        24: getfield      #152                // Field net/minecraft/client/Minecraft.options:Lnet/minecraft/client/Options;
        27: getfield      #581                // Field net/minecraft/client/Options.keyPlayerList:Lnet/minecraft/client/KeyMapping;
        30: invokevirtual #585                // Method net/minecraft/client/KeyMapping.isDown:()Z
        33: ifeq          103
        36: aload_0
        37: getfield      #54                 // Field minecraft:Lnet/minecraft/client/Minecraft;
        40: invokevirtual #590                // Method net/minecraft/client/Minecraft.isLocalServer:()Z
        43: ifeq          73
        46: aload_0
        47: getfield      #54                 // Field minecraft:Lnet/minecraft/client/Minecraft;
        50: getfield      #254                // Field net/minecraft/client/Minecraft.player:Lnet/minecraft/client/player/LocalPlayer;
        53: getfield      #593                // Field net/minecraft/client/player/LocalPlayer.connection:Lnet/minecraft/client/multiplayer/ClientPacketListener;
        56: invokevirtual #597                // Method net/minecraft/client/multiplayer/ClientPacketListener.getListedOnlinePlayers:()Ljava/util/Collection;
        59: invokeinterface #603,  1          // InterfaceMethod java/util/Collection.size:()I
        64: iconst_1
        65: if_icmpgt     73
        68: aload         4
        70: ifnull        103
        73: aload_0
        74: getfield      #86                 // Field tabList:Lnet/minecraft/client/gui/components/PlayerTabOverlay;
        77: iconst_1
        78: invokevirtual #608                // Method net/minecraft/client/gui/components/PlayerTabOverlay.setVisible:(Z)V
        81: aload_1
        82: invokevirtual #169                // Method net/minecraft/client/gui/GuiGraphicsExtractor.nextStratum:()V
        85: aload_0
        86: getfield      #86                 // Field tabList:Lnet/minecraft/client/gui/components/PlayerTabOverlay;
        89: aload_1
        90: aload_1
        91: invokevirtual #409                // Method net/minecraft/client/gui/GuiGraphicsExtractor.guiWidth:()I
        94: aload_3
        95: aload         4
        97: invokevirtual #612                // Method net/minecraft/client/gui/components/PlayerTabOverlay.extractRenderState:(Lnet/minecraft/client/gui/GuiGraphicsExtractor;ILnet/minecraft/world/scores/Scoreboard;Lnet/minecraft/world/scores/Objective;)V
       100: goto          111
       103: aload_0
       104: getfield      #86                 // Field tabList:Lnet/minecraft/client/gui/components/PlayerTabOverlay;
       107: iconst_0
       108: invokevirtual #608                // Method net/minecraft/client/gui/components/PlayerTabOverlay.setVisible:(Z)V
       111: return

  private void extractCrosshair(net.minecraft.client.gui.GuiGraphicsExtractor, net.minecraft.client.DeltaTracker);
    Code:
         0: aload_0
         1: getfield      #54                 // Field minecraft:Lnet/minecraft/client/Minecraft;
         4: getfield      #152                // Field net/minecraft/client/Minecraft.options:Lnet/minecraft/client/Options;
         7: astore_3
         8: aload_3
         9: invokevirtual #275                // Method net/minecraft/client/Options.getCameraType:()Lnet/minecraft/client/CameraType;
        12: invokevirtual #279                // Method net/minecraft/client/CameraType.isFirstPerson:()Z
        15: ifne          19
        18: return
        19: aload_0
        20: getfield      #54                 // Field minecraft:Lnet/minecraft/client/Minecraft;
        23: getfield      #615                // Field net/minecraft/client/Minecraft.gameMode:Lnet/minecraft/client/multiplayer/MultiPlayerGameMode;
        26: invokevirtual #619                // Method net/minecraft/client/multiplayer/MultiPlayerGameMode.getPlayerMode:()Lnet/minecraft/world/level/GameType;
        29: getstatic     #625                // Field net/minecraft/world/level/GameType.SPECTATOR:Lnet/minecraft/world/level/GameType;
        32: if_acmpne     50
        35: aload_0
        36: aload_0
        37: getfield      #54                 // Field minecraft:Lnet/minecraft/client/Minecraft;
        40: getfield      #631                // Field net/minecraft/client/Minecraft.hitResult:Lnet/minecraft/world/phys/HitResult;
        43: invokevirtual #635                // Method canRenderCrosshairForSpectator:(Lnet/minecraft/world/phys/HitResult;)Z
        46: ifne          50
        49: return
        50: aload_0
        51: getfield      #54                 // Field minecraft:Lnet/minecraft/client/Minecraft;
        54: getfield      #639                // Field net/minecraft/client/Minecraft.debugEntries:Lnet/minecraft/client/gui/components/debug/DebugScreenEntryList;
        57: getstatic     #643                // Field net/minecraft/client/gui/components/debug/DebugScreenEntries.THREE_DIMENSIONAL_CROSSHAIR:Lnet/minecraft/resources/Identifier;
        60: invokevirtual #648                // Method net/minecraft/client/gui/components/debug/DebugScreenEntryList.isCurrentlyEnabled:(Lnet/minecraft/resources/Identifier;)Z
        63: ifne          377
        66: aload_1
        67: invokevirtual #169                // Method net/minecraft/client/gui/GuiGraphicsExtractor.nextStratum:()V
        70: bipush        15
        72: istore        4
        74: aload_1
        75: getstatic     #654                // Field net/minecraft/client/renderer/RenderPipelines.CROSSHAIR:Lcom/mojang/blaze3d/pipeline/RenderPipeline;
        78: getstatic     #660                // Field CROSSHAIR_SPRITE:Lnet/minecraft/resources/Identifier;
        81: aload_1
        82: invokevirtual #409                // Method net/minecraft/client/gui/GuiGraphicsExtractor.guiWidth:()I
        85: bipush        15
        87: isub
        88: iconst_2
        89: idiv
        90: aload_1
        91: invokevirtual #412                // Method net/minecraft/client/gui/GuiGraphicsExtractor.guiHeight:()I
        94: bipush        15
        96: isub
        97: iconst_2
        98: idiv
        99: bipush        15
       101: bipush        15
       103: invokevirtual #663                // Method net/minecraft/client/gui/GuiGraphicsExtractor.blitSprite:(Lcom/mojang/blaze3d/pipeline/RenderPipeline;Lnet/minecraft/resources/Identifier;IIII)V
       106: aload_0
       107: getfield      #54                 // Field minecraft:Lnet/minecraft/client/Minecraft;
       110: getfield      #152                // Field net/minecraft/client/Minecraft.options:Lnet/minecraft/client/Options;
       113: invokevirtual #667                // Method net/minecraft/client/Options.attackIndicator:()Lnet/minecraft/client/OptionInstance;
       116: invokevirtual #236                // Method net/minecraft/client/OptionInstance.get:()Ljava/lang/Object;
       119: getstatic     #670                // Field net/minecraft/client/AttackIndicatorStatus.CROSSHAIR:Lnet/minecraft/client/AttackIndicatorStatus;
       122: if_acmpne     377
       125: aload_0
       126: getfield      #54                 // Field minecraft:Lnet/minecraft/client/Minecraft;
       129: getfield      #254                // Field net/minecraft/client/Minecraft.player:Lnet/minecraft/client/player/LocalPlayer;
       132: fconst_0
       133: invokevirtual #675                // Method net/minecraft/client/player/LocalPlayer.getAttackStrengthScale:(F)F
       136: fstore        5
       138: iconst_0
       139: istore        6
       141: aload_0
       142: getfield      #54                 // Field minecraft:Lnet/minecraft/client/Minecraft;
       145: getfield      #679                // Field net/minecraft/client/Minecraft.crosshairPickEntity:Lnet/minecraft/world/entity/Entity;
       148: ifnull        271
       151: aload_0
       152: getfield      #54                 // Field minecraft:Lnet/minecraft/client/Minecraft;
       155: getfield      #679                // Field net/minecraft/client/Minecraft.crosshairPickEntity:Lnet/minecraft/world/entity/Entity;
       158: instanceof    #683                // class net/minecraft/world/entity/LivingEntity
       161: ifeq          271
       164: fload         5
       166: fconst_1
       167: fcmpl
       168: iflt          271
       171: aload_0
       172: getfield      #54                 // Field minecraft:Lnet/minecraft/client/Minecraft;
       175: getfield      #254                // Field net/minecraft/client/Minecraft.player:Lnet/minecraft/client/player/LocalPlayer;
       178: invokevirtual #685                // Method net/minecraft/client/player/LocalPlayer.getCurrentItemAttackStrengthDelay:()F
       181: ldc_w         #688                // float 5.0f
       184: fcmpl
       185: ifle          192
       188: iconst_1
       189: goto          193
       192: iconst_0
       193: istore        6
       195: iload         6
       197: aload_0
       198: getfield      #54                 // Field minecraft:Lnet/minecraft/client/Minecraft;
       201: getfield      #679                // Field net/minecraft/client/Minecraft.crosshairPickEntity:Lnet/minecraft/world/entity/Entity;
       204: invokevirtual #689                // Method net/minecraft/world/entity/Entity.isAlive:()Z
       207: iand
       208: istore        6
       210: aload_0
       211: getfield      #54                 // Field minecraft:Lnet/minecraft/client/Minecraft;
       214: getfield      #254                // Field net/minecraft/client/Minecraft.player:Lnet/minecraft/client/player/LocalPlayer;
       217: invokevirtual #694                // Method net/minecraft/client/player/LocalPlayer.getActiveItem:()Lnet/minecraft/world/item/ItemStack;
       220: getstatic     #698                // Field net/minecraft/core/component/DataComponents.ATTACK_RANGE:Lnet/minecraft/core/component/DataComponentType;
       223: invokevirtual #309                // Method net/minecraft/world/item/ItemStack.get:(Lnet/minecraft/core/component/DataComponentType;)Ljava/lang/Object;
       226: checkcast     #701                // class net/minecraft/world/item/component/AttackRange
       229: astore        7
       231: iload         6
       233: aload         7
       235: ifnull        263
       238: aload         7
       240: aload_0
       241: getfield      #54                 // Field minecraft:Lnet/minecraft/client/Minecraft;
       244: getfield      #254                // Field net/minecraft/client/Minecraft.player:Lnet/minecraft/client/player/LocalPlayer;
       247: aload_0
       248: getfield      #54                 // Field minecraft:Lnet/minecraft/client/Minecraft;
       251: getfield      #631                // Field net/minecraft/client/Minecraft.hitResult:Lnet/minecraft/world/phys/HitResult;
       254: invokevirtual #703                // Method net/minecraft/world/phys/HitResult.getLocation:()Lnet/minecraft/world/phys/Vec3;
       257: invokevirtual #709                // Method net/minecraft/world/item/component/AttackRange.isInRange:(Lnet/minecraft/world/entity/LivingEntity;Lnet/minecraft/world/phys/Vec3;)Z
       260: ifeq          267
       263: iconst_1
       264: goto          268
       267: iconst_0
       268: iand
       269: istore        6
       271: aload_1
       272: invokevirtual #412                // Method net/minecraft/client/gui/GuiGraphicsExtractor.guiHeight:()I
       275: iconst_2
       276: idiv
       277: bipush        7
       279: isub
       280: bipush        16
       282: iadd
       283: istore        7
       285: aload_1
       286: invokevirtual #409                // Method net/minecraft/client/gui/GuiGraphicsExtractor.guiWidth:()I
       289: iconst_2
       290: idiv
       291: bipush        8
       293: isub
       294: istore        8
       296: iload         6
       298: ifeq          322
       301: aload_1
       302: getstatic     #654                // Field net/minecraft/client/renderer/RenderPipelines.CROSSHAIR:Lcom/mojang/blaze3d/pipeline/RenderPipeline;
       305: getstatic     #713                // Field CROSSHAIR_ATTACK_INDICATOR_FULL_SPRITE:Lnet/minecraft/resources/Identifier;
       308: iload         8
       310: iload         7
       312: bipush        16
       314: bipush        16
       316: invokevirtual #663                // Method net/minecraft/client/gui/GuiGraphicsExtractor.blitSprite:(Lcom/mojang/blaze3d/pipeline/RenderPipeline;Lnet/minecraft/resources/Identifier;IIII)V
       319: goto          377
       322: fload         5
       324: fconst_1
       325: fcmpg
       326: ifge          377
       329: fload         5
       331: ldc_w         #716                // float 17.0f
       334: fmul
       335: f2i
       336: istore        9
       338: aload_1
       339: getstatic     #654                // Field net/minecraft/client/renderer/RenderPipelines.CROSSHAIR:Lcom/mojang/blaze3d/pipeline/RenderPipeline;
       342: getstatic     #717                // Field CROSSHAIR_ATTACK_INDICATOR_BACKGROUND_SPRITE:Lnet/minecraft/resources/Identifier;
       345: iload         8
       347: iload         7
       349: bipush        16
       351: iconst_4
       352: invokevirtual #663                // Method net/minecraft/client/gui/GuiGraphicsExtractor.blitSprite:(Lcom/mojang/blaze3d/pipeline/RenderPipeline;Lnet/minecraft/resources/Identifier;IIII)V
       355: aload_1
       356: getstatic     #654                // Field net/minecraft/client/renderer/RenderPipelines.CROSSHAIR:Lcom/mojang/blaze3d/pipeline/RenderPipeline;
       359: getstatic     #720                // Field CROSSHAIR_ATTACK_INDICATOR_PROGRESS_SPRITE:Lnet/minecraft/resources/Identifier;
       362: bipush        16
       364: iconst_4
       365: iconst_0
       366: iconst_0
       367: iload         8
       369: iload         7
       371: iload         9
       373: iconst_4
       374: invokevirtual #723                // Method net/minecraft/client/gui/GuiGraphicsExtractor.blitSprite:(Lcom/mojang/blaze3d/pipeline/RenderPipeline;Lnet/minecraft/resources/Identifier;IIIIIIII)V
       377: return

  private boolean canRenderCrosshairForSpectator(net.minecraft.world.phys.HitResult);
    Code:
         0: aload_1
         1: ifnonnull     6
         4: iconst_0
         5: ireturn
         6: aload_1
         7: invokevirtual #726                // Method net/minecraft/world/phys/HitResult.getType:()Lnet/minecraft/world/phys/HitResult$Type;
        10: getstatic     #730                // Field net/minecraft/world/phys/HitResult$Type.ENTITY:Lnet/minecraft/world/phys/HitResult$Type;
        13: if_acmpne     27
        16: aload_1
        17: checkcast     #736                // class net/minecraft/world/phys/EntityHitResult
        20: invokevirtual #738                // Method net/minecraft/world/phys/EntityHitResult.getEntity:()Lnet/minecraft/world/entity/Entity;
        23: instanceof    #741                // class net/minecraft/world/MenuProvider
        26: ireturn
        27: aload_1
        28: invokevirtual #726                // Method net/minecraft/world/phys/HitResult.getType:()Lnet/minecraft/world/phys/HitResult$Type;
        31: getstatic     #743                // Field net/minecraft/world/phys/HitResult$Type.BLOCK:Lnet/minecraft/world/phys/HitResult$Type;
        34: if_acmpne     72
        37: aload_1
        38: checkcast     #746                // class net/minecraft/world/phys/BlockHitResult
        41: invokevirtual #748                // Method net/minecraft/world/phys/BlockHitResult.getBlockPos:()Lnet/minecraft/core/BlockPos;
        44: astore_2
        45: aload_0
        46: getfield      #54                 // Field minecraft:Lnet/minecraft/client/Minecraft;
        49: getfield      #534                // Field net/minecraft/client/Minecraft.level:Lnet/minecraft/client/multiplayer/ClientLevel;
        52: astore_3
        53: aload_3
        54: aload_2
        55: invokevirtual #752                // Method net/minecraft/world/level/Level.getBlockState:(Lnet/minecraft/core/BlockPos;)Lnet/minecraft/world/level/block/state/BlockState;
        58: aload_3
        59: aload_2
        60: invokevirtual #758                // Method net/minecraft/world/level/block/state/BlockState.getMenuProvider:(Lnet/minecraft/world/level/Level;Lnet/minecraft/core/BlockPos;)Lnet/minecraft/world/MenuProvider;
        63: ifnull        70
        66: iconst_1
        67: goto          71
        70: iconst_0
        71: ireturn
        72: iconst_0
        73: ireturn

  private void extractEffects(net.minecraft.client.gui.GuiGraphicsExtractor, net.minecraft.client.DeltaTracker);
    Code:
         0: aload_0
         1: getfield      #54                 // Field minecraft:Lnet/minecraft/client/Minecraft;
         4: getfield      #254                // Field net/minecraft/client/Minecraft.player:Lnet/minecraft/client/player/LocalPlayer;
         7: invokevirtual #764                // Method net/minecraft/client/player/LocalPlayer.getActiveEffects:()Ljava/util/Collection;
        10: astore_3
        11: aload_3
        12: invokeinterface #767,  1          // InterfaceMethod java/util/Collection.isEmpty:()Z
        17: ifne          43
        20: aload_0
        21: getfield      #54                 // Field minecraft:Lnet/minecraft/client/Minecraft;
        24: getfield      #144                // Field net/minecraft/client/Minecraft.screen:Lnet/minecraft/client/gui/screens/Screen;
        27: ifnull        44
        30: aload_0
        31: getfield      #54                 // Field minecraft:Lnet/minecraft/client/Minecraft;
        34: getfield      #144                // Field net/minecraft/client/Minecraft.screen:Lnet/minecraft/client/gui/screens/Screen;
        37: invokevirtual #770                // Method net/minecraft/client/gui/screens/Screen.showsActiveEffects:()Z
        40: ifeq          44
        43: return
        44: iconst_0
        45: istore        4
        47: iconst_0
        48: istore        5
        50: invokestatic  #773                // Method com/google/common/collect/Ordering.natural:()Lcom/google/common/collect/Ordering;
        53: invokevirtual #779                // Method com/google/common/collect/Ordering.reverse:()Lcom/google/common/collect/Ordering;
        56: aload_3
        57: invokevirtual #782                // Method com/google/common/collect/Ordering.sortedCopy:(Ljava/lang/Iterable;)Ljava/util/List;
        60: invokeinterface #786,  1          // InterfaceMethod java/util/List.iterator:()Ljava/util/Iterator;
        65: astore        6
        67: aload         6
        69: invokeinterface #792,  1          // InterfaceMethod java/util/Iterator.hasNext:()Z
        74: ifeq          352
        77: aload         6
        79: invokeinterface #797,  1          // InterfaceMethod java/util/Iterator.next:()Ljava/lang/Object;
        84: checkcast     #800                // class net/minecraft/world/effect/MobEffectInstance
        87: astore        7
        89: aload         7
        91: invokevirtual #802                // Method net/minecraft/world/effect/MobEffectInstance.getEffect:()Lnet/minecraft/core/Holder;
        94: astore        8
        96: aload         7
        98: invokevirtual #806                // Method net/minecraft/world/effect/MobEffectInstance.showIcon:()Z
       101: ifeq          349
       104: aload_1
       105: invokevirtual #409                // Method net/minecraft/client/gui/GuiGraphicsExtractor.guiWidth:()I
       108: istore        9
       110: iconst_1
       111: istore        10
       113: aload_0
       114: getfield      #54                 // Field minecraft:Lnet/minecraft/client/Minecraft;
       117: invokevirtual #809                // Method net/minecraft/client/Minecraft.isDemo:()Z
       120: ifeq          126
       123: iinc          10, 15
       126: aload         8
       128: invokeinterface #812,  1          // InterfaceMethod net/minecraft/core/Holder.value:()Ljava/lang/Object;
       133: checkcast     #817                // class net/minecraft/world/effect/MobEffect
       136: invokevirtual #819                // Method net/minecraft/world/effect/MobEffect.isBeneficial:()Z
       139: ifeq          158
       142: iinc          4, 1
       145: iload         9
       147: bipush        25
       149: iload         4
       151: imul
       152: isub
       153: istore        9
       155: goto          174
       158: iinc          5, 1
       161: iload         9
       163: bipush        25
       165: iload         5
       167: imul
       168: isub
       169: istore        9
       171: iinc          10, 26
       174: fconst_1
       175: fstore        11
       177: aload         7
       179: invokevirtual #822                // Method net/minecraft/world/effect/MobEffectInstance.isAmbient:()Z
       182: ifeq          206
       185: aload_1
       186: getstatic     #825                // Field net/minecraft/client/renderer/RenderPipelines.GUI_TEXTURED:Lcom/mojang/blaze3d/pipeline/RenderPipeline;
       189: getstatic     #828                // Field EFFECT_BACKGROUND_AMBIENT_SPRITE:Lnet/minecraft/resources/Identifier;
       192: iload         9
       194: iload         10
       196: bipush        24
       198: bipush        24
       200: invokevirtual #663                // Method net/minecraft/client/gui/GuiGraphicsExtractor.blitSprite:(Lcom/mojang/blaze3d/pipeline/RenderPipeline;Lnet/minecraft/resources/Identifier;IIII)V
       203: goto          320
       206: aload_1
       207: getstatic     #825                // Field net/minecraft/client/renderer/RenderPipelines.GUI_TEXTURED:Lcom/mojang/blaze3d/pipeline/RenderPipeline;
       210: getstatic     #831                // Field EFFECT_BACKGROUND_SPRITE:Lnet/minecraft/resources/Identifier;
       213: iload         9
       215: iload         10
       217: bipush        24
       219: bipush        24
       221: invokevirtual #663                // Method net/minecraft/client/gui/GuiGraphicsExtractor.blitSprite:(Lcom/mojang/blaze3d/pipeline/RenderPipeline;Lnet/minecraft/resources/Identifier;IIII)V
       224: aload         7
       226: sipush        200
       229: invokevirtual #834                // Method net/minecraft/world/effect/MobEffectInstance.endsWithin:(I)Z
       232: ifeq          320
       235: aload         7
       237: invokevirtual #838                // Method net/minecraft/world/effect/MobEffectInstance.getDuration:()I
       240: istore        12
       242: bipush        10
       244: iload         12
       246: bipush        20
       248: idiv
       249: isub
       250: istore        13
       252: iload         12
       254: i2f
       255: ldc_w         #406                // float 10.0f
       258: fdiv
       259: ldc_w         #688                // float 5.0f
       262: fdiv
       263: ldc_w         #264                // float 0.5f
       266: fmul
       267: fconst_0
       268: ldc_w         #264                // float 0.5f
       271: invokestatic  #841                // Method net/minecraft/util/Mth.clamp:(FFF)F
       274: iload         12
       276: i2f
       277: ldc_w         #843                // float 3.1415927f
       280: fmul
       281: ldc_w         #688                // float 5.0f
       284: fdiv
       285: f2d
       286: invokestatic  #844                // Method net/minecraft/util/Mth.cos:(D)F
       289: iload         13
       291: i2f
       292: ldc_w         #406                // float 10.0f
       295: fdiv
       296: ldc_w         #848                // float 0.25f
       299: fmul
       300: fconst_0
       301: ldc_w         #848                // float 0.25f
       304: invokestatic  #841                // Method net/minecraft/util/Mth.clamp:(FFF)F
       307: fmul
       308: fadd
       309: fstore        11
       311: fload         11
       313: fconst_0
       314: fconst_1
       315: invokestatic  #841                // Method net/minecraft/util/Mth.clamp:(FFF)F
       318: fstore        11
       320: aload_1
       321: getstatic     #825                // Field net/minecraft/client/renderer/RenderPipelines.GUI_TEXTURED:Lcom/mojang/blaze3d/pipeline/RenderPipeline;
       324: aload         8
       326: invokestatic  #849                // Method getMobEffectSprite:(Lnet/minecraft/core/Holder;)Lnet/minecraft/resources/Identifier;
       329: iload         9
       331: iconst_3
       332: iadd
       333: iload         10
       335: iconst_3
       336: iadd
       337: bipush        18
       339: bipush        18
       341: fload         11
       343: invokestatic  #853                // Method net/minecraft/util/ARGB.white:(F)I
       346: invokevirtual #856                // Method net/minecraft/client/gui/GuiGraphicsExtractor.blitSprite:(Lcom/mojang/blaze3d/pipeline/RenderPipeline;Lnet/minecraft/resources/Identifier;IIIII)V
       349: goto          67
       352: return

  public static net.minecraft.resources.Identifier getMobEffectSprite(net.minecraft.core.Holder<net.minecraft.world.effect.MobEffect>);
    Code:
         0: aload_0
         1: invokeinterface #859,  1          // InterfaceMethod net/minecraft/core/Holder.unwrapKey:()Ljava/util/Optional;
         6: invokedynamic #862,  0            // InvokeDynamic #6:apply:()Ljava/util/function/Function;
        11: invokevirtual #865                // Method java/util/Optional.map:(Ljava/util/function/Function;)Ljava/util/Optional;
        14: invokedynamic #869,  0            // InvokeDynamic #7:apply:()Ljava/util/function/Function;
        19: invokevirtual #865                // Method java/util/Optional.map:(Ljava/util/function/Function;)Ljava/util/Optional;
        22: invokedynamic #870,  0            // InvokeDynamic #8:get:()Ljava/util/function/Supplier;
        27: invokevirtual #871                // Method java/util/Optional.orElseGet:(Ljava/util/function/Supplier;)Ljava/lang/Object;
        30: checkcast     #328                // class net/minecraft/resources/Identifier
        33: areturn

  private void extractHotbarAndDecorations(net.minecraft.client.gui.GuiGraphicsExtractor, net.minecraft.client.DeltaTracker);
    Code:
         0: aload_0
         1: getfield      #54                 // Field minecraft:Lnet/minecraft/client/Minecraft;
         4: getfield      #615                // Field net/minecraft/client/Minecraft.gameMode:Lnet/minecraft/client/multiplayer/MultiPlayerGameMode;
         7: invokevirtual #619                // Method net/minecraft/client/multiplayer/MultiPlayerGameMode.getPlayerMode:()Lnet/minecraft/world/level/GameType;
        10: getstatic     #625                // Field net/minecraft/world/level/GameType.SPECTATOR:Lnet/minecraft/world/level/GameType;
        13: if_acmpne     27
        16: aload_0
        17: getfield      #70                 // Field spectatorGui:Lnet/minecraft/client/gui/components/spectator/SpectatorGui;
        20: aload_1
        21: invokevirtual #875                // Method net/minecraft/client/gui/components/spectator/SpectatorGui.extractHotbar:(Lnet/minecraft/client/gui/GuiGraphicsExtractor;)V
        24: goto          33
        27: aload_0
        28: aload_1
        29: aload_2
        30: invokevirtual #878                // Method extractItemHotbar:(Lnet/minecraft/client/gui/GuiGraphicsExtractor;Lnet/minecraft/client/DeltaTracker;)V
        33: aload_0
        34: getfield      #54                 // Field minecraft:Lnet/minecraft/client/Minecraft;
        37: getfield      #615                // Field net/minecraft/client/Minecraft.gameMode:Lnet/minecraft/client/multiplayer/MultiPlayerGameMode;
        40: invokevirtual #881                // Method net/minecraft/client/multiplayer/MultiPlayerGameMode.canHurtPlayer:()Z
        43: ifeq          51
        46: aload_0
        47: aload_1
        48: invokevirtual #884                // Method extractPlayerHealth:(Lnet/minecraft/client/gui/GuiGraphicsExtractor;)V
        51: aload_0
        52: aload_1
        53: invokevirtual #887                // Method extractVehicleHealth:(Lnet/minecraft/client/gui/GuiGraphicsExtractor;)V
        56: aload_0
        57: invokevirtual #890                // Method nextContextualInfoState:()Lnet/minecraft/client/gui/Gui$ContextualInfo;
        60: astore_3
        61: aload_3
        62: aload_0
        63: getfield      #50                 // Field contextualInfoBar:Lorg/apache/commons/lang3/tuple/Pair;
        66: invokevirtual #894                // Method org/apache/commons/lang3/tuple/Pair.getKey:()Ljava/lang/Object;
        69: if_acmpeq     101
        72: aload_0
        73: aload_3
        74: aload_0
        75: getfield      #127                // Field contextualInfoBarRenderers:Ljava/util/Map;
        78: aload_3
        79: invokeinterface #897,  2          // InterfaceMethod java/util/Map.get:(Ljava/lang/Object;)Ljava/lang/Object;
        84: checkcast     #902                // class java/util/function/Supplier
        87: invokeinterface #904,  1          // InterfaceMethod java/util/function/Supplier.get:()Ljava/lang/Object;
        92: checkcast     #40                 // class net/minecraft/client/gui/contextualbar/ContextualBarRenderer
        95: invokestatic  #44                 // Method org/apache/commons/lang3/tuple/Pair.of:(Ljava/lang/Object;Ljava/lang/Object;)Lorg/apache/commons/lang3/tuple/Pair;
        98: putfield      #50                 // Field contextualInfoBar:Lorg/apache/commons/lang3/tuple/Pair;
       101: aload_0
       102: getfield      #50                 // Field contextualInfoBar:Lorg/apache/commons/lang3/tuple/Pair;
       105: invokevirtual #905                // Method org/apache/commons/lang3/tuple/Pair.getValue:()Ljava/lang/Object;
       108: checkcast     #40                 // class net/minecraft/client/gui/contextualbar/ContextualBarRenderer
       111: aload_1
       112: aload_2
       113: invokeinterface #908,  3          // InterfaceMethod net/minecraft/client/gui/contextualbar/ContextualBarRenderer.extractBackground:(Lnet/minecraft/client/gui/GuiGraphicsExtractor;Lnet/minecraft/client/DeltaTracker;)V
       118: aload_0
       119: getfield      #54                 // Field minecraft:Lnet/minecraft/client/Minecraft;
       122: getfield      #615                // Field net/minecraft/client/Minecraft.gameMode:Lnet/minecraft/client/multiplayer/MultiPlayerGameMode;
       125: invokevirtual #911                // Method net/minecraft/client/multiplayer/MultiPlayerGameMode.hasExperience:()Z
       128: ifeq          165
       131: aload_0
       132: getfield      #54                 // Field minecraft:Lnet/minecraft/client/Minecraft;
       135: getfield      #254                // Field net/minecraft/client/Minecraft.player:Lnet/minecraft/client/player/LocalPlayer;
       138: getfield      #914                // Field net/minecraft/client/player/LocalPlayer.experienceLevel:I
       141: ifle          165
       144: aload_1
       145: aload_0
       146: getfield      #54                 // Field minecraft:Lnet/minecraft/client/Minecraft;
       149: getfield      #917                // Field net/minecraft/client/Minecraft.font:Lnet/minecraft/client/gui/Font;
       152: aload_0
       153: getfield      #54                 // Field minecraft:Lnet/minecraft/client/Minecraft;
       156: getfield      #254                // Field net/minecraft/client/Minecraft.player:Lnet/minecraft/client/player/LocalPlayer;
       159: getfield      #914                // Field net/minecraft/client/player/LocalPlayer.experienceLevel:I
       162: invokestatic  #921                // InterfaceMethod net/minecraft/client/gui/contextualbar/ContextualBarRenderer.extractExperienceLevel:(Lnet/minecraft/client/gui/GuiGraphicsExtractor;Lnet/minecraft/client/gui/Font;I)V
       165: aload_0
       166: getfield      #50                 // Field contextualInfoBar:Lorg/apache/commons/lang3/tuple/Pair;
       169: invokevirtual #905                // Method org/apache/commons/lang3/tuple/Pair.getValue:()Ljava/lang/Object;
       172: checkcast     #40                 // class net/minecraft/client/gui/contextualbar/ContextualBarRenderer
       175: aload_1
       176: aload_2
       177: invokeinterface #925,  3          // InterfaceMethod net/minecraft/client/gui/contextualbar/ContextualBarRenderer.extractRenderState:(Lnet/minecraft/client/gui/GuiGraphicsExtractor;Lnet/minecraft/client/DeltaTracker;)V
       182: aload_0
       183: getfield      #54                 // Field minecraft:Lnet/minecraft/client/Minecraft;
       186: getfield      #615                // Field net/minecraft/client/Minecraft.gameMode:Lnet/minecraft/client/multiplayer/MultiPlayerGameMode;
       189: invokevirtual #619                // Method net/minecraft/client/multiplayer/MultiPlayerGameMode.getPlayerMode:()Lnet/minecraft/world/level/GameType;
       192: getstatic     #625                // Field net/minecraft/world/level/GameType.SPECTATOR:Lnet/minecraft/world/level/GameType;
       195: if_acmpeq     206
       198: aload_0
       199: aload_1
       200: invokevirtual #927                // Method extractSelectedItemName:(Lnet/minecraft/client/gui/GuiGraphicsExtractor;)V
       203: goto          227
       206: aload_0
       207: getfield      #54                 // Field minecraft:Lnet/minecraft/client/Minecraft;
       210: getfield      #254                // Field net/minecraft/client/Minecraft.player:Lnet/minecraft/client/player/LocalPlayer;
       213: invokevirtual #930                // Method net/minecraft/client/player/LocalPlayer.isSpectator:()Z
       216: ifeq          227
       219: aload_0
       220: getfield      #70                 // Field spectatorGui:Lnet/minecraft/client/gui/components/spectator/SpectatorGui;
       223: aload_1
       224: invokevirtual #933                // Method net/minecraft/client/gui/components/spectator/SpectatorGui.extractAction:(Lnet/minecraft/client/gui/GuiGraphicsExtractor;)V
       227: return

  private void extractItemHotbar(net.minecraft.client.gui.GuiGraphicsExtractor, net.minecraft.client.DeltaTracker);
    Code:
         0: aload_0
         1: invokevirtual #936                // Method getCameraPlayer:()Lnet/minecraft/world/entity/player/Player;
         4: astore_3
         5: aload_3
         6: ifnonnull     10
         9: return
        10: aload_3
        11: invokevirtual #940                // Method net/minecraft/world/entity/player/Player.getOffhandItem:()Lnet/minecraft/world/item/ItemStack;
        14: astore        4
        16: aload_3
        17: invokevirtual #943                // Method net/minecraft/world/entity/player/Player.getMainArm:()Lnet/minecraft/world/entity/HumanoidArm;
        20: invokevirtual #947                // Method net/minecraft/world/entity/HumanoidArm.getOpposite:()Lnet/minecraft/world/entity/HumanoidArm;
        23: astore        5
        25: aload_1
        26: invokevirtual #409                // Method net/minecraft/client/gui/GuiGraphicsExtractor.guiWidth:()I
        29: iconst_2
        30: idiv
        31: istore        6
        33: sipush        182
        36: istore        7
        38: bipush        91
        40: istore        8
        42: aload_1
        43: getstatic     #825                // Field net/minecraft/client/renderer/RenderPipelines.GUI_TEXTURED:Lcom/mojang/blaze3d/pipeline/RenderPipeline;
        46: getstatic     #952                // Field HOTBAR_SPRITE:Lnet/minecraft/resources/Identifier;
        49: iload         6
        51: bipush        91
        53: isub
        54: aload_1
        55: invokevirtual #412                // Method net/minecraft/client/gui/GuiGraphicsExtractor.guiHeight:()I
        58: bipush        22
        60: isub
        61: sipush        182
        64: bipush        22
        66: invokevirtual #663                // Method net/minecraft/client/gui/GuiGraphicsExtractor.blitSprite:(Lcom/mojang/blaze3d/pipeline/RenderPipeline;Lnet/minecraft/resources/Identifier;IIII)V
        69: aload_1
        70: getstatic     #825                // Field net/minecraft/client/renderer/RenderPipelines.GUI_TEXTURED:Lcom/mojang/blaze3d/pipeline/RenderPipeline;
        73: getstatic     #955                // Field HOTBAR_SELECTION_SPRITE:Lnet/minecraft/resources/Identifier;
        76: iload         6
        78: bipush        91
        80: isub
        81: iconst_1
        82: isub
        83: aload_3
        84: invokevirtual #958                // Method net/minecraft/world/entity/player/Player.getInventory:()Lnet/minecraft/world/entity/player/Inventory;
        87: invokevirtual #962                // Method net/minecraft/world/entity/player/Inventory.getSelectedSlot:()I
        90: bipush        20
        92: imul
        93: iadd
        94: aload_1
        95: invokevirtual #412                // Method net/minecraft/client/gui/GuiGraphicsExtractor.guiHeight:()I
        98: bipush        22
       100: isub
       101: iconst_1
       102: isub
       103: bipush        24
       105: bipush        23
       107: invokevirtual #663                // Method net/minecraft/client/gui/GuiGraphicsExtractor.blitSprite:(Lcom/mojang/blaze3d/pipeline/RenderPipeline;Lnet/minecraft/resources/Identifier;IIII)V
       110: aload         4
       112: invokevirtual #967                // Method net/minecraft/world/item/ItemStack.isEmpty:()Z
       115: ifne          184
       118: aload         5
       120: getstatic     #968                // Field net/minecraft/world/entity/HumanoidArm.LEFT:Lnet/minecraft/world/entity/HumanoidArm;
       123: if_acmpne     158
       126: aload_1
       127: getstatic     #825                // Field net/minecraft/client/renderer/RenderPipelines.GUI_TEXTURED:Lcom/mojang/blaze3d/pipeline/RenderPipeline;
       130: getstatic     #972                // Field HOTBAR_OFFHAND_LEFT_SPRITE:Lnet/minecraft/resources/Identifier;
       133: iload         6
       135: bipush        91
       137: isub
       138: bipush        29
       140: isub
       141: aload_1
       142: invokevirtual #412                // Method net/minecraft/client/gui/GuiGraphicsExtractor.guiHeight:()I
       145: bipush        23
       147: isub
       148: bipush        29
       150: bipush        24
       152: invokevirtual #663                // Method net/minecraft/client/gui/GuiGraphicsExtractor.blitSprite:(Lcom/mojang/blaze3d/pipeline/RenderPipeline;Lnet/minecraft/resources/Identifier;IIII)V
       155: goto          184
       158: aload_1
       159: getstatic     #825                // Field net/minecraft/client/renderer/RenderPipelines.GUI_TEXTURED:Lcom/mojang/blaze3d/pipeline/RenderPipeline;
       162: getstatic     #975                // Field HOTBAR_OFFHAND_RIGHT_SPRITE:Lnet/minecraft/resources/Identifier;
       165: iload         6
       167: bipush        91
       169: iadd
       170: aload_1
       171: invokevirtual #412                // Method net/minecraft/client/gui/GuiGraphicsExtractor.guiHeight:()I
       174: bipush        23
       176: isub
       177: bipush        29
       179: bipush        24
       181: invokevirtual #663                // Method net/minecraft/client/gui/GuiGraphicsExtractor.blitSprite:(Lcom/mojang/blaze3d/pipeline/RenderPipeline;Lnet/minecraft/resources/Identifier;IIII)V
       184: iconst_1
       185: istore        9
       187: iconst_0
       188: istore        10
       190: iload         10
       192: bipush        9
       194: if_icmpge     254
       197: iload         6
       199: bipush        90
       201: isub
       202: iload         10
       204: bipush        20
       206: imul
       207: iadd
       208: iconst_2
       209: iadd
       210: istore        11
       212: aload_1
       213: invokevirtual #412                // Method net/minecraft/client/gui/GuiGraphicsExtractor.guiHeight:()I
       216: bipush        16
       218: isub
       219: iconst_3
       220: isub
       221: istore        12
       223: aload_0
       224: aload_1
       225: iload         11
       227: iload         12
       229: aload_2
       230: aload_3
       231: aload_3
       232: invokevirtual #958                // Method net/minecraft/world/entity/player/Player.getInventory:()Lnet/minecraft/world/entity/player/Inventory;
       235: iload         10
       237: invokevirtual #978                // Method net/minecraft/world/entity/player/Inventory.getItem:(I)Lnet/minecraft/world/item/ItemStack;
       240: iload         9
       242: iinc          9, 1
       245: invokevirtual #982                // Method extractSlot:(Lnet/minecraft/client/gui/GuiGraphicsExtractor;IILnet/minecraft/client/DeltaTracker;Lnet/minecraft/world/entity/player/Player;Lnet/minecraft/world/item/ItemStack;I)V
       248: iinc          10, 1
       251: goto          190
       254: aload         4
       256: invokevirtual #967                // Method net/minecraft/world/item/ItemStack.isEmpty:()Z
       259: ifne          332
       262: aload_1
       263: invokevirtual #412                // Method net/minecraft/client/gui/GuiGraphicsExtractor.guiHeight:()I
       266: bipush        16
       268: isub
       269: iconst_3
       270: isub
       271: istore        10
       273: aload         5
       275: getstatic     #968                // Field net/minecraft/world/entity/HumanoidArm.LEFT:Lnet/minecraft/world/entity/HumanoidArm;
       278: if_acmpne     308
       281: aload_0
       282: aload_1
       283: iload         6
       285: bipush        91
       287: isub
       288: bipush        26
       290: isub
       291: iload         10
       293: aload_2
       294: aload_3
       295: aload         4
       297: iload         9
       299: iinc          9, 1
       302: invokevirtual #982                // Method extractSlot:(Lnet/minecraft/client/gui/GuiGraphicsExtractor;IILnet/minecraft/client/DeltaTracker;Lnet/minecraft/world/entity/player/Player;Lnet/minecraft/world/item/ItemStack;I)V
       305: goto          332
       308: aload_0
       309: aload_1
       310: iload         6
       312: bipush        91
       314: iadd
       315: bipush        10
       317: iadd
       318: iload         10
       320: aload_2
       321: aload_3
       322: aload         4
       324: iload         9
       326: iinc          9, 1
       329: invokevirtual #982                // Method extractSlot:(Lnet/minecraft/client/gui/GuiGraphicsExtractor;IILnet/minecraft/client/DeltaTracker;Lnet/minecraft/world/entity/player/Player;Lnet/minecraft/world/item/ItemStack;I)V
       332: aload_0
       333: getfield      #54                 // Field minecraft:Lnet/minecraft/client/Minecraft;
       336: getfield      #152                // Field net/minecraft/client/Minecraft.options:Lnet/minecraft/client/Options;
       339: invokevirtual #667                // Method net/minecraft/client/Options.attackIndicator:()Lnet/minecraft/client/OptionInstance;
       342: invokevirtual #236                // Method net/minecraft/client/OptionInstance.get:()Ljava/lang/Object;
       345: getstatic     #986                // Field net/minecraft/client/AttackIndicatorStatus.HOTBAR:Lnet/minecraft/client/AttackIndicatorStatus;
       348: if_acmpne     469
       351: aload_0
       352: getfield      #54                 // Field minecraft:Lnet/minecraft/client/Minecraft;
       355: getfield      #254                // Field net/minecraft/client/Minecraft.player:Lnet/minecraft/client/player/LocalPlayer;
       358: fconst_0
       359: invokevirtual #675                // Method net/minecraft/client/player/LocalPlayer.getAttackStrengthScale:(F)F
       362: fstore        10
       364: fload         10
       366: fconst_1
       367: fcmpg
       368: ifge          469
       371: aload_1
       372: invokevirtual #412                // Method net/minecraft/client/gui/GuiGraphicsExtractor.guiHeight:()I
       375: bipush        20
       377: isub
       378: istore        11
       380: iload         6
       382: bipush        91
       384: iadd
       385: bipush        6
       387: iadd
       388: istore        12
       390: aload         5
       392: getstatic     #989                // Field net/minecraft/world/entity/HumanoidArm.RIGHT:Lnet/minecraft/world/entity/HumanoidArm;
       395: if_acmpne     408
       398: iload         6
       400: bipush        91
       402: isub
       403: bipush        22
       405: isub
       406: istore        12
       408: fload         10
       410: ldc_w         #992                // float 19.0f
       413: fmul
       414: f2i
       415: istore        13
       417: aload_1
       418: getstatic     #825                // Field net/minecraft/client/renderer/RenderPipelines.GUI_TEXTURED:Lcom/mojang/blaze3d/pipeline/RenderPipeline;
       421: getstatic     #993                // Field HOTBAR_ATTACK_INDICATOR_BACKGROUND_SPRITE:Lnet/minecraft/resources/Identifier;
       424: iload         12
       426: iload         11
       428: bipush        18
       430: bipush        18
       432: invokevirtual #663                // Method net/minecraft/client/gui/GuiGraphicsExtractor.blitSprite:(Lcom/mojang/blaze3d/pipeline/RenderPipeline;Lnet/minecraft/resources/Identifier;IIII)V
       435: aload_1
       436: getstatic     #825                // Field net/minecraft/client/renderer/RenderPipelines.GUI_TEXTURED:Lcom/mojang/blaze3d/pipeline/RenderPipeline;
       439: getstatic     #996                // Field HOTBAR_ATTACK_INDICATOR_PROGRESS_SPRITE:Lnet/minecraft/resources/Identifier;
       442: bipush        18
       444: bipush        18
       446: iconst_0
       447: bipush        18
       449: iload         13
       451: isub
       452: iload         12
       454: iload         11
       456: bipush        18
       458: iadd
       459: iload         13
       461: isub
       462: bipush        18
       464: iload         13
       466: invokevirtual #723                // Method net/minecraft/client/gui/GuiGraphicsExtractor.blitSprite:(Lcom/mojang/blaze3d/pipeline/RenderPipeline;Lnet/minecraft/resources/Identifier;IIIIIIII)V
       469: return

  private void extractSelectedItemName(net.minecraft.client.gui.GuiGraphicsExtractor);
    Code:
         0: aload_0
         1: getfield      #999                // Field toolHighlightTimer:I
         4: ifle          162
         7: aload_0
         8: getfield      #31                 // Field lastToolHighlight:Lnet/minecraft/world/item/ItemStack;
        11: invokevirtual #967                // Method net/minecraft/world/item/ItemStack.isEmpty:()Z
        14: ifne          162
        17: invokestatic  #1002               // InterfaceMethod net/minecraft/network/chat/Component.empty:()Lnet/minecraft/network/chat/MutableComponent;
        20: aload_0
        21: getfield      #31                 // Field lastToolHighlight:Lnet/minecraft/world/item/ItemStack;
        24: invokevirtual #1008               // Method net/minecraft/world/item/ItemStack.getHoverName:()Lnet/minecraft/network/chat/Component;
        27: invokevirtual #1012               // Method net/minecraft/network/chat/MutableComponent.append:(Lnet/minecraft/network/chat/Component;)Lnet/minecraft/network/chat/MutableComponent;
        30: aload_0
        31: getfield      #31                 // Field lastToolHighlight:Lnet/minecraft/world/item/ItemStack;
        34: invokevirtual #1018               // Method net/minecraft/world/item/ItemStack.getRarity:()Lnet/minecraft/world/item/Rarity;
        37: invokevirtual #1022               // Method net/minecraft/world/item/Rarity.color:()Lnet/minecraft/ChatFormatting;
        40: invokevirtual #1027               // Method net/minecraft/network/chat/MutableComponent.withStyle:(Lnet/minecraft/ChatFormatting;)Lnet/minecraft/network/chat/MutableComponent;
        43: astore_2
        44: aload_0
        45: getfield      #31                 // Field lastToolHighlight:Lnet/minecraft/world/item/ItemStack;
        48: getstatic     #1031               // Field net/minecraft/core/component/DataComponents.CUSTOM_NAME:Lnet/minecraft/core/component/DataComponentType;
        51: invokevirtual #1034               // Method net/minecraft/world/item/ItemStack.has:(Lnet/minecraft/core/component/DataComponentType;)Z
        54: ifeq          65
        57: aload_2
        58: getstatic     #1038               // Field net/minecraft/ChatFormatting.ITALIC:Lnet/minecraft/ChatFormatting;
        61: invokevirtual #1027               // Method net/minecraft/network/chat/MutableComponent.withStyle:(Lnet/minecraft/ChatFormatting;)Lnet/minecraft/network/chat/MutableComponent;
        64: pop
        65: aload_0
        66: invokevirtual #422                // Method getFont:()Lnet/minecraft/client/gui/Font;
        69: aload_2
        70: invokevirtual #466                // Method net/minecraft/client/gui/Font.width:(Lnet/minecraft/network/chat/FormattedText;)I
        73: istore_3
        74: aload_1
        75: invokevirtual #409                // Method net/minecraft/client/gui/GuiGraphicsExtractor.guiWidth:()I
        78: iload_3
        79: isub
        80: iconst_2
        81: idiv
        82: istore        4
        84: aload_1
        85: invokevirtual #412                // Method net/minecraft/client/gui/GuiGraphicsExtractor.guiHeight:()I
        88: bipush        59
        90: isub
        91: istore        5
        93: aload_0
        94: getfield      #54                 // Field minecraft:Lnet/minecraft/client/Minecraft;
        97: getfield      #615                // Field net/minecraft/client/Minecraft.gameMode:Lnet/minecraft/client/multiplayer/MultiPlayerGameMode;
       100: invokevirtual #881                // Method net/minecraft/client/multiplayer/MultiPlayerGameMode.canHurtPlayer:()Z
       103: ifne          109
       106: iinc          5, 14
       109: aload_0
       110: getfield      #999                // Field toolHighlightTimer:I
       113: i2f
       114: ldc_w         #1044               // float 256.0f
       117: fmul
       118: ldc_w         #406                // float 10.0f
       121: fdiv
       122: f2i
       123: istore        6
       125: iload         6
       127: sipush        255
       130: if_icmple     138
       133: sipush        255
       136: istore        6
       138: iload         6
       140: ifle          162
       143: aload_1
       144: aload_0
       145: invokevirtual #422                // Method getFont:()Lnet/minecraft/client/gui/Font;
       148: aload_2
       149: iload         4
       151: iload         5
       153: iload_3
       154: iload         6
       156: invokestatic  #460                // Method net/minecraft/util/ARGB.white:(I)I
       159: invokevirtual #472                // Method net/minecraft/client/gui/GuiGraphicsExtractor.textWithBackdrop:(Lnet/minecraft/client/gui/Font;Lnet/minecraft/network/chat/Component;IIII)V
       162: return

  private void extractDemoOverlay(net.minecraft.client.gui.GuiGraphicsExtractor, net.minecraft.client.DeltaTracker);
    Code:
         0: aload_0
         1: getfield      #54                 // Field minecraft:Lnet/minecraft/client/Minecraft;
         4: invokevirtual #809                // Method net/minecraft/client/Minecraft.isDemo:()Z
         7: ifne          11
        10: return
        11: invokestatic  #390                // Method net/minecraft/util/profiling/Profiler.get:()Lnet/minecraft/util/profiling/ProfilerFiller;
        14: ldc_w         #1045               // String demo
        17: invokeinterface #397,  2          // InterfaceMethod net/minecraft/util/profiling/ProfilerFiller.push:(Ljava/lang/String;)V
        22: aload_1
        23: invokevirtual #169                // Method net/minecraft/client/gui/GuiGraphicsExtractor.nextStratum:()V
        26: aload_0
        27: getfield      #54                 // Field minecraft:Lnet/minecraft/client/Minecraft;
        30: getfield      #534                // Field net/minecraft/client/Minecraft.level:Lnet/minecraft/client/multiplayer/ClientLevel;
        33: invokevirtual #1047               // Method net/minecraft/client/multiplayer/ClientLevel.getGameTime:()J
        36: ldc2_w        #1053               // long 120500l
        39: lcmp
        40: iflt          50
        43: getstatic     #1055               // Field DEMO_EXPIRED_TEXT:Lnet/minecraft/network/chat/Component;
        46: astore_3
        47: goto          95
        50: ldc_w         #1058               // String demo.remainingTime
        53: iconst_1
        54: anewarray     #6                  // class java/lang/Object
        57: dup
        58: iconst_0
        59: ldc2_w        #1053               // long 120500l
        62: aload_0
        63: getfield      #54                 // Field minecraft:Lnet/minecraft/client/Minecraft;
        66: getfield      #534                // Field net/minecraft/client/Minecraft.level:Lnet/minecraft/client/multiplayer/ClientLevel;
        69: invokevirtual #1047               // Method net/minecraft/client/multiplayer/ClientLevel.getGameTime:()J
        72: lsub
        73: l2i
        74: aload_0
        75: getfield      #54                 // Field minecraft:Lnet/minecraft/client/Minecraft;
        78: getfield      #534                // Field net/minecraft/client/Minecraft.level:Lnet/minecraft/client/multiplayer/ClientLevel;
        81: invokevirtual #1060               // Method net/minecraft/client/multiplayer/ClientLevel.tickRateManager:()Lnet/minecraft/world/TickRateManager;
        84: invokevirtual #1064               // Method net/minecraft/world/TickRateManager.tickrate:()F
        87: invokestatic  #1069               // Method net/minecraft/util/StringUtil.formatTickDuration:(IF)Ljava/lang/String;
        90: aastore
        91: invokestatic  #1075               // InterfaceMethod net/minecraft/network/chat/Component.translatable:(Ljava/lang/String;[Ljava/lang/Object;)Lnet/minecraft/network/chat/MutableComponent;
        94: astore_3
        95: aload_0
        96: invokevirtual #422                // Method getFont:()Lnet/minecraft/client/gui/Font;
        99: aload_3
       100: invokevirtual #466                // Method net/minecraft/client/gui/Font.width:(Lnet/minecraft/network/chat/FormattedText;)I
       103: istore        4
       105: aload_1
       106: invokevirtual #409                // Method net/minecraft/client/gui/GuiGraphicsExtractor.guiWidth:()I
       109: iload         4
       111: isub
       112: bipush        10
       114: isub
       115: istore        5
       117: iconst_5
       118: istore        6
       120: aload_1
       121: aload_0
       122: invokevirtual #422                // Method getFont:()Lnet/minecraft/client/gui/Font;
       125: aload_3
       126: iload         5
       128: iconst_5
       129: iload         4
       131: iconst_m1
       132: invokevirtual #472                // Method net/minecraft/client/gui/GuiGraphicsExtractor.textWithBackdrop:(Lnet/minecraft/client/gui/Font;Lnet/minecraft/network/chat/Component;IIII)V
       135: invokestatic  #390                // Method net/minecraft/util/profiling/Profiler.get:()Lnet/minecraft/util/profiling/ProfilerFiller;
       138: invokeinterface #419,  1          // InterfaceMethod net/minecraft/util/profiling/ProfilerFiller.pop:()V
       143: return

  private void displayScoreboardSidebar(net.minecraft.client.gui.GuiGraphicsExtractor, net.minecraft.world.scores.Objective);
    Code:
         0: aload_2
         1: invokevirtual #1081               // Method net/minecraft/world/scores/Objective.getScoreboard:()Lnet/minecraft/world/scores/Scoreboard;
         4: astore_3
         5: aload_2
         6: getstatic     #1084               // Field net/minecraft/network/chat/numbers/StyledFormat.SIDEBAR_DEFAULT:Lnet/minecraft/network/chat/numbers/StyledFormat;
         9: invokevirtual #1090               // Method net/minecraft/world/scores/Objective.numberFormatOrDefault:(Lnet/minecraft/network/chat/numbers/NumberFormat;)Lnet/minecraft/network/chat/numbers/NumberFormat;
        12: astore        4
        14: aload_3
        15: aload_2
        16: invokevirtual #1094               // Method net/minecraft/world/scores/Scoreboard.listPlayerScores:(Lnet/minecraft/world/scores/Objective;)Ljava/util/Collection;
        19: invokeinterface #1098,  1         // InterfaceMethod java/util/Collection.stream:()Ljava/util/stream/Stream;
        24: invokedynamic #1102,  0           // InvokeDynamic #9:test:()Ljava/util/function/Predicate;
        29: invokeinterface #1106,  2         // InterfaceMethod java/util/stream/Stream.filter:(Ljava/util/function/Predicate;)Ljava/util/stream/Stream;
        34: getstatic     #1112               // Field SCORE_DISPLAY_ORDER:Ljava/util/Comparator;
        37: invokeinterface #1116,  2         // InterfaceMethod java/util/stream/Stream.sorted:(Ljava/util/Comparator;)Ljava/util/stream/Stream;
        42: ldc2_w        #1120               // long 15l
        45: invokeinterface #1122,  3         // InterfaceMethod java/util/stream/Stream.limit:(J)Ljava/util/stream/Stream;
        50: aload_0
        51: aload_3
        52: aload         4
        54: invokedynamic #1126,  0           // InvokeDynamic #10:apply:(Lnet/minecraft/client/gui/Gui;Lnet/minecraft/world/scores/Scoreboard;Lnet/minecraft/network/chat/numbers/NumberFormat;)Ljava/util/function/Function;
        59: invokeinterface #1129,  2         // InterfaceMethod java/util/stream/Stream.map:(Ljava/util/function/Function;)Ljava/util/stream/Stream;
        64: invokedynamic #1132,  0           // InvokeDynamic #11:apply:()Ljava/util/function/IntFunction;
        69: invokeinterface #1135,  2         // InterfaceMethod java/util/stream/Stream.toArray:(Ljava/util/function/IntFunction;)[Ljava/lang/Object;
        74: checkcast     #1139               // class "[Lnet/minecraft/client/gui/Gui$1DisplayEntry;"
        77: astore        5
        79: aload_2
        80: invokevirtual #1141               // Method net/minecraft/world/scores/Objective.getDisplayName:()Lnet/minecraft/network/chat/Component;
        83: astore        6
        85: aload_0
        86: invokevirtual #422                // Method getFont:()Lnet/minecraft/client/gui/Font;
        89: aload         6
        91: invokevirtual #466                // Method net/minecraft/client/gui/Font.width:(Lnet/minecraft/network/chat/FormattedText;)I
        94: istore        7
        96: iload         7
        98: istore        8
       100: aload_0
       101: invokevirtual #422                // Method getFont:()Lnet/minecraft/client/gui/Font;
       104: ldc_w         #1144               // String :
       107: invokevirtual #1146               // Method net/minecraft/client/gui/Font.width:(Ljava/lang/String;)I
       110: istore        9
       112: aload         5
       114: astore        10
       116: aload         10
       118: arraylength
       119: istore        11
       121: iconst_0
       122: istore        12
       124: iload         12
       126: iload         11
       128: if_icmpge     184
       131: aload         10
       133: iload         12
       135: aaload
       136: astore        13
       138: iload         8
       140: aload_0
       141: invokevirtual #422                // Method getFont:()Lnet/minecraft/client/gui/Font;
       144: aload         13
       146: getfield      #1149               // Field net/minecraft/client/gui/Gui$1DisplayEntry.name:Lnet/minecraft/network/chat/Component;
       149: invokevirtual #466                // Method net/minecraft/client/gui/Font.width:(Lnet/minecraft/network/chat/FormattedText;)I
       152: aload         13
       154: getfield      #1154               // Field net/minecraft/client/gui/Gui$1DisplayEntry.scoreWidth:I
       157: ifle          171
       160: iload         9
       162: aload         13
       164: getfield      #1154               // Field net/minecraft/client/gui/Gui$1DisplayEntry.scoreWidth:I
       167: iadd
       168: goto          172
       171: iconst_0
       172: iadd
       173: invokestatic  #1157               // Method java/lang/Math.max:(II)I
       176: istore        8
       178: iinc          12, 1
       181: goto          124
       184: iload         8
       186: istore        10
       188: aload         5
       190: arraylength
       191: istore        11
       193: iload         11
       195: aload_0
       196: invokevirtual #422                // Method getFont:()Lnet/minecraft/client/gui/Font;
       199: invokestatic  #1163               // Method java/util/Objects.requireNonNull:(Ljava/lang/Object;)Ljava/lang/Object;
       202: pop
       203: bipush        9
       205: imul
       206: istore        12
       208: aload_1
       209: invokevirtual #412                // Method net/minecraft/client/gui/GuiGraphicsExtractor.guiHeight:()I
       212: iconst_2
       213: idiv
       214: iload         12
       216: iconst_3
       217: idiv
       218: iadd
       219: istore        13
       221: iconst_3
       222: istore        14
       224: aload_1
       225: invokevirtual #409                // Method net/minecraft/client/gui/GuiGraphicsExtractor.guiWidth:()I
       228: iload         10
       230: isub
       231: iconst_3
       232: isub
       233: istore        15
       235: aload_1
       236: invokevirtual #409                // Method net/minecraft/client/gui/GuiGraphicsExtractor.guiWidth:()I
       239: iconst_3
       240: isub
       241: iconst_2
       242: iadd
       243: istore        16
       245: aload_0
       246: getfield      #54                 // Field minecraft:Lnet/minecraft/client/Minecraft;
       249: getfield      #152                // Field net/minecraft/client/Minecraft.options:Lnet/minecraft/client/Options;
       252: ldc_w         #1168               // float 0.3f
       255: invokevirtual #1169               // Method net/minecraft/client/Options.getBackgroundColor:(F)I
       258: istore        17
       260: aload_0
       261: getfield      #54                 // Field minecraft:Lnet/minecraft/client/Minecraft;
       264: getfield      #152                // Field net/minecraft/client/Minecraft.options:Lnet/minecraft/client/Options;
       267: ldc_w         #1172               // float 0.4f
       270: invokevirtual #1169               // Method net/minecraft/client/Options.getBackgroundColor:(F)I
       273: istore        18
       275: iload         13
       277: iload         11
       279: aload_0
       280: invokevirtual #422                // Method getFont:()Lnet/minecraft/client/gui/Font;
       283: invokestatic  #1163               // Method java/util/Objects.requireNonNull:(Ljava/lang/Object;)Ljava/lang/Object;
       286: pop
       287: bipush        9
       289: imul
       290: isub
       291: istore        19
       293: aload_1
       294: iload         15
       296: iconst_2
       297: isub
       298: iload         19
       300: aload_0
       301: invokevirtual #422                // Method getFont:()Lnet/minecraft/client/gui/Font;
       304: invokestatic  #1163               // Method java/util/Objects.requireNonNull:(Ljava/lang/Object;)Ljava/lang/Object;
       307: pop
       308: bipush        9
       310: isub
       311: iconst_1
       312: isub
       313: iload         16
       315: iload         19
       317: iconst_1
       318: isub
       319: iload         18
       321: invokevirtual #415                // Method net/minecraft/client/gui/GuiGraphicsExtractor.fill:(IIIII)V
       324: aload_1
       325: iload         15
       327: iconst_2
       328: isub
       329: iload         19
       331: iconst_1
       332: isub
       333: iload         16
       335: iload         13
       337: iload         17
       339: invokevirtual #415                // Method net/minecraft/client/gui/GuiGraphicsExtractor.fill:(IIIII)V
       342: aload_1
       343: aload_0
       344: invokevirtual #422                // Method getFont:()Lnet/minecraft/client/gui/Font;
       347: aload         6
       349: iload         15
       351: iload         10
       353: iconst_2
       354: idiv
       355: iadd
       356: iload         7
       358: iconst_2
       359: idiv
       360: isub
       361: iload         19
       363: aload_0
       364: invokevirtual #422                // Method getFont:()Lnet/minecraft/client/gui/Font;
       367: invokestatic  #1163               // Method java/util/Objects.requireNonNull:(Ljava/lang/Object;)Ljava/lang/Object;
       370: pop
       371: bipush        9
       373: isub
       374: iconst_m1
       375: iconst_0
       376: invokevirtual #1173               // Method net/minecraft/client/gui/GuiGraphicsExtractor.text:(Lnet/minecraft/client/gui/Font;Lnet/minecraft/network/chat/Component;IIIZ)V
       379: iconst_0
       380: istore        20
       382: iload         20
       384: iload         11
       386: if_icmpge     467
       389: aload         5
       391: iload         20
       393: aaload
       394: astore        21
       396: iload         13
       398: iload         11
       400: iload         20
       402: isub
       403: aload_0
       404: invokevirtual #422                // Method getFont:()Lnet/minecraft/client/gui/Font;
       407: invokestatic  #1163               // Method java/util/Objects.requireNonNull:(Ljava/lang/Object;)Ljava/lang/Object;
       410: pop
       411: bipush        9
       413: imul
       414: isub
       415: istore        22
       417: aload_1
       418: aload_0
       419: invokevirtual #422                // Method getFont:()Lnet/minecraft/client/gui/Font;
       422: aload         21
       424: getfield      #1149               // Field net/minecraft/client/gui/Gui$1DisplayEntry.name:Lnet/minecraft/network/chat/Component;
       427: iload         15
       429: iload         22
       431: iconst_m1
       432: iconst_0
       433: invokevirtual #1173               // Method net/minecraft/client/gui/GuiGraphicsExtractor.text:(Lnet/minecraft/client/gui/Font;Lnet/minecraft/network/chat/Component;IIIZ)V
       436: aload_1
       437: aload_0
       438: invokevirtual #422                // Method getFont:()Lnet/minecraft/client/gui/Font;
       441: aload         21
       443: getfield      #1177               // Field net/minecraft/client/gui/Gui$1DisplayEntry.score:Lnet/minecraft/network/chat/Component;
       446: iload         16
       448: aload         21
       450: getfield      #1154               // Field net/minecraft/client/gui/Gui$1DisplayEntry.scoreWidth:I
       453: isub
       454: iload         22
       456: iconst_m1
       457: iconst_0
       458: invokevirtual #1173               // Method net/minecraft/client/gui/GuiGraphicsExtractor.text:(Lnet/minecraft/client/gui/Font;Lnet/minecraft/network/chat/Component;IIIZ)V
       461: iinc          20, 1
       464: goto          382
       467: return

  private net.minecraft.world.entity.player.Player getCameraPlayer();
    Code:
         0: aload_0
         1: getfield      #54                 // Field minecraft:Lnet/minecraft/client/Minecraft;
         4: invokevirtual #246                // Method net/minecraft/client/Minecraft.getCameraEntity:()Lnet/minecraft/world/entity/Entity;
         7: astore_2
         8: aload_2
         9: instanceof    #403                // class net/minecraft/world/entity/player/Player
        12: ifeq          24
        15: aload_2
        16: checkcast     #403                // class net/minecraft/world/entity/player/Player
        19: astore_1
        20: aload_1
        21: goto          25
        24: aconst_null
        25: areturn

  private net.minecraft.world.entity.LivingEntity getPlayerVehicleWithHealth();
    Code:
         0: aload_0
         1: invokevirtual #936                // Method getCameraPlayer:()Lnet/minecraft/world/entity/player/Player;
         4: astore_1
         5: aload_1
         6: ifnull        32
         9: aload_1
        10: invokevirtual #1180               // Method net/minecraft/world/entity/player/Player.getVehicle:()Lnet/minecraft/world/entity/Entity;
        13: astore_2
        14: aload_2
        15: ifnonnull     20
        18: aconst_null
        19: areturn
        20: aload_2
        21: instanceof    #683                // class net/minecraft/world/entity/LivingEntity
        24: ifeq          32
        27: aload_2
        28: checkcast     #683                // class net/minecraft/world/entity/LivingEntity
        31: areturn
        32: aconst_null
        33: areturn

  private int getVehicleMaxHearts(net.minecraft.world.entity.LivingEntity);
    Code:
         0: aload_1
         1: ifnull        11
         4: aload_1
         5: invokevirtual #1183               // Method net/minecraft/world/entity/LivingEntity.showVehicleHealth:()Z
         8: ifne          13
        11: iconst_0
        12: ireturn
        13: aload_1
        14: invokevirtual #1186               // Method net/minecraft/world/entity/LivingEntity.getMaxHealth:()F
        17: fstore_2
        18: fload_2
        19: ldc_w         #264                // float 0.5f
        22: fadd
        23: f2i
        24: iconst_2
        25: idiv
        26: istore_3
        27: iload_3
        28: bipush        30
        30: if_icmple     36
        33: bipush        30
        35: istore_3
        36: iload_3
        37: ireturn

  private int getVisibleVehicleHeartRows(int);
    Code:
         0: iload_1
         1: i2d
         2: ldc2_w        #1189               // double 10.0d
         5: ddiv
         6: invokestatic  #1191               // Method java/lang/Math.ceil:(D)D
         9: d2i
        10: ireturn

  private void extractPlayerHealth(net.minecraft.client.gui.GuiGraphicsExtractor);
    Code:
         0: aload_0
         1: invokevirtual #936                // Method getCameraPlayer:()Lnet/minecraft/world/entity/player/Player;
         4: astore_2
         5: aload_2
         6: ifnonnull     10
         9: return
        10: aload_2
        11: invokevirtual #1195               // Method net/minecraft/world/entity/player/Player.getHealth:()F
        14: invokestatic  #1198               // Method net/minecraft/util/Mth.ceil:(F)I
        17: istore_3
        18: aload_0
        19: getfield      #1200               // Field healthBlinkTime:J
        22: aload_0
        23: getfield      #522                // Field tickCount:I
        26: i2l
        27: lcmp
        28: ifle          58
        31: aload_0
        32: getfield      #1200               // Field healthBlinkTime:J
        35: aload_0
        36: getfield      #522                // Field tickCount:I
        39: i2l
        40: lsub
        41: ldc2_w        #1204               // long 3l
        44: ldiv
        45: ldc2_w        #1206               // long 2l
        48: lrem
        49: lconst_1
        50: lcmp
        51: ifne          58
        54: iconst_1
        55: goto          59
        58: iconst_0
        59: istore        4
        61: invokestatic  #1208               // Method net/minecraft/util/Util.getMillis:()J
        64: lstore        5
        66: iload_3
        67: aload_0
        68: getfield      #1213               // Field lastHealth:I
        71: if_icmpge     102
        74: aload_2
        75: getfield      #1216               // Field net/minecraft/world/entity/player/Player.invulnerableTime:I
        78: ifle          102
        81: aload_0
        82: lload         5
        84: putfield      #1219               // Field lastHealthTime:J
        87: aload_0
        88: aload_0
        89: getfield      #522                // Field tickCount:I
        92: bipush        20
        94: iadd
        95: i2l
        96: putfield      #1200               // Field healthBlinkTime:J
        99: goto          135
       102: iload_3
       103: aload_0
       104: getfield      #1213               // Field lastHealth:I
       107: if_icmple     135
       110: aload_2
       111: getfield      #1216               // Field net/minecraft/world/entity/player/Player.invulnerableTime:I
       114: ifle          135
       117: aload_0
       118: lload         5
       120: putfield      #1219               // Field lastHealthTime:J
       123: aload_0
       124: aload_0
       125: getfield      #522                // Field tickCount:I
       128: bipush        10
       130: iadd
       131: i2l
       132: putfield      #1200               // Field healthBlinkTime:J
       135: lload         5
       137: aload_0
       138: getfield      #1219               // Field lastHealthTime:J
       141: lsub
       142: ldc2_w        #1222               // long 1000l
       145: lcmp
       146: ifle          160
       149: aload_0
       150: iload_3
       151: putfield      #1224               // Field displayHealth:I
       154: aload_0
       155: lload         5
       157: putfield      #1219               // Field lastHealthTime:J
       160: aload_0
       161: iload_3
       162: putfield      #1213               // Field lastHealth:I
       165: aload_0
       166: getfield      #1224               // Field displayHealth:I
       169: istore        7
       171: aload_0
       172: getfield      #17                 // Field random:Lnet/minecraft/util/RandomSource;
       175: aload_0
       176: getfield      #522                // Field tickCount:I
       179: ldc_w         #1227               // int 312871
       182: imul
       183: i2l
       184: invokeinterface #1228,  3         // InterfaceMethod net/minecraft/util/RandomSource.setSeed:(J)V
       189: aload_1
       190: invokevirtual #409                // Method net/minecraft/client/gui/GuiGraphicsExtractor.guiWidth:()I
       193: iconst_2
       194: idiv
       195: bipush        91
       197: isub
       198: istore        8
       200: aload_1
       201: invokevirtual #409                // Method net/minecraft/client/gui/GuiGraphicsExtractor.guiWidth:()I
       204: iconst_2
       205: idiv
       206: bipush        91
       208: iadd
       209: istore        9
       211: aload_1
       212: invokevirtual #412                // Method net/minecraft/client/gui/GuiGraphicsExtractor.guiHeight:()I
       215: bipush        39
       217: isub
       218: istore        10
       220: aload_2
       221: getstatic     #1232               // Field net/minecraft/world/entity/ai/attributes/Attributes.MAX_HEALTH:Lnet/minecraft/core/Holder;
       224: invokevirtual #1237               // Method net/minecraft/world/entity/player/Player.getAttributeValue:(Lnet/minecraft/core/Holder;)D
       227: d2f
       228: iload         7
       230: iload_3
       231: invokestatic  #1157               // Method java/lang/Math.max:(II)I
       234: i2f
       235: invokestatic  #1241               // Method java/lang/Math.max:(FF)F
       238: fstore        11
       240: aload_2
       241: invokevirtual #1244               // Method net/minecraft/world/entity/player/Player.getAbsorptionAmount:()F
       244: invokestatic  #1198               // Method net/minecraft/util/Mth.ceil:(F)I
       247: istore        12
       249: fload         11
       251: iload         12
       253: i2f
       254: fadd
       255: fconst_2
       256: fdiv
       257: ldc_w         #406                // float 10.0f
       260: fdiv
       261: invokestatic  #1198               // Method net/minecraft/util/Mth.ceil:(F)I
       264: istore        13
       266: bipush        10
       268: iload         13
       270: iconst_2
       271: isub
       272: isub
       273: iconst_3
       274: invokestatic  #1157               // Method java/lang/Math.max:(II)I
       277: istore        14
       279: iload         10
       281: bipush        10
       283: isub
       284: istore        15
       286: iconst_m1
       287: istore        16
       289: aload_2
       290: getstatic     #1247               // Field net/minecraft/world/effect/MobEffects.REGENERATION:Lnet/minecraft/core/Holder;
       293: invokevirtual #1250               // Method net/minecraft/world/entity/player/Player.hasEffect:(Lnet/minecraft/core/Holder;)Z
       296: ifeq          315
       299: aload_0
       300: getfield      #522                // Field tickCount:I
       303: fload         11
       305: ldc_w         #688                // float 5.0f
       308: fadd
       309: invokestatic  #1198               // Method net/minecraft/util/Mth.ceil:(F)I
       312: irem
       313: istore        16
       315: invokestatic  #390                // Method net/minecraft/util/profiling/Profiler.get:()Lnet/minecraft/util/profiling/ProfilerFiller;
       318: ldc_w         #1254               // String armor
       321: invokeinterface #397,  2          // InterfaceMethod net/minecraft/util/profiling/ProfilerFiller.push:(Ljava/lang/String;)V
       326: aload_1
       327: aload_2
       328: iload         10
       330: iload         13
       332: iload         14
       334: iload         8
       336: invokestatic  #1256               // Method extractArmor:(Lnet/minecraft/client/gui/GuiGraphicsExtractor;Lnet/minecraft/world/entity/player/Player;IIII)V
       339: invokestatic  #390                // Method net/minecraft/util/profiling/Profiler.get:()Lnet/minecraft/util/profiling/ProfilerFiller;
       342: ldc_w         #1260               // String health
       345: invokeinterface #1262,  2         // InterfaceMethod net/minecraft/util/profiling/ProfilerFiller.popPush:(Ljava/lang/String;)V
       350: aload_0
       351: aload_1
       352: aload_2
       353: iload         8
       355: iload         10
       357: iload         14
       359: iload         16
       361: fload         11
       363: iload_3
       364: iload         7
       366: iload         12
       368: iload         4
       370: invokevirtual #1265               // Method extractHearts:(Lnet/minecraft/client/gui/GuiGraphicsExtractor;Lnet/minecraft/world/entity/player/Player;IIIIFIIIZ)V
       373: aload_0
       374: invokevirtual #1269               // Method getPlayerVehicleWithHealth:()Lnet/minecraft/world/entity/LivingEntity;
       377: astore        17
       379: aload_0
       380: aload         17
       382: invokevirtual #1273               // Method getVehicleMaxHearts:(Lnet/minecraft/world/entity/LivingEntity;)I
       385: istore        18
       387: iload         18
       389: ifne          416
       392: invokestatic  #390                // Method net/minecraft/util/profiling/Profiler.get:()Lnet/minecraft/util/profiling/ProfilerFiller;
       395: ldc_w         #1277               // String food
       398: invokeinterface #1262,  2         // InterfaceMethod net/minecraft/util/profiling/ProfilerFiller.popPush:(Ljava/lang/String;)V
       403: aload_0
       404: aload_1
       405: aload_2
       406: iload         10
       408: iload         9
       410: invokevirtual #1279               // Method extractFood:(Lnet/minecraft/client/gui/GuiGraphicsExtractor;Lnet/minecraft/world/entity/player/Player;II)V
       413: iinc          15, -10
       416: invokestatic  #390                // Method net/minecraft/util/profiling/Profiler.get:()Lnet/minecraft/util/profiling/ProfilerFiller;
       419: ldc_w         #1283               // String air
       422: invokeinterface #1262,  2         // InterfaceMethod net/minecraft/util/profiling/ProfilerFiller.popPush:(Ljava/lang/String;)V
       427: aload_0
       428: aload_1
       429: aload_2
       430: iload         18
       432: iload         15
       434: iload         9
       436: invokevirtual #1285               // Method extractAirBubbles:(Lnet/minecraft/client/gui/GuiGraphicsExtractor;Lnet/minecraft/world/entity/player/Player;III)V
       439: invokestatic  #390                // Method net/minecraft/util/profiling/Profiler.get:()Lnet/minecraft/util/profiling/ProfilerFiller;
       442: invokeinterface #419,  1          // InterfaceMethod net/minecraft/util/profiling/ProfilerFiller.pop:()V
       447: return

  private static void extractArmor(net.minecraft.client.gui.GuiGraphicsExtractor, net.minecraft.world.entity.player.Player, int, int, int, int);
    Code:
         0: aload_1
         1: invokevirtual #1289               // Method net/minecraft/world/entity/player/Player.getArmorValue:()I
         4: istore        6
         6: iload         6
         8: ifgt          12
        11: return
        12: iload_2
        13: iload_3
        14: iconst_1
        15: isub
        16: iload         4
        18: imul
        19: isub
        20: bipush        10
        22: isub
        23: istore        7
        25: iconst_0
        26: istore        8
        28: iload         8
        30: bipush        10
        32: if_icmpge     138
        35: iload         5
        37: iload         8
        39: bipush        8
        41: imul
        42: iadd
        43: istore        9
        45: iload         8
        47: iconst_2
        48: imul
        49: iconst_1
        50: iadd
        51: iload         6
        53: if_icmpge     74
        56: aload_0
        57: getstatic     #825                // Field net/minecraft/client/renderer/RenderPipelines.GUI_TEXTURED:Lcom/mojang/blaze3d/pipeline/RenderPipeline;
        60: getstatic     #1292               // Field ARMOR_FULL_SPRITE:Lnet/minecraft/resources/Identifier;
        63: iload         9
        65: iload         7
        67: bipush        9
        69: bipush        9
        71: invokevirtual #663                // Method net/minecraft/client/gui/GuiGraphicsExtractor.blitSprite:(Lcom/mojang/blaze3d/pipeline/RenderPipeline;Lnet/minecraft/resources/Identifier;IIII)V
        74: iload         8
        76: iconst_2
        77: imul
        78: iconst_1
        79: iadd
        80: iload         6
        82: if_icmpne     103
        85: aload_0
        86: getstatic     #825                // Field net/minecraft/client/renderer/RenderPipelines.GUI_TEXTURED:Lcom/mojang/blaze3d/pipeline/RenderPipeline;
        89: getstatic     #1295               // Field ARMOR_HALF_SPRITE:Lnet/minecraft/resources/Identifier;
        92: iload         9
        94: iload         7
        96: bipush        9
        98: bipush        9
       100: invokevirtual #663                // Method net/minecraft/client/gui/GuiGraphicsExtractor.blitSprite:(Lcom/mojang/blaze3d/pipeline/RenderPipeline;Lnet/minecraft/resources/Identifier;IIII)V
       103: iload         8
       105: iconst_2
       106: imul
       107: iconst_1
       108: iadd
       109: iload         6
       111: if_icmple     132
       114: aload_0
       115: getstatic     #825                // Field net/minecraft/client/renderer/RenderPipelines.GUI_TEXTURED:Lcom/mojang/blaze3d/pipeline/RenderPipeline;
       118: getstatic     #1298               // Field ARMOR_EMPTY_SPRITE:Lnet/minecraft/resources/Identifier;
       121: iload         9
       123: iload         7
       125: bipush        9
       127: bipush        9
       129: invokevirtual #663                // Method net/minecraft/client/gui/GuiGraphicsExtractor.blitSprite:(Lcom/mojang/blaze3d/pipeline/RenderPipeline;Lnet/minecraft/resources/Identifier;IIII)V
       132: iinc          8, 1
       135: goto          28
       138: return

  private void extractHearts(net.minecraft.client.gui.GuiGraphicsExtractor, net.minecraft.world.entity.player.Player, int, int, int, int, float, int, int, int, boolean);
    Code:
         0: aload_2
         1: invokestatic  #1301               // Method net/minecraft/client/gui/Gui$HeartType.forPlayer:(Lnet/minecraft/world/entity/player/Player;)Lnet/minecraft/client/gui/Gui$HeartType;
         4: astore        12
         6: aload_2
         7: invokevirtual #1307               // Method net/minecraft/world/entity/player/Player.level:()Lnet/minecraft/world/level/Level;
        10: invokevirtual #1310               // Method net/minecraft/world/level/Level.getLevelData:()Lnet/minecraft/world/level/storage/LevelData;
        13: invokeinterface #1314,  1         // InterfaceMethod net/minecraft/world/level/storage/LevelData.isHardcore:()Z
        18: istore        13
        20: fload         7
        22: f2d
        23: ldc2_w        #1319               // double 2.0d
        26: ddiv
        27: invokestatic  #1321               // Method net/minecraft/util/Mth.ceil:(D)I
        30: istore        14
        32: iload         10
        34: i2d
        35: ldc2_w        #1319               // double 2.0d
        38: ddiv
        39: invokestatic  #1321               // Method net/minecraft/util/Mth.ceil:(D)I
        42: istore        15
        44: iload         14
        46: iconst_2
        47: imul
        48: istore        16
        50: iload         14
        52: iload         15
        54: iadd
        55: iconst_1
        56: isub
        57: istore        17
        59: iload         17
        61: iflt          329
        64: iload         17
        66: bipush        10
        68: idiv
        69: istore        18
        71: iload         17
        73: bipush        10
        75: irem
        76: istore        19
        78: iload_3
        79: iload         19
        81: bipush        8
        83: imul
        84: iadd
        85: istore        20
        87: iload         4
        89: iload         18
        91: iload         5
        93: imul
        94: isub
        95: istore        21
        97: iload         8
        99: iload         10
       101: iadd
       102: iconst_4
       103: if_icmpgt     121
       106: iload         21
       108: aload_0
       109: getfield      #17                 // Field random:Lnet/minecraft/util/RandomSource;
       112: iconst_2
       113: invokeinterface #1323,  2         // InterfaceMethod net/minecraft/util/RandomSource.nextInt:(I)I
       118: iadd
       119: istore        21
       121: iload         17
       123: iload         14
       125: if_icmpge     138
       128: iload         17
       130: iload         6
       132: if_icmpne     138
       135: iinc          21, -2
       138: aload_0
       139: aload_1
       140: getstatic     #1326               // Field net/minecraft/client/gui/Gui$HeartType.CONTAINER:Lnet/minecraft/client/gui/Gui$HeartType;
       143: iload         20
       145: iload         21
       147: iload         13
       149: iload         11
       151: iconst_0
       152: invokevirtual #1330               // Method extractHeart:(Lnet/minecraft/client/gui/GuiGraphicsExtractor;Lnet/minecraft/client/gui/Gui$HeartType;IIZZZ)V
       155: iload         17
       157: iconst_2
       158: imul
       159: istore        22
       161: iload         17
       163: iload         14
       165: if_icmplt     172
       168: iconst_1
       169: goto          173
       172: iconst_0
       173: istore        23
       175: iload         23
       177: ifeq          240
       180: iload         22
       182: iload         16
       184: isub
       185: istore        24
       187: iload         24
       189: iload         10
       191: if_icmpge     240
       194: iload         24
       196: iconst_1
       197: iadd
       198: iload         10
       200: if_icmpne     207
       203: iconst_1
       204: goto          208
       207: iconst_0
       208: istore        25
       210: aload_0
       211: aload_1
       212: aload         12
       214: getstatic     #1334               // Field net/minecraft/client/gui/Gui$HeartType.WITHERED:Lnet/minecraft/client/gui/Gui$HeartType;
       217: if_acmpne     225
       220: aload         12
       222: goto          228
       225: getstatic     #1337               // Field net/minecraft/client/gui/Gui$HeartType.ABSORBING:Lnet/minecraft/client/gui/Gui$HeartType;
       228: iload         20
       230: iload         21
       232: iload         13
       234: iconst_0
       235: iload         25
       237: invokevirtual #1330               // Method extractHeart:(Lnet/minecraft/client/gui/GuiGraphicsExtractor;Lnet/minecraft/client/gui/Gui$HeartType;IIZZZ)V
       240: iload         11
       242: ifeq          284
       245: iload         22
       247: iload         9
       249: if_icmpge     284
       252: iload         22
       254: iconst_1
       255: iadd
       256: iload         9
       258: if_icmpne     265
       261: iconst_1
       262: goto          266
       265: iconst_0
       266: istore        24
       268: aload_0
       269: aload_1
       270: aload         12
       272: iload         20
       274: iload         21
       276: iload         13
       278: iconst_1
       279: iload         24
       281: invokevirtual #1330               // Method extractHeart:(Lnet/minecraft/client/gui/GuiGraphicsExtractor;Lnet/minecraft/client/gui/Gui$HeartType;IIZZZ)V
       284: iload         22
       286: iload         8
       288: if_icmpge     323
       291: iload         22
       293: iconst_1
       294: iadd
       295: iload         8
       297: if_icmpne     304
       300: iconst_1
       301: goto          305
       304: iconst_0
       305: istore        24
       307: aload_0
       308: aload_1
       309: aload         12
       311: iload         20
       313: iload         21
       315: iload         13
       317: iconst_0
       318: iload         24
       320: invokevirtual #1330               // Method extractHeart:(Lnet/minecraft/client/gui/GuiGraphicsExtractor;Lnet/minecraft/client/gui/Gui$HeartType;IIZZZ)V
       323: iinc          17, -1
       326: goto          59
       329: return

  private void extractHeart(net.minecraft.client.gui.GuiGraphicsExtractor, net.minecraft.client.gui.Gui$HeartType, int, int, boolean, boolean, boolean);
    Code:
         0: aload_1
         1: getstatic     #825                // Field net/minecraft/client/renderer/RenderPipelines.GUI_TEXTURED:Lcom/mojang/blaze3d/pipeline/RenderPipeline;
         4: aload_2
         5: iload         5
         7: iload         7
         9: iload         6
        11: invokevirtual #1340               // Method net/minecraft/client/gui/Gui$HeartType.getSprite:(ZZZ)Lnet/minecraft/resources/Identifier;
        14: iload_3
        15: iload         4
        17: bipush        9
        19: bipush        9
        21: invokevirtual #663                // Method net/minecraft/client/gui/GuiGraphicsExtractor.blitSprite:(Lcom/mojang/blaze3d/pipeline/RenderPipeline;Lnet/minecraft/resources/Identifier;IIII)V
        24: return

  private void extractAirBubbles(net.minecraft.client.gui.GuiGraphicsExtractor, net.minecraft.world.entity.player.Player, int, int, int);
    Code:
         0: aload_2
         1: invokevirtual #1344               // Method net/minecraft/world/entity/player/Player.getMaxAirSupply:()I
         4: istore        6
         6: aload_2
         7: invokevirtual #1347               // Method net/minecraft/world/entity/player/Player.getAirSupply:()I
        10: i2l
        11: iconst_0
        12: iload         6
        14: invokestatic  #1350               // Method java/lang/Math.clamp:(JII)I
        17: istore        7
        19: aload_2
        20: getstatic     #1353               // Field net/minecraft/tags/FluidTags.WATER:Lnet/minecraft/tags/TagKey;
        23: invokevirtual #1359               // Method net/minecraft/world/entity/player/Player.isEyeInFluid:(Lnet/minecraft/tags/TagKey;)Z
        26: istore        8
        28: iload         8
        30: ifne          40
        33: iload         7
        35: iload         6
        37: if_icmpge     282
        40: aload_0
        41: iload_3
        42: iload         4
        44: invokevirtual #1363               // Method getAirBubbleYLine:(II)I
        47: istore        4
        49: iload         7
        51: iload         6
        53: bipush        -2
        55: invokestatic  #1366               // Method getCurrentAirSupplyBubble:(III)I
        58: istore        9
        60: iload         7
        62: iload         6
        64: iconst_0
        65: invokestatic  #1366               // Method getCurrentAirSupplyBubble:(III)I
        68: istore        10
        70: bipush        10
        72: iload         7
        74: iload         6
        76: iload         7
        78: iload         8
        80: invokestatic  #1369               // Method getEmptyBubbleDelayDuration:(IZ)I
        83: invokestatic  #1366               // Method getCurrentAirSupplyBubble:(III)I
        86: isub
        87: istore        11
        89: iload         9
        91: iload         10
        93: if_icmpeq     100
        96: iconst_1
        97: goto          101
       100: iconst_0
       101: istore        12
       103: iload         8
       105: ifne          113
       108: aload_0
       109: iconst_0
       110: putfield      #1373               // Field lastBubblePopSoundPlayed:I
       113: iconst_1
       114: istore        13
       116: iload         13
       118: bipush        10
       120: if_icmpgt     282
       123: iload         5
       125: iload         13
       127: iconst_1
       128: isub
       129: bipush        8
       131: imul
       132: isub
       133: bipush        9
       135: isub
       136: istore        14
       138: iload         13
       140: iload         9
       142: if_icmpgt     166
       145: aload_1
       146: getstatic     #825                // Field net/minecraft/client/renderer/RenderPipelines.GUI_TEXTURED:Lcom/mojang/blaze3d/pipeline/RenderPipeline;
       149: getstatic     #1376               // Field AIR_SPRITE:Lnet/minecraft/resources/Identifier;
       152: iload         14
       154: iload         4
       156: bipush        9
       158: bipush        9
       160: invokevirtual #663                // Method net/minecraft/client/gui/GuiGraphicsExtractor.blitSprite:(Lcom/mojang/blaze3d/pipeline/RenderPipeline;Lnet/minecraft/resources/Identifier;IIII)V
       163: goto          276
       166: iload         12
       168: ifeq          213
       171: iload         13
       173: iload         10
       175: if_icmpne     213
       178: iload         8
       180: ifeq          213
       183: aload_1
       184: getstatic     #825                // Field net/minecraft/client/renderer/RenderPipelines.GUI_TEXTURED:Lcom/mojang/blaze3d/pipeline/RenderPipeline;
       187: getstatic     #1379               // Field AIR_POPPING_SPRITE:Lnet/minecraft/resources/Identifier;
       190: iload         14
       192: iload         4
       194: bipush        9
       196: bipush        9
       198: invokevirtual #663                // Method net/minecraft/client/gui/GuiGraphicsExtractor.blitSprite:(Lcom/mojang/blaze3d/pipeline/RenderPipeline;Lnet/minecraft/resources/Identifier;IIII)V
       201: aload_0
       202: iload         13
       204: aload_2
       205: iload         11
       207: invokevirtual #1382               // Method playAirBubblePoppedSound:(ILnet/minecraft/world/entity/player/Player;I)V
       210: goto          276
       213: iload         13
       215: bipush        10
       217: iload         11
       219: isub
       220: if_icmple     276
       223: iload         11
       225: bipush        10
       227: if_icmpne     252
       230: aload_0
       231: getfield      #522                // Field tickCount:I
       234: iconst_2
       235: irem
       236: ifne          252
       239: aload_0
       240: getfield      #17                 // Field random:Lnet/minecraft/util/RandomSource;
       243: iconst_2
       244: invokeinterface #1323,  2         // InterfaceMethod net/minecraft/util/RandomSource.nextInt:(I)I
       249: goto          253
       252: iconst_0
       253: istore        15
       255: aload_1
       256: getstatic     #825                // Field net/minecraft/client/renderer/RenderPipelines.GUI_TEXTURED:Lcom/mojang/blaze3d/pipeline/RenderPipeline;
       259: getstatic     #1386               // Field AIR_EMPTY_SPRITE:Lnet/minecraft/resources/Identifier;
       262: iload         14
       264: iload         4
       266: iload         15
       268: iadd
       269: bipush        9
       271: bipush        9
       273: invokevirtual #663                // Method net/minecraft/client/gui/GuiGraphicsExtractor.blitSprite:(Lcom/mojang/blaze3d/pipeline/RenderPipeline;Lnet/minecraft/resources/Identifier;IIII)V
       276: iinc          13, 1
       279: goto          116
       282: return

  private int getAirBubbleYLine(int, int);
    Code:
         0: aload_0
         1: iload_1
         2: invokevirtual #1389               // Method getVisibleVehicleHeartRows:(I)I
         5: iconst_1
         6: isub
         7: istore_3
         8: iload_2
         9: iload_3
        10: bipush        10
        12: imul
        13: isub
        14: istore_2
        15: iload_2
        16: ireturn

  private static int getCurrentAirSupplyBubble(int, int, int);
    Code:
         0: iload_0
         1: iload_2
         2: iadd
         3: bipush        10
         5: imul
         6: i2f
         7: iload_1
         8: i2f
         9: fdiv
        10: invokestatic  #1198               // Method net/minecraft/util/Mth.ceil:(F)I
        13: ireturn

  private static int getEmptyBubbleDelayDuration(int, boolean);
    Code:
         0: iload_0
         1: ifeq          8
         4: iload_1
         5: ifne          12
         8: iconst_0
         9: goto          13
        12: iconst_1
        13: ireturn

  private void playAirBubblePoppedSound(int, net.minecraft.world.entity.player.Player, int);
    Code:
         0: aload_0
         1: getfield      #1373               // Field lastBubblePopSoundPlayed:I
         4: iload_1
         5: if_icmpeq     62
         8: ldc_w         #264                // float 0.5f
        11: ldc_w         #1392               // float 0.1f
        14: iconst_0
        15: iload_3
        16: iconst_3
        17: isub
        18: iconst_1
        19: iadd
        20: invokestatic  #1157               // Method java/lang/Math.max:(II)I
        23: i2f
        24: fmul
        25: fadd
        26: fstore        4
        28: fconst_1
        29: ldc_w         #1392               // float 0.1f
        32: iconst_0
        33: iload_3
        34: iconst_5
        35: isub
        36: iconst_1
        37: iadd
        38: invokestatic  #1157               // Method java/lang/Math.max:(II)I
        41: i2f
        42: fmul
        43: fadd
        44: fstore        5
        46: aload_2
        47: getstatic     #1393               // Field net/minecraft/sounds/SoundEvents.BUBBLE_POP:Lnet/minecraft/sounds/SoundEvent;
        50: fload         4
        52: fload         5
        54: invokevirtual #1399               // Method net/minecraft/world/entity/player/Player.playSound:(Lnet/minecraft/sounds/SoundEvent;FF)V
        57: aload_0
        58: iload_1
        59: putfield      #1373               // Field lastBubblePopSoundPlayed:I
        62: return

  private void extractFood(net.minecraft.client.gui.GuiGraphicsExtractor, net.minecraft.world.entity.player.Player, int, int);
    Code:
         0: aload_2
         1: invokevirtual #1403               // Method net/minecraft/world/entity/player/Player.getFoodData:()Lnet/minecraft/world/food/FoodData;
         4: astore        5
         6: aload         5
         8: invokevirtual #1407               // Method net/minecraft/world/food/FoodData.getFoodLevel:()I
        11: istore        6
        13: iconst_0
        14: istore        7
        16: iload         7
        18: bipush        10
        20: if_icmpge     204
        23: iload_3
        24: istore        8
        26: aload_2
        27: getstatic     #1414               // Field net/minecraft/world/effect/MobEffects.HUNGER:Lnet/minecraft/core/Holder;
        30: invokevirtual #1250               // Method net/minecraft/world/entity/player/Player.hasEffect:(Lnet/minecraft/core/Holder;)Z
        33: ifeq          54
        36: getstatic     #1417               // Field FOOD_EMPTY_HUNGER_SPRITE:Lnet/minecraft/resources/Identifier;
        39: astore        9
        41: getstatic     #1420               // Field FOOD_HALF_HUNGER_SPRITE:Lnet/minecraft/resources/Identifier;
        44: astore        10
        46: getstatic     #1423               // Field FOOD_FULL_HUNGER_SPRITE:Lnet/minecraft/resources/Identifier;
        49: astore        11
        51: goto          69
        54: getstatic     #1426               // Field FOOD_EMPTY_SPRITE:Lnet/minecraft/resources/Identifier;
        57: astore        9
        59: getstatic     #1429               // Field FOOD_HALF_SPRITE:Lnet/minecraft/resources/Identifier;
        62: astore        10
        64: getstatic     #1432               // Field FOOD_FULL_SPRITE:Lnet/minecraft/resources/Identifier;
        67: astore        11
        69: aload_2
        70: invokevirtual #1403               // Method net/minecraft/world/entity/player/Player.getFoodData:()Lnet/minecraft/world/food/FoodData;
        73: invokevirtual #1435               // Method net/minecraft/world/food/FoodData.getSaturationLevel:()F
        76: fconst_0
        77: fcmpg
        78: ifgt          112
        81: aload_0
        82: getfield      #522                // Field tickCount:I
        85: iload         6
        87: iconst_3
        88: imul
        89: iconst_1
        90: iadd
        91: irem
        92: ifne          112
        95: iload         8
        97: aload_0
        98: getfield      #17                 // Field random:Lnet/minecraft/util/RandomSource;
       101: iconst_3
       102: invokeinterface #1323,  2         // InterfaceMethod net/minecraft/util/RandomSource.nextInt:(I)I
       107: iconst_1
       108: isub
       109: iadd
       110: istore        8
       112: iload         4
       114: iload         7
       116: bipush        8
       118: imul
       119: isub
       120: bipush        9
       122: isub
       123: istore        12
       125: aload_1
       126: getstatic     #825                // Field net/minecraft/client/renderer/RenderPipelines.GUI_TEXTURED:Lcom/mojang/blaze3d/pipeline/RenderPipeline;
       129: aload         9
       131: iload         12
       133: iload         8
       135: bipush        9
       137: bipush        9
       139: invokevirtual #663                // Method net/minecraft/client/gui/GuiGraphicsExtractor.blitSprite:(Lcom/mojang/blaze3d/pipeline/RenderPipeline;Lnet/minecraft/resources/Identifier;IIII)V
       142: iload         7
       144: iconst_2
       145: imul
       146: iconst_1
       147: iadd
       148: iload         6
       150: if_icmpge     170
       153: aload_1
       154: getstatic     #825                // Field net/minecraft/client/renderer/RenderPipelines.GUI_TEXTURED:Lcom/mojang/blaze3d/pipeline/RenderPipeline;
       157: aload         11
       159: iload         12
       161: iload         8
       163: bipush        9
       165: bipush        9
       167: invokevirtual #663                // Method net/minecraft/client/gui/GuiGraphicsExtractor.blitSprite:(Lcom/mojang/blaze3d/pipeline/RenderPipeline;Lnet/minecraft/resources/Identifier;IIII)V
       170: iload         7
       172: iconst_2
       173: imul
       174: iconst_1
       175: iadd
       176: iload         6
       178: if_icmpne     198
       181: aload_1
       182: getstatic     #825                // Field net/minecraft/client/renderer/RenderPipelines.GUI_TEXTURED:Lcom/mojang/blaze3d/pipeline/RenderPipeline;
       185: aload         10
       187: iload         12
       189: iload         8
       191: bipush        9
       193: bipush        9
       195: invokevirtual #663                // Method net/minecraft/client/gui/GuiGraphicsExtractor.blitSprite:(Lcom/mojang/blaze3d/pipeline/RenderPipeline;Lnet/minecraft/resources/Identifier;IIII)V
       198: iinc          7, 1
       201: goto          16
       204: return

  private void extractVehicleHealth(net.minecraft.client.gui.GuiGraphicsExtractor);
    Code:
         0: aload_0
         1: invokevirtual #1269               // Method getPlayerVehicleWithHealth:()Lnet/minecraft/world/entity/LivingEntity;
         4: astore_2
         5: aload_2
         6: ifnonnull     10
         9: return
        10: aload_0
        11: aload_2
        12: invokevirtual #1273               // Method getVehicleMaxHearts:(Lnet/minecraft/world/entity/LivingEntity;)I
        15: istore_3
        16: iload_3
        17: ifne          21
        20: return
        21: aload_2
        22: invokevirtual #1438               // Method net/minecraft/world/entity/LivingEntity.getHealth:()F
        25: f2d
        26: invokestatic  #1191               // Method java/lang/Math.ceil:(D)D
        29: d2i
        30: istore        4
        32: invokestatic  #390                // Method net/minecraft/util/profiling/Profiler.get:()Lnet/minecraft/util/profiling/ProfilerFiller;
        35: ldc_w         #1439               // String mountHealth
        38: invokeinterface #1262,  2         // InterfaceMethod net/minecraft/util/profiling/ProfilerFiller.popPush:(Ljava/lang/String;)V
        43: aload_1
        44: invokevirtual #412                // Method net/minecraft/client/gui/GuiGraphicsExtractor.guiHeight:()I
        47: bipush        39
        49: isub
        50: istore        5
        52: aload_1
        53: invokevirtual #409                // Method net/minecraft/client/gui/GuiGraphicsExtractor.guiWidth:()I
        56: iconst_2
        57: idiv
        58: bipush        91
        60: iadd
        61: istore        6
        63: iload         5
        65: istore        7
        67: iconst_0
        68: istore        8
        70: iload_3
        71: ifle          207
        74: iload_3
        75: bipush        10
        77: invokestatic  #1441               // Method java/lang/Math.min:(II)I
        80: istore        9
        82: iload_3
        83: iload         9
        85: isub
        86: istore_3
        87: iconst_0
        88: istore        10
        90: iload         10
        92: iload         9
        94: if_icmpge     198
        97: iload         6
        99: iload         10
       101: bipush        8
       103: imul
       104: isub
       105: bipush        9
       107: isub
       108: istore        11
       110: aload_1
       111: getstatic     #825                // Field net/minecraft/client/renderer/RenderPipelines.GUI_TEXTURED:Lcom/mojang/blaze3d/pipeline/RenderPipeline;
       114: getstatic     #1444               // Field HEART_VEHICLE_CONTAINER_SPRITE:Lnet/minecraft/resources/Identifier;
       117: iload         11
       119: iload         7
       121: bipush        9
       123: bipush        9
       125: invokevirtual #663                // Method net/minecraft/client/gui/GuiGraphicsExtractor.blitSprite:(Lcom/mojang/blaze3d/pipeline/RenderPipeline;Lnet/minecraft/resources/Identifier;IIII)V
       128: iload         10
       130: iconst_2
       131: imul
       132: iconst_1
       133: iadd
       134: iload         8
       136: iadd
       137: iload         4
       139: if_icmpge     160
       142: aload_1
       143: getstatic     #825                // Field net/minecraft/client/renderer/RenderPipelines.GUI_TEXTURED:Lcom/mojang/blaze3d/pipeline/RenderPipeline;
       146: getstatic     #1447               // Field HEART_VEHICLE_FULL_SPRITE:Lnet/minecraft/resources/Identifier;
       149: iload         11
       151: iload         7
       153: bipush        9
       155: bipush        9
       157: invokevirtual #663                // Method net/minecraft/client/gui/GuiGraphicsExtractor.blitSprite:(Lcom/mojang/blaze3d/pipeline/RenderPipeline;Lnet/minecraft/resources/Identifier;IIII)V
       160: iload         10
       162: iconst_2
       163: imul
       164: iconst_1
       165: iadd
       166: iload         8
       168: iadd
       169: iload         4
       171: if_icmpne     192
       174: aload_1
       175: getstatic     #825                // Field net/minecraft/client/renderer/RenderPipelines.GUI_TEXTURED:Lcom/mojang/blaze3d/pipeline/RenderPipeline;
       178: getstatic     #1450               // Field HEART_VEHICLE_HALF_SPRITE:Lnet/minecraft/resources/Identifier;
       181: iload         11
       183: iload         7
       185: bipush        9
       187: bipush        9
       189: invokevirtual #663                // Method net/minecraft/client/gui/GuiGraphicsExtractor.blitSprite:(Lcom/mojang/blaze3d/pipeline/RenderPipeline;Lnet/minecraft/resources/Identifier;IIII)V
       192: iinc          10, 1
       195: goto          90
       198: iinc          7, -10
       201: iinc          8, 20
       204: goto          70
       207: return

  private void extractTextureOverlay(net.minecraft.client.gui.GuiGraphicsExtractor, net.minecraft.resources.Identifier, float);
    Code:
         0: fload_3
         1: invokestatic  #853                // Method net/minecraft/util/ARGB.white:(F)I
         4: istore        4
         6: aload_1
         7: getstatic     #825                // Field net/minecraft/client/renderer/RenderPipelines.GUI_TEXTURED:Lcom/mojang/blaze3d/pipeline/RenderPipeline;
        10: aload_2
        11: iconst_0
        12: iconst_0
        13: fconst_0
        14: fconst_0
        15: aload_1
        16: invokevirtual #409                // Method net/minecraft/client/gui/GuiGraphicsExtractor.guiWidth:()I
        19: aload_1
        20: invokevirtual #412                // Method net/minecraft/client/gui/GuiGraphicsExtractor.guiHeight:()I
        23: aload_1
        24: invokevirtual #409                // Method net/minecraft/client/gui/GuiGraphicsExtractor.guiWidth:()I
        27: aload_1
        28: invokevirtual #412                // Method net/minecraft/client/gui/GuiGraphicsExtractor.guiHeight:()I
        31: iload         4
        33: invokevirtual #1453               // Method net/minecraft/client/gui/GuiGraphicsExtractor.blit:(Lcom/mojang/blaze3d/pipeline/RenderPipeline;Lnet/minecraft/resources/Identifier;IIFFIIIII)V
        36: return

  private void extractSpyglassOverlay(net.minecraft.client.gui.GuiGraphicsExtractor, float);
    Code:
         0: aload_1
         1: invokevirtual #409                // Method net/minecraft/client/gui/GuiGraphicsExtractor.guiWidth:()I
         4: aload_1
         5: invokevirtual #412                // Method net/minecraft/client/gui/GuiGraphicsExtractor.guiHeight:()I
         8: invokestatic  #1441               // Method java/lang/Math.min:(II)I
        11: i2f
        12: fstore_3
        13: fload_3
        14: fstore        4
        16: aload_1
        17: invokevirtual #409                // Method net/minecraft/client/gui/GuiGraphicsExtractor.guiWidth:()I
        20: i2f
        21: fload_3
        22: fdiv
        23: aload_1
        24: invokevirtual #412                // Method net/minecraft/client/gui/GuiGraphicsExtractor.guiHeight:()I
        27: i2f
        28: fload         4
        30: fdiv
        31: invokestatic  #1457               // Method java/lang/Math.min:(FF)F
        34: fload_2
        35: fmul
        36: fstore        5
        38: fload_3
        39: fload         5
        41: fmul
        42: invokestatic  #1459               // Method net/minecraft/util/Mth.floor:(F)I
        45: istore        6
        47: fload         4
        49: fload         5
        51: fmul
        52: invokestatic  #1459               // Method net/minecraft/util/Mth.floor:(F)I
        55: istore        7
        57: aload_1
        58: invokevirtual #409                // Method net/minecraft/client/gui/GuiGraphicsExtractor.guiWidth:()I
        61: iload         6
        63: isub
        64: iconst_2
        65: idiv
        66: istore        8
        68: aload_1
        69: invokevirtual #412                // Method net/minecraft/client/gui/GuiGraphicsExtractor.guiHeight:()I
        72: iload         7
        74: isub
        75: iconst_2
        76: idiv
        77: istore        9
        79: iload         8
        81: iload         6
        83: iadd
        84: istore        10
        86: iload         9
        88: iload         7
        90: iadd
        91: istore        11
        93: aload_1
        94: getstatic     #825                // Field net/minecraft/client/renderer/RenderPipelines.GUI_TEXTURED:Lcom/mojang/blaze3d/pipeline/RenderPipeline;
        97: getstatic     #1461               // Field SPYGLASS_SCOPE_LOCATION:Lnet/minecraft/resources/Identifier;
       100: iload         8
       102: iload         9
       104: fconst_0
       105: fconst_0
       106: iload         6
       108: iload         7
       110: iload         6
       112: iload         7
       114: invokevirtual #1464               // Method net/minecraft/client/gui/GuiGraphicsExtractor.blit:(Lcom/mojang/blaze3d/pipeline/RenderPipeline;Lnet/minecraft/resources/Identifier;IIFFIIII)V
       117: aload_1
       118: getstatic     #1467               // Field net/minecraft/client/renderer/RenderPipelines.GUI:Lcom/mojang/blaze3d/pipeline/RenderPipeline;
       121: iconst_0
       122: iload         11
       124: aload_1
       125: invokevirtual #409                // Method net/minecraft/client/gui/GuiGraphicsExtractor.guiWidth:()I
       128: aload_1
       129: invokevirtual #412                // Method net/minecraft/client/gui/GuiGraphicsExtractor.guiHeight:()I
       132: ldc_w         #1470               // int -16777216
       135: invokevirtual #1471               // Method net/minecraft/client/gui/GuiGraphicsExtractor.fill:(Lcom/mojang/blaze3d/pipeline/RenderPipeline;IIIII)V
       138: aload_1
       139: getstatic     #1467               // Field net/minecraft/client/renderer/RenderPipelines.GUI:Lcom/mojang/blaze3d/pipeline/RenderPipeline;
       142: iconst_0
       143: iconst_0
       144: aload_1
       145: invokevirtual #409                // Method net/minecraft/client/gui/GuiGraphicsExtractor.guiWidth:()I
       148: iload         9
       150: ldc_w         #1470               // int -16777216
       153: invokevirtual #1471               // Method net/minecraft/client/gui/GuiGraphicsExtractor.fill:(Lcom/mojang/blaze3d/pipeline/RenderPipeline;IIIII)V
       156: aload_1
       157: getstatic     #1467               // Field net/minecraft/client/renderer/RenderPipelines.GUI:Lcom/mojang/blaze3d/pipeline/RenderPipeline;
       160: iconst_0
       161: iload         9
       163: iload         8
       165: iload         11
       167: ldc_w         #1470               // int -16777216
       170: invokevirtual #1471               // Method net/minecraft/client/gui/GuiGraphicsExtractor.fill:(Lcom/mojang/blaze3d/pipeline/RenderPipeline;IIIII)V
       173: aload_1
       174: getstatic     #1467               // Field net/minecraft/client/renderer/RenderPipelines.GUI:Lcom/mojang/blaze3d/pipeline/RenderPipeline;
       177: iload         10
       179: iload         9
       181: aload_1
       182: invokevirtual #409                // Method net/minecraft/client/gui/GuiGraphicsExtractor.guiWidth:()I
       185: iload         11
       187: ldc_w         #1470               // int -16777216
       190: invokevirtual #1471               // Method net/minecraft/client/gui/GuiGraphicsExtractor.fill:(Lcom/mojang/blaze3d/pipeline/RenderPipeline;IIIII)V
       193: return

  private void updateVignetteBrightness(net.minecraft.world.entity.Entity);
    Code:
         0: aload_1
         1: invokevirtual #1474               // Method net/minecraft/world/entity/Entity.getX:()D
         4: aload_1
         5: invokevirtual #1478               // Method net/minecraft/world/entity/Entity.getEyeY:()D
         8: aload_1
         9: invokevirtual #1481               // Method net/minecraft/world/entity/Entity.getZ:()D
        12: invokestatic  #1484               // Method net/minecraft/core/BlockPos.containing:(DDD)Lnet/minecraft/core/BlockPos;
        15: astore_2
        16: aload_1
        17: invokevirtual #1490               // Method net/minecraft/world/entity/Entity.level:()Lnet/minecraft/world/level/Level;
        20: invokevirtual #1491               // Method net/minecraft/world/level/Level.dimensionType:()Lnet/minecraft/world/level/dimension/DimensionType;
        23: aload_1
        24: invokevirtual #1490               // Method net/minecraft/world/entity/Entity.level:()Lnet/minecraft/world/level/Level;
        27: aload_2
        28: invokevirtual #1495               // Method net/minecraft/world/level/Level.getMaxLocalRawBrightness:(Lnet/minecraft/core/BlockPos;)I
        31: invokestatic  #1499               // Method net/minecraft/client/renderer/Lightmap.getBrightness:(Lnet/minecraft/world/level/dimension/DimensionType;I)F
        34: fstore_3
        35: fconst_1
        36: fload_3
        37: fsub
        38: fconst_0
        39: fconst_1
        40: invokestatic  #841                // Method net/minecraft/util/Mth.clamp:(FFF)F
        43: fstore        4
        45: aload_0
        46: dup
        47: getfield      #21                 // Field vignetteBrightness:F
        50: fload         4
        52: aload_0
        53: getfield      #21                 // Field vignetteBrightness:F
        56: fsub
        57: ldc_w         #1505               // float 0.01f
        60: fmul
        61: fadd
        62: putfield      #21                 // Field vignetteBrightness:F
        65: return

  private void extractVignette(net.minecraft.client.gui.GuiGraphicsExtractor, net.minecraft.world.entity.Entity);
    Code:
         0: aload_0
         1: getfield      #54                 // Field minecraft:Lnet/minecraft/client/Minecraft;
         4: getfield      #534                // Field net/minecraft/client/Minecraft.level:Lnet/minecraft/client/multiplayer/ClientLevel;
         7: invokevirtual #1506               // Method net/minecraft/client/multiplayer/ClientLevel.getWorldBorder:()Lnet/minecraft/world/level/border/WorldBorder;
        10: astore_3
        11: fconst_0
        12: fstore        4
        14: aload_2
        15: ifnull        85
        18: aload_3
        19: aload_2
        20: invokevirtual #1510               // Method net/minecraft/world/level/border/WorldBorder.getDistanceToBorder:(Lnet/minecraft/world/entity/Entity;)D
        23: d2f
        24: fstore        5
        26: aload_3
        27: invokevirtual #1516               // Method net/minecraft/world/level/border/WorldBorder.getLerpSpeed:()D
        30: aload_3
        31: invokevirtual #1519               // Method net/minecraft/world/level/border/WorldBorder.getWarningTime:()I
        34: i2d
        35: dmul
        36: aload_3
        37: invokevirtual #1522               // Method net/minecraft/world/level/border/WorldBorder.getLerpTarget:()D
        40: aload_3
        41: invokevirtual #1525               // Method net/minecraft/world/level/border/WorldBorder.getSize:()D
        44: dsub
        45: invokestatic  #1528               // Method java/lang/Math.abs:(D)D
        48: invokestatic  #1531               // Method java/lang/Math.min:(DD)D
        51: dstore        6
        53: aload_3
        54: invokevirtual #1534               // Method net/minecraft/world/level/border/WorldBorder.getWarningBlocks:()I
        57: i2d
        58: dload         6
        60: invokestatic  #1537               // Method java/lang/Math.max:(DD)D
        63: dstore        8
        65: fload         5
        67: f2d
        68: dload         8
        70: dcmpg
        71: ifge          85
        74: fconst_1
        75: fload         5
        77: f2d
        78: dload         8
        80: ddiv
        81: d2f
        82: fsub
        83: fstore        4
        85: aload_0
        86: getfield      #21                 // Field vignetteBrightness:F
        89: fconst_0
        90: fconst_1
        91: invokestatic  #841                // Method net/minecraft/util/Mth.clamp:(FFF)F
        94: fstore        6
        96: fload         4
        98: fconst_0
        99: fcmpl
       100: ifle          148
       103: fload         4
       105: fconst_0
       106: fconst_1
       107: invokestatic  #841                // Method net/minecraft/util/Mth.clamp:(FFF)F
       110: fstore        4
       112: fload         6
       114: fconst_1
       115: fload         4
       117: fsub
       118: fmul
       119: fstore        7
       121: fload         6
       123: fconst_1
       124: fload         6
       126: fsub
       127: fload         4
       129: fmul
       130: fadd
       131: fstore        8
       133: fconst_1
       134: fload         7
       136: fload         8
       138: fload         8
       140: invokestatic  #1539               // Method net/minecraft/util/ARGB.colorFromFloat:(FFFF)I
       143: istore        5
       145: goto          160
       148: fconst_1
       149: fload         6
       151: fload         6
       153: fload         6
       155: invokestatic  #1539               // Method net/minecraft/util/ARGB.colorFromFloat:(FFFF)I
       158: istore        5
       160: aload_1
       161: getstatic     #1543               // Field net/minecraft/client/renderer/RenderPipelines.VIGNETTE:Lcom/mojang/blaze3d/pipeline/RenderPipeline;
       164: getstatic     #1546               // Field VIGNETTE_LOCATION:Lnet/minecraft/resources/Identifier;
       167: iconst_0
       168: iconst_0
       169: fconst_0
       170: fconst_0
       171: aload_1
       172: invokevirtual #409                // Method net/minecraft/client/gui/GuiGraphicsExtractor.guiWidth:()I
       175: aload_1
       176: invokevirtual #412                // Method net/minecraft/client/gui/GuiGraphicsExtractor.guiHeight:()I
       179: aload_1
       180: invokevirtual #409                // Method net/minecraft/client/gui/GuiGraphicsExtractor.guiWidth:()I
       183: aload_1
       184: invokevirtual #412                // Method net/minecraft/client/gui/GuiGraphicsExtractor.guiHeight:()I
       187: iload         5
       189: invokevirtual #1453               // Method net/minecraft/client/gui/GuiGraphicsExtractor.blit:(Lcom/mojang/blaze3d/pipeline/RenderPipeline;Lnet/minecraft/resources/Identifier;IIFFIIIII)V
       192: return

  private void extractPortalOverlay(net.minecraft.client.gui.GuiGraphicsExtractor, float);
    Code:
         0: fload_2
         1: fconst_1
         2: fcmpg
         3: ifge          24
         6: fload_2
         7: fload_2
         8: fmul
         9: fstore_2
        10: fload_2
        11: fload_2
        12: fmul
        13: fstore_2
        14: fload_2
        15: ldc_w         #1549               // float 0.8f
        18: fmul
        19: ldc_w         #1550               // float 0.2f
        22: fadd
        23: fstore_2
        24: fload_2
        25: invokestatic  #853                // Method net/minecraft/util/ARGB.white:(F)I
        28: istore_3
        29: aload_0
        30: getfield      #54                 // Field minecraft:Lnet/minecraft/client/Minecraft;
        33: invokevirtual #1551               // Method net/minecraft/client/Minecraft.getModelManager:()Lnet/minecraft/client/resources/model/ModelManager;
        36: invokevirtual #1555               // Method net/minecraft/client/resources/model/ModelManager.getBlockStateModelSet:()Lnet/minecraft/client/renderer/block/BlockStateModelSet;
        39: getstatic     #1561               // Field net/minecraft/world/level/block/Blocks.NETHER_PORTAL:Lnet/minecraft/world/level/block/Block;
        42: invokevirtual #1567               // Method net/minecraft/world/level/block/Block.defaultBlockState:()Lnet/minecraft/world/level/block/state/BlockState;
        45: invokevirtual #1573               // Method net/minecraft/client/renderer/block/BlockStateModelSet.getParticleMaterial:(Lnet/minecraft/world/level/block/state/BlockState;)Lnet/minecraft/client/resources/model/sprite/Material$Baked;
        48: invokevirtual #1579               // Method net/minecraft/client/resources/model/sprite/Material$Baked.sprite:()Lnet/minecraft/client/renderer/texture/TextureAtlasSprite;
        51: astore        4
        53: aload_1
        54: getstatic     #825                // Field net/minecraft/client/renderer/RenderPipelines.GUI_TEXTURED:Lcom/mojang/blaze3d/pipeline/RenderPipeline;
        57: aload         4
        59: iconst_0
        60: iconst_0
        61: aload_1
        62: invokevirtual #409                // Method net/minecraft/client/gui/GuiGraphicsExtractor.guiWidth:()I
        65: aload_1
        66: invokevirtual #412                // Method net/minecraft/client/gui/GuiGraphicsExtractor.guiHeight:()I
        69: iload_3
        70: invokevirtual #1585               // Method net/minecraft/client/gui/GuiGraphicsExtractor.blitSprite:(Lcom/mojang/blaze3d/pipeline/RenderPipeline;Lnet/minecraft/client/renderer/texture/TextureAtlasSprite;IIIII)V
        73: return

  private void extractConfusionOverlay(net.minecraft.client.gui.GuiGraphicsExtractor, float);
    Code:
         0: aload_1
         1: invokevirtual #409                // Method net/minecraft/client/gui/GuiGraphicsExtractor.guiWidth:()I
         4: istore_3
         5: aload_1
         6: invokevirtual #412                // Method net/minecraft/client/gui/GuiGraphicsExtractor.guiHeight:()I
         9: istore        4
        11: aload_1
        12: invokevirtual #437                // Method net/minecraft/client/gui/GuiGraphicsExtractor.pose:()Lorg/joml/Matrix3x2fStack;
        15: invokevirtual #441                // Method org/joml/Matrix3x2fStack.pushMatrix:()Lorg/joml/Matrix3x2fStack;
        18: pop
        19: fload_2
        20: fconst_2
        21: fconst_1
        22: invokestatic  #269                // Method net/minecraft/util/Mth.lerp:(FFF)F
        25: fstore        5
        27: aload_1
        28: invokevirtual #437                // Method net/minecraft/client/gui/GuiGraphicsExtractor.pose:()Lorg/joml/Matrix3x2fStack;
        31: iload_3
        32: i2f
        33: fconst_2
        34: fdiv
        35: iload         4
        37: i2f
        38: fconst_2
        39: fdiv
        40: invokevirtual #446                // Method org/joml/Matrix3x2fStack.translate:(FF)Lorg/joml/Matrix3x2f;
        43: pop
        44: aload_1
        45: invokevirtual #437                // Method net/minecraft/client/gui/GuiGraphicsExtractor.pose:()Lorg/joml/Matrix3x2fStack;
        48: fload         5
        50: fload         5
        52: invokevirtual #492                // Method org/joml/Matrix3x2fStack.scale:(FF)Lorg/joml/Matrix3x2f;
        55: pop
        56: aload_1
        57: invokevirtual #437                // Method net/minecraft/client/gui/GuiGraphicsExtractor.pose:()Lorg/joml/Matrix3x2fStack;
        60: iload_3
        61: ineg
        62: i2f
        63: fconst_2
        64: fdiv
        65: iload         4
        67: ineg
        68: i2f
        69: fconst_2
        70: fdiv
        71: invokevirtual #446                // Method org/joml/Matrix3x2fStack.translate:(FF)Lorg/joml/Matrix3x2f;
        74: pop
        75: ldc_w         #1550               // float 0.2f
        78: fload_2
        79: fmul
        80: fstore        6
        82: ldc_w         #1172               // float 0.4f
        85: fload_2
        86: fmul
        87: fstore        7
        89: ldc_w         #1550               // float 0.2f
        92: fload_2
        93: fmul
        94: fstore        8
        96: aload_1
        97: getstatic     #1588               // Field net/minecraft/client/renderer/RenderPipelines.GUI_NAUSEA_OVERLAY:Lcom/mojang/blaze3d/pipeline/RenderPipeline;
       100: getstatic     #1591               // Field NAUSEA_LOCATION:Lnet/minecraft/resources/Identifier;
       103: iconst_0
       104: iconst_0
       105: fconst_0
       106: fconst_0
       107: iload_3
       108: iload         4
       110: iload_3
       111: iload         4
       113: fconst_1
       114: fload         6
       116: fload         7
       118: fload         8
       120: invokestatic  #1539               // Method net/minecraft/util/ARGB.colorFromFloat:(FFFF)I
       123: invokevirtual #1453               // Method net/minecraft/client/gui/GuiGraphicsExtractor.blit:(Lcom/mojang/blaze3d/pipeline/RenderPipeline;Lnet/minecraft/resources/Identifier;IIFFIIIII)V
       126: aload_1
       127: invokevirtual #437                // Method net/minecraft/client/gui/GuiGraphicsExtractor.pose:()Lorg/joml/Matrix3x2fStack;
       130: invokevirtual #476                // Method org/joml/Matrix3x2fStack.popMatrix:()Lorg/joml/Matrix3x2fStack;
       133: pop
       134: return

  private void extractSlot(net.minecraft.client.gui.GuiGraphicsExtractor, int, int, net.minecraft.client.DeltaTracker, net.minecraft.world.entity.player.Player, net.minecraft.world.item.ItemStack, int);
    Code:
         0: aload         6
         2: invokevirtual #967                // Method net/minecraft/world/item/ItemStack.isEmpty:()Z
         5: ifeq          9
         8: return
         9: aload         6
        11: invokevirtual #1594               // Method net/minecraft/world/item/ItemStack.getPopTime:()I
        14: i2f
        15: aload         4
        17: iconst_0
        18: invokeinterface #353,  2          // InterfaceMethod net/minecraft/client/DeltaTracker.getGameTimeDeltaPartialTick:(Z)F
        23: fsub
        24: fstore        8
        26: fload         8
        28: fconst_0
        29: fcmpl
        30: ifle          107
        33: fconst_1
        34: fload         8
        36: ldc_w         #688                // float 5.0f
        39: fdiv
        40: fadd
        41: fstore        9
        43: aload_1
        44: invokevirtual #437                // Method net/minecraft/client/gui/GuiGraphicsExtractor.pose:()Lorg/joml/Matrix3x2fStack;
        47: invokevirtual #441                // Method org/joml/Matrix3x2fStack.pushMatrix:()Lorg/joml/Matrix3x2fStack;
        50: pop
        51: aload_1
        52: invokevirtual #437                // Method net/minecraft/client/gui/GuiGraphicsExtractor.pose:()Lorg/joml/Matrix3x2fStack;
        55: iload_2
        56: bipush        8
        58: iadd
        59: i2f
        60: iload_3
        61: bipush        12
        63: iadd
        64: i2f
        65: invokevirtual #446                // Method org/joml/Matrix3x2fStack.translate:(FF)Lorg/joml/Matrix3x2f;
        68: pop
        69: aload_1
        70: invokevirtual #437                // Method net/minecraft/client/gui/GuiGraphicsExtractor.pose:()Lorg/joml/Matrix3x2fStack;
        73: fconst_1
        74: fload         9
        76: fdiv
        77: fload         9
        79: fconst_1
        80: fadd
        81: fconst_2
        82: fdiv
        83: invokevirtual #492                // Method org/joml/Matrix3x2fStack.scale:(FF)Lorg/joml/Matrix3x2f;
        86: pop
        87: aload_1
        88: invokevirtual #437                // Method net/minecraft/client/gui/GuiGraphicsExtractor.pose:()Lorg/joml/Matrix3x2fStack;
        91: iload_2
        92: bipush        8
        94: iadd
        95: ineg
        96: i2f
        97: iload_3
        98: bipush        12
       100: iadd
       101: ineg
       102: i2f
       103: invokevirtual #446                // Method org/joml/Matrix3x2fStack.translate:(FF)Lorg/joml/Matrix3x2f;
       106: pop
       107: aload_1
       108: aload         5
       110: aload         6
       112: iload_2
       113: iload_3
       114: iload         7
       116: invokevirtual #1597               // Method net/minecraft/client/gui/GuiGraphicsExtractor.item:(Lnet/minecraft/world/entity/LivingEntity;Lnet/minecraft/world/item/ItemStack;III)V
       119: fload         8
       121: fconst_0
       122: fcmpl
       123: ifle          134
       126: aload_1
       127: invokevirtual #437                // Method net/minecraft/client/gui/GuiGraphicsExtractor.pose:()Lorg/joml/Matrix3x2fStack;
       130: invokevirtual #476                // Method org/joml/Matrix3x2fStack.popMatrix:()Lorg/joml/Matrix3x2fStack;
       133: pop
       134: aload_1
       135: aload_0
       136: getfield      #54                 // Field minecraft:Lnet/minecraft/client/Minecraft;
       139: getfield      #917                // Field net/minecraft/client/Minecraft.font:Lnet/minecraft/client/gui/Font;
       142: aload         6
       144: iload_2
       145: iload_3
       146: invokevirtual #1601               // Method net/minecraft/client/gui/GuiGraphicsExtractor.itemDecorations:(Lnet/minecraft/client/gui/Font;Lnet/minecraft/world/item/ItemStack;II)V
       149: return

  public void tick(boolean);
    Code:
         0: aload_0
         1: invokevirtual #1605               // Method tickAutosaveIndicator:()V
         4: iload_1
         5: ifne          12
         8: aload_0
         9: invokevirtual #1608               // Method tick:()V
        12: return

  private void tick();
    Code:
         0: aload_0
         1: getfield      #430                // Field overlayMessageTime:I
         4: ifle          17
         7: aload_0
         8: dup
         9: getfield      #430                // Field overlayMessageTime:I
        12: iconst_1
        13: isub
        14: putfield      #430                // Field overlayMessageTime:I
        17: aload_0
        18: getfield      #482                // Field titleTime:I
        21: ifle          51
        24: aload_0
        25: dup
        26: getfield      #482                // Field titleTime:I
        29: iconst_1
        30: isub
        31: putfield      #482                // Field titleTime:I
        34: aload_0
        35: getfield      #482                // Field titleTime:I
        38: ifgt          51
        41: aload_0
        42: aconst_null
        43: putfield      #479                // Field title:Lnet/minecraft/network/chat/Component;
        46: aload_0
        47: aconst_null
        48: putfield      #495                // Field subtitle:Lnet/minecraft/network/chat/Component;
        51: aload_0
        52: dup
        53: getfield      #522                // Field tickCount:I
        56: iconst_1
        57: iadd
        58: putfield      #522                // Field tickCount:I
        61: aload_0
        62: getfield      #54                 // Field minecraft:Lnet/minecraft/client/Minecraft;
        65: invokevirtual #246                // Method net/minecraft/client/Minecraft.getCameraEntity:()Lnet/minecraft/world/entity/Entity;
        68: astore_1
        69: aload_1
        70: ifnull        78
        73: aload_0
        74: aload_1
        75: invokevirtual #1611               // Method updateVignetteBrightness:(Lnet/minecraft/world/entity/Entity;)V
        78: aload_0
        79: getfield      #54                 // Field minecraft:Lnet/minecraft/client/Minecraft;
        82: getfield      #254                // Field net/minecraft/client/Minecraft.player:Lnet/minecraft/client/player/LocalPlayer;
        85: ifnull        213
        88: aload_0
        89: getfield      #54                 // Field minecraft:Lnet/minecraft/client/Minecraft;
        92: getfield      #254                // Field net/minecraft/client/Minecraft.player:Lnet/minecraft/client/player/LocalPlayer;
        95: invokevirtual #1615               // Method net/minecraft/client/player/LocalPlayer.getInventory:()Lnet/minecraft/world/entity/player/Inventory;
        98: invokevirtual #1616               // Method net/minecraft/world/entity/player/Inventory.getSelectedItem:()Lnet/minecraft/world/item/ItemStack;
       101: astore_2
       102: aload_2
       103: invokevirtual #967                // Method net/minecraft/world/item/ItemStack.isEmpty:()Z
       106: ifeq          117
       109: aload_0
       110: iconst_0
       111: putfield      #999                // Field toolHighlightTimer:I
       114: goto          208
       117: aload_0
       118: getfield      #31                 // Field lastToolHighlight:Lnet/minecraft/world/item/ItemStack;
       121: invokevirtual #967                // Method net/minecraft/world/item/ItemStack.isEmpty:()Z
       124: ifne          160
       127: aload_2
       128: aload_0
       129: getfield      #31                 // Field lastToolHighlight:Lnet/minecraft/world/item/ItemStack;
       132: invokevirtual #1619               // Method net/minecraft/world/item/ItemStack.getItem:()Lnet/minecraft/world/item/Item;
       135: invokevirtual #1622               // Method net/minecraft/world/item/ItemStack.is:(Ljava/lang/Object;)Z
       138: ifeq          160
       141: aload_2
       142: invokevirtual #1008               // Method net/minecraft/world/item/ItemStack.getHoverName:()Lnet/minecraft/network/chat/Component;
       145: aload_0
       146: getfield      #31                 // Field lastToolHighlight:Lnet/minecraft/world/item/ItemStack;
       149: invokevirtual #1008               // Method net/minecraft/world/item/ItemStack.getHoverName:()Lnet/minecraft/network/chat/Component;
       152: invokeinterface #1626,  2         // InterfaceMethod net/minecraft/network/chat/Component.equals:(Ljava/lang/Object;)Z
       157: ifne          191
       160: aload_0
       161: ldc2_w        #1629               // double 40.0d
       164: aload_0
       165: getfield      #54                 // Field minecraft:Lnet/minecraft/client/Minecraft;
       168: getfield      #152                // Field net/minecraft/client/Minecraft.options:Lnet/minecraft/client/Options;
       171: invokevirtual #1631               // Method net/minecraft/client/Options.notificationDisplayTime:()Lnet/minecraft/client/OptionInstance;
       174: invokevirtual #236                // Method net/minecraft/client/OptionInstance.get:()Ljava/lang/Object;
       177: checkcast     #379                // class java/lang/Double
       180: invokevirtual #1634               // Method java/lang/Double.doubleValue:()D
       183: dmul
       184: d2i
       185: putfield      #999                // Field toolHighlightTimer:I
       188: goto          208
       191: aload_0
       192: getfield      #999                // Field toolHighlightTimer:I
       195: ifle          208
       198: aload_0
       199: dup
       200: getfield      #999                // Field toolHighlightTimer:I
       203: iconst_1
       204: isub
       205: putfield      #999                // Field toolHighlightTimer:I
       208: aload_0
       209: aload_2
       210: putfield      #31                 // Field lastToolHighlight:Lnet/minecraft/world/item/ItemStack;
       213: aload_0
       214: getfield      #77                 // Field chat:Lnet/minecraft/client/gui/components/ChatComponent;
       217: invokevirtual #1637               // Method net/minecraft/client/gui/components/ChatComponent.tick:()V
       220: return

  private void tickAutosaveIndicator();
    Code:
         0: aload_0
         1: getfield      #54                 // Field minecraft:Lnet/minecraft/client/Minecraft;
         4: invokevirtual #1638               // Method net/minecraft/client/Minecraft.getSingleplayerServer:()Lnet/minecraft/client/server/IntegratedServer;
         7: astore_1
         8: aload_1
         9: ifnull        23
        12: aload_1
        13: invokevirtual #1642               // Method net/minecraft/server/MinecraftServer.isCurrentlySaving:()Z
        16: ifeq          23
        19: iconst_1
        20: goto          24
        23: iconst_0
        24: istore_2
        25: aload_0
        26: aload_0
        27: getfield      #1647               // Field autosaveIndicatorValue:F
        30: putfield      #1650               // Field lastAutosaveIndicatorValue:F
        33: aload_0
        34: ldc_w         #1550               // float 0.2f
        37: aload_0
        38: getfield      #1647               // Field autosaveIndicatorValue:F
        41: iload_2
        42: ifeq          49
        45: fconst_1
        46: goto          50
        49: fconst_0
        50: invokestatic  #269                // Method net/minecraft/util/Mth.lerp:(FFF)F
        53: putfield      #1647               // Field autosaveIndicatorValue:F
        56: return

  public void setNowPlaying(net.minecraft.network.chat.Component);
    Code:
         0: ldc_w         #1653               // String record.nowPlaying
         3: iconst_1
         4: anewarray     #6                  // class java/lang/Object
         7: dup
         8: iconst_0
         9: aload_1
        10: aastore
        11: invokestatic  #1075               // InterfaceMethod net/minecraft/network/chat/Component.translatable:(Ljava/lang/String;[Ljava/lang/Object;)Lnet/minecraft/network/chat/MutableComponent;
        14: astore_2
        15: aload_0
        16: aload_2
        17: iconst_1
        18: invokevirtual #1655               // Method setOverlayMessage:(Lnet/minecraft/network/chat/Component;Z)V
        21: aload_0
        22: getfield      #54                 // Field minecraft:Lnet/minecraft/client/Minecraft;
        25: invokevirtual #1659               // Method net/minecraft/client/Minecraft.getNarrator:()Lnet/minecraft/client/GameNarrator;
        28: aload_2
        29: invokevirtual #1663               // Method net/minecraft/client/GameNarrator.saySystemNow:(Lnet/minecraft/network/chat/Component;)V
        32: return

  public void setOverlayMessage(net.minecraft.network.chat.Component, boolean);
    Code:
         0: aload_0
         1: aload_1
         2: putfield      #426                // Field overlayMessageString:Lnet/minecraft/network/chat/Component;
         5: aload_0
         6: bipush        60
         8: putfield      #430                // Field overlayMessageTime:I
        11: aload_0
        12: iload_2
        13: putfield      #450                // Field animateOverlayMessageColor:Z
        16: return

  public void setTimes(int, int, int);
    Code:
         0: iload_1
         1: iflt          9
         4: aload_0
         5: iload_1
         6: putfield      #134                // Field titleFadeInTime:I
         9: iload_2
        10: iflt          18
        13: aload_0
        14: iload_2
        15: putfield      #138                // Field titleStayTime:I
        18: iload_3
        19: iflt          27
        22: aload_0
        23: iload_3
        24: putfield      #141                // Field titleFadeOutTime:I
        27: aload_0
        28: getfield      #482                // Field titleTime:I
        31: ifle          52
        34: aload_0
        35: aload_0
        36: getfield      #134                // Field titleFadeInTime:I
        39: aload_0
        40: getfield      #138                // Field titleStayTime:I
        43: iadd
        44: aload_0
        45: getfield      #141                // Field titleFadeOutTime:I
        48: iadd
        49: putfield      #482                // Field titleTime:I
        52: return

  public void setSubtitle(net.minecraft.network.chat.Component);
    Code:
         0: aload_0
         1: aload_1
         2: putfield      #495                // Field subtitle:Lnet/minecraft/network/chat/Component;
         5: return

  public void setTitle(net.minecraft.network.chat.Component);
    Code:
         0: aload_0
         1: aload_1
         2: putfield      #479                // Field title:Lnet/minecraft/network/chat/Component;
         5: aload_0
         6: aload_0
         7: getfield      #134                // Field titleFadeInTime:I
        10: aload_0
        11: getfield      #138                // Field titleStayTime:I
        14: iadd
        15: aload_0
        16: getfield      #141                // Field titleFadeOutTime:I
        19: iadd
        20: putfield      #482                // Field titleTime:I
        23: return

  public void clearTitles();
    Code:
         0: aload_0
         1: aconst_null
         2: putfield      #479                // Field title:Lnet/minecraft/network/chat/Component;
         5: aload_0
         6: aconst_null
         7: putfield      #495                // Field subtitle:Lnet/minecraft/network/chat/Component;
        10: aload_0
        11: iconst_0
        12: putfield      #482                // Field titleTime:I
        15: return

  public net.minecraft.client.gui.components.ChatComponent getChat();
    Code:
         0: aload_0
         1: getfield      #77                 // Field chat:Lnet/minecraft/client/gui/components/ChatComponent;
         4: areturn

  public int getGuiTicks();
    Code:
         0: aload_0
         1: getfield      #522                // Field tickCount:I
         4: ireturn

  public net.minecraft.client.gui.Font getFont();
    Code:
         0: aload_0
         1: getfield      #54                 // Field minecraft:Lnet/minecraft/client/Minecraft;
         4: getfield      #917                // Field net/minecraft/client/Minecraft.font:Lnet/minecraft/client/gui/Font;
         7: areturn

  public net.minecraft.client.gui.components.spectator.SpectatorGui getSpectatorGui();
    Code:
         0: aload_0
         1: getfield      #70                 // Field spectatorGui:Lnet/minecraft/client/gui/components/spectator/SpectatorGui;
         4: areturn

  public net.minecraft.client.gui.components.PlayerTabOverlay getTabList();
    Code:
         0: aload_0
         1: getfield      #86                 // Field tabList:Lnet/minecraft/client/gui/components/PlayerTabOverlay;
         4: areturn

  public void onDisconnected();
    Code:
         0: aload_0
         1: getfield      #86                 // Field tabList:Lnet/minecraft/client/gui/components/PlayerTabOverlay;
         4: invokevirtual #1669               // Method net/minecraft/client/gui/components/PlayerTabOverlay.reset:()V
         7: aload_0
         8: getfield      #93                 // Field bossOverlay:Lnet/minecraft/client/gui/components/BossHealthOverlay;
        11: invokevirtual #1672               // Method net/minecraft/client/gui/components/BossHealthOverlay.reset:()V
        14: aload_0
        15: getfield      #54                 // Field minecraft:Lnet/minecraft/client/Minecraft;
        18: invokevirtual #1673               // Method net/minecraft/client/Minecraft.getToastManager:()Lnet/minecraft/client/gui/components/toasts/ToastManager;
        21: invokevirtual #1677               // Method net/minecraft/client/gui/components/toasts/ToastManager.clear:()V
        24: aload_0
        25: getfield      #63                 // Field debugOverlay:Lnet/minecraft/client/gui/components/DebugScreenOverlay;
        28: invokevirtual #1682               // Method net/minecraft/client/gui/components/DebugScreenOverlay.reset:()V
        31: aload_0
        32: getfield      #77                 // Field chat:Lnet/minecraft/client/gui/components/ChatComponent;
        35: iconst_1
        36: invokevirtual #1683               // Method net/minecraft/client/gui/components/ChatComponent.clearMessages:(Z)V
        39: aload_0
        40: invokevirtual #1686               // Method clearTitles:()V
        43: aload_0
        44: invokevirtual #131                // Method resetTitleTimes:()V
        47: return

  public net.minecraft.client.gui.components.BossHealthOverlay getBossOverlay();
    Code:
         0: aload_0
         1: getfield      #93                 // Field bossOverlay:Lnet/minecraft/client/gui/components/BossHealthOverlay;
         4: areturn

  public net.minecraft.client.gui.components.DebugScreenOverlay getDebugOverlay();
    Code:
         0: aload_0
         1: getfield      #63                 // Field debugOverlay:Lnet/minecraft/client/gui/components/DebugScreenOverlay;
         4: areturn

  public void clearCache();
    Code:
         0: aload_0
         1: getfield      #63                 // Field debugOverlay:Lnet/minecraft/client/gui/components/DebugScreenOverlay;
         4: invokevirtual #1689               // Method net/minecraft/client/gui/components/DebugScreenOverlay.clearChunkCache:()V
         7: return

  public void extractSavingIndicator(net.minecraft.client.gui.GuiGraphicsExtractor, net.minecraft.client.DeltaTracker);
    Code:
         0: aload_0
         1: getfield      #54                 // Field minecraft:Lnet/minecraft/client/Minecraft;
         4: getfield      #152                // Field net/minecraft/client/Minecraft.options:Lnet/minecraft/client/Options;
         7: invokevirtual #1692               // Method net/minecraft/client/Options.showAutosaveIndicator:()Lnet/minecraft/client/OptionInstance;
        10: invokevirtual #236                // Method net/minecraft/client/OptionInstance.get:()Ljava/lang/Object;
        13: checkcast     #241                // class java/lang/Boolean
        16: invokevirtual #243                // Method java/lang/Boolean.booleanValue:()Z
        19: ifeq          146
        22: aload_0
        23: getfield      #1647               // Field autosaveIndicatorValue:F
        26: fconst_0
        27: fcmpl
        28: ifgt          40
        31: aload_0
        32: getfield      #1650               // Field lastAutosaveIndicatorValue:F
        35: fconst_0
        36: fcmpl
        37: ifle          146
        40: ldc_w         #435                // float 255.0f
        43: aload_2
        44: invokeinterface #1695,  1         // InterfaceMethod net/minecraft/client/DeltaTracker.getRealtimeDeltaTicks:()F
        49: aload_0
        50: getfield      #1650               // Field lastAutosaveIndicatorValue:F
        53: aload_0
        54: getfield      #1647               // Field autosaveIndicatorValue:F
        57: invokestatic  #269                // Method net/minecraft/util/Mth.lerp:(FFF)F
        60: fconst_0
        61: fconst_1
        62: invokestatic  #841                // Method net/minecraft/util/Mth.clamp:(FFF)F
        65: fmul
        66: invokestatic  #1459               // Method net/minecraft/util/Mth.floor:(F)I
        69: istore_3
        70: iload_3
        71: ifle          146
        74: aload_0
        75: invokevirtual #422                // Method getFont:()Lnet/minecraft/client/gui/Font;
        78: astore        4
        80: aload         4
        82: getstatic     #1698               // Field SAVING_TEXT:Lnet/minecraft/network/chat/Component;
        85: invokevirtual #466                // Method net/minecraft/client/gui/Font.width:(Lnet/minecraft/network/chat/FormattedText;)I
        88: istore        5
        90: iload_3
        91: iconst_m1
        92: invokestatic  #1701               // Method net/minecraft/util/ARGB.color:(II)I
        95: istore        6
        97: aload_1
        98: invokevirtual #409                // Method net/minecraft/client/gui/GuiGraphicsExtractor.guiWidth:()I
       101: iload         5
       103: isub
       104: iconst_5
       105: isub
       106: istore        7
       108: aload_1
       109: invokevirtual #412                // Method net/minecraft/client/gui/GuiGraphicsExtractor.guiHeight:()I
       112: aload         4
       114: invokestatic  #1163               // Method java/util/Objects.requireNonNull:(Ljava/lang/Object;)Ljava/lang/Object;
       117: pop
       118: bipush        9
       120: isub
       121: iconst_5
       122: isub
       123: istore        8
       125: aload_1
       126: invokevirtual #169                // Method net/minecraft/client/gui/GuiGraphicsExtractor.nextStratum:()V
       129: aload_1
       130: aload         4
       132: getstatic     #1698               // Field SAVING_TEXT:Lnet/minecraft/network/chat/Component;
       135: iload         7
       137: iload         8
       139: iload         5
       141: iload         6
       143: invokevirtual #472                // Method net/minecraft/client/gui/GuiGraphicsExtractor.textWithBackdrop:(Lnet/minecraft/client/gui/Font;Lnet/minecraft/network/chat/Component;IIII)V
       146: return

  private boolean willPrioritizeExperienceInfo();
    Code:
         0: aload_0
         1: getfield      #54                 // Field minecraft:Lnet/minecraft/client/Minecraft;
         4: getfield      #254                // Field net/minecraft/client/Minecraft.player:Lnet/minecraft/client/player/LocalPlayer;
         7: getfield      #1703               // Field net/minecraft/client/player/LocalPlayer.experienceDisplayStartTick:I
        10: bipush        100
        12: iadd
        13: aload_0
        14: getfield      #54                 // Field minecraft:Lnet/minecraft/client/Minecraft;
        17: getfield      #254                // Field net/minecraft/client/Minecraft.player:Lnet/minecraft/client/player/LocalPlayer;
        20: getfield      #1706               // Field net/minecraft/client/player/LocalPlayer.tickCount:I
        23: if_icmple     30
        26: iconst_1
        27: goto          31
        30: iconst_0
        31: ireturn

  private boolean willPrioritizeJumpInfo();
    Code:
         0: aload_0
         1: getfield      #54                 // Field minecraft:Lnet/minecraft/client/Minecraft;
         4: getfield      #254                // Field net/minecraft/client/Minecraft.player:Lnet/minecraft/client/player/LocalPlayer;
         7: invokevirtual #1707               // Method net/minecraft/client/player/LocalPlayer.getJumpRidingScale:()F
        10: fconst_0
        11: fcmpl
        12: ifgt          46
        15: aload_0
        16: getfield      #54                 // Field minecraft:Lnet/minecraft/client/Minecraft;
        19: getfield      #254                // Field net/minecraft/client/Minecraft.player:Lnet/minecraft/client/player/LocalPlayer;
        22: invokevirtual #1710               // Method net/minecraft/client/player/LocalPlayer.jumpableVehicle:()Lnet/minecraft/world/entity/PlayerRideableJumping;
        25: invokedynamic #1714,  0           // InvokeDynamic #12:apply:()Ljava/util/function/Function;
        30: iconst_0
        31: invokestatic  #1715               // Method java/lang/Integer.valueOf:(I)Ljava/lang/Integer;
        34: invokestatic  #1721               // Method net/minecraft/Optionull.mapOrDefault:(Ljava/lang/Object;Ljava/util/function/Function;Ljava/lang/Object;)Ljava/lang/Object;
        37: checkcast     #1716               // class java/lang/Integer
        40: invokevirtual #1727               // Method java/lang/Integer.intValue:()I
        43: ifle          50
        46: iconst_1
        47: goto          51
        50: iconst_0
        51: ireturn

  private net.minecraft.client.gui.Gui$ContextualInfo nextContextualInfoState();
    Code:
         0: aload_0
         1: getfield      #54                 // Field minecraft:Lnet/minecraft/client/Minecraft;
         4: getfield      #254                // Field net/minecraft/client/Minecraft.player:Lnet/minecraft/client/player/LocalPlayer;
         7: getfield      #593                // Field net/minecraft/client/player/LocalPlayer.connection:Lnet/minecraft/client/multiplayer/ClientPacketListener;
        10: invokevirtual #1730               // Method net/minecraft/client/multiplayer/ClientPacketListener.getWaypointManager:()Lnet/minecraft/client/waypoints/ClientWaypointManager;
        13: invokevirtual #1734               // Method net/minecraft/client/waypoints/ClientWaypointManager.hasWaypoints:()Z
        16: istore_1
        17: aload_0
        18: getfield      #54                 // Field minecraft:Lnet/minecraft/client/Minecraft;
        21: getfield      #254                // Field net/minecraft/client/Minecraft.player:Lnet/minecraft/client/player/LocalPlayer;
        24: invokevirtual #1710               // Method net/minecraft/client/player/LocalPlayer.jumpableVehicle:()Lnet/minecraft/world/entity/PlayerRideableJumping;
        27: ifnull        34
        30: iconst_1
        31: goto          35
        34: iconst_0
        35: istore_2
        36: aload_0
        37: getfield      #54                 // Field minecraft:Lnet/minecraft/client/Minecraft;
        40: getfield      #615                // Field net/minecraft/client/Minecraft.gameMode:Lnet/minecraft/client/multiplayer/MultiPlayerGameMode;
        43: invokevirtual #911                // Method net/minecraft/client/multiplayer/MultiPlayerGameMode.hasExperience:()Z
        46: istore_3
        47: iload_1
        48: ifeq          85
        51: iload_2
        52: ifeq          66
        55: aload_0
        56: invokevirtual #1739               // Method willPrioritizeJumpInfo:()Z
        59: ifeq          66
        62: getstatic     #118                // Field net/minecraft/client/gui/Gui$ContextualInfo.JUMPABLE_VEHICLE:Lnet/minecraft/client/gui/Gui$ContextualInfo;
        65: areturn
        66: iload_3
        67: ifeq          81
        70: aload_0
        71: invokevirtual #1742               // Method willPrioritizeExperienceInfo:()Z
        74: ifeq          81
        77: getstatic     #108                // Field net/minecraft/client/gui/Gui$ContextualInfo.EXPERIENCE:Lnet/minecraft/client/gui/Gui$ContextualInfo;
        80: areturn
        81: getstatic     #114                // Field net/minecraft/client/gui/Gui$ContextualInfo.LOCATOR:Lnet/minecraft/client/gui/Gui$ContextualInfo;
        84: areturn
        85: iload_2
        86: ifeq          93
        89: getstatic     #118                // Field net/minecraft/client/gui/Gui$ContextualInfo.JUMPABLE_VEHICLE:Lnet/minecraft/client/gui/Gui$ContextualInfo;
        92: areturn
        93: iload_3
        94: ifeq          101
        97: getstatic     #108                // Field net/minecraft/client/gui/Gui$ContextualInfo.EXPERIENCE:Lnet/minecraft/client/gui/Gui$ContextualInfo;
       100: areturn
       101: getstatic     #34                 // Field net/minecraft/client/gui/Gui$ContextualInfo.EMPTY:Lnet/minecraft/client/gui/Gui$ContextualInfo;
       104: areturn

  private static net.minecraft.client.gui.Gui$1DisplayEntry[] lambda$displayScoreboardSidebar$2(int);
    Code:
         0: iload_0
         1: anewarray     #1150               // class net/minecraft/client/gui/Gui$1DisplayEntry
         4: areturn

  private net.minecraft.client.gui.Gui$1DisplayEntry lambda$displayScoreboardSidebar$1(net.minecraft.world.scores.Scoreboard, net.minecraft.network.chat.numbers.NumberFormat, net.minecraft.world.scores.PlayerScoreEntry);
    Code:
         0: aload_1
         1: aload_3
         2: invokevirtual #1745               // Method net/minecraft/world/scores/PlayerScoreEntry.owner:()Ljava/lang/String;
         5: invokevirtual #548                // Method net/minecraft/world/scores/Scoreboard.getPlayersTeam:(Ljava/lang/String;)Lnet/minecraft/world/scores/PlayerTeam;
         8: astore        4
        10: aload_3
        11: invokevirtual #1750               // Method net/minecraft/world/scores/PlayerScoreEntry.ownerName:()Lnet/minecraft/network/chat/Component;
        14: astore        5
        16: aload         4
        18: aload         5
        20: invokestatic  #1753               // Method net/minecraft/world/scores/PlayerTeam.formatNameForTeam:(Lnet/minecraft/world/scores/Team;Lnet/minecraft/network/chat/Component;)Lnet/minecraft/network/chat/MutableComponent;
        23: astore        6
        25: aload_3
        26: aload_2
        27: invokevirtual #1757               // Method net/minecraft/world/scores/PlayerScoreEntry.formatValue:(Lnet/minecraft/network/chat/numbers/NumberFormat;)Lnet/minecraft/network/chat/MutableComponent;
        30: astore        7
        32: aload_0
        33: invokevirtual #422                // Method getFont:()Lnet/minecraft/client/gui/Font;
        36: aload         7
        38: invokevirtual #466                // Method net/minecraft/client/gui/Font.width:(Lnet/minecraft/network/chat/FormattedText;)I
        41: istore        8
        43: new           #1150               // class net/minecraft/client/gui/Gui$1DisplayEntry
        46: dup
        47: aload         6
        49: aload         7
        51: iload         8
        53: invokespecial #1761               // Method net/minecraft/client/gui/Gui$1DisplayEntry."<init>":(Lnet/minecraft/network/chat/Component;Lnet/minecraft/network/chat/Component;I)V
        56: areturn

  private static boolean lambda$displayScoreboardSidebar$0(net.minecraft.world.scores.PlayerScoreEntry);
    Code:
         0: aload_0
         1: invokevirtual #1764               // Method net/minecraft/world/scores/PlayerScoreEntry.isHidden:()Z
         4: ifne          11
         7: iconst_1
         8: goto          12
        11: iconst_0
        12: ireturn

  private static net.minecraft.resources.Identifier lambda$getMobEffectSprite$0(net.minecraft.resources.Identifier);
    Code:
         0: aload_0
         1: ldc_w         #1767               // String mob_effect/
         4: invokevirtual #1769               // Method net/minecraft/resources/Identifier.withPrefix:(Ljava/lang/String;)Lnet/minecraft/resources/Identifier;
         7: areturn

  private static java.lang.String lambda$extractCameraOverlays$0(java.lang.String);
    Code:
         0: aload_0
         1: invokedynamic #1773,  0           // InvokeDynamic #13:makeConcatWithConstants:(Ljava/lang/String;)Ljava/lang/String;
         6: areturn

  private void lambda$extractSubtitleOverlay$0(net.minecraft.client.gui.GuiGraphicsExtractor);
    Code:
         0: aload_0
         1: getfield      #100                // Field subtitleOverlay:Lnet/minecraft/client/gui/components/SubtitleOverlay;
         4: aload_1
         5: invokevirtual #227                // Method net/minecraft/client/gui/components/SubtitleOverlay.extractRenderState:(Lnet/minecraft/client/gui/GuiGraphicsExtractor;)V
         8: return

  private static net.minecraft.client.gui.contextualbar.ContextualBarRenderer lambda$new$3(net.minecraft.client.Minecraft);
    Code:
         0: new           #1777               // class net/minecraft/client/gui/contextualbar/JumpableVehicleBarRenderer
         3: dup
         4: aload_0
         5: invokespecial #1779               // Method net/minecraft/client/gui/contextualbar/JumpableVehicleBarRenderer."<init>":(Lnet/minecraft/client/Minecraft;)V
         8: areturn

  private static net.minecraft.client.gui.contextualbar.ContextualBarRenderer lambda$new$2(net.minecraft.client.Minecraft);
    Code:
         0: new           #1780               // class net/minecraft/client/gui/contextualbar/LocatorBarRenderer
         3: dup
         4: aload_0
         5: invokespecial #1782               // Method net/minecraft/client/gui/contextualbar/LocatorBarRenderer."<init>":(Lnet/minecraft/client/Minecraft;)V
         8: areturn

  private static net.minecraft.client.gui.contextualbar.ContextualBarRenderer lambda$new$1(net.minecraft.client.Minecraft);
    Code:
         0: new           #1783               // class net/minecraft/client/gui/contextualbar/ExperienceBarRenderer
         3: dup
         4: aload_0
         5: invokespecial #1785               // Method net/minecraft/client/gui/contextualbar/ExperienceBarRenderer."<init>":(Lnet/minecraft/client/Minecraft;)V
         8: areturn

  private static net.minecraft.client.gui.contextualbar.ContextualBarRenderer lambda$new$0();
    Code:
         0: getstatic     #39                 // Field net/minecraft/client/gui/contextualbar/ContextualBarRenderer.EMPTY:Lnet/minecraft/client/gui/contextualbar/ContextualBarRenderer;
         3: areturn

  static {};
    Code:
         0: ldc_w         #1786               // String hud/crosshair
         3: invokestatic  #1788               // Method net/minecraft/resources/Identifier.withDefaultNamespace:(Ljava/lang/String;)Lnet/minecraft/resources/Identifier;
         6: putstatic     #660                // Field CROSSHAIR_SPRITE:Lnet/minecraft/resources/Identifier;
         9: ldc_w         #1791               // String hud/crosshair_attack_indicator_full
        12: invokestatic  #1788               // Method net/minecraft/resources/Identifier.withDefaultNamespace:(Ljava/lang/String;)Lnet/minecraft/resources/Identifier;
        15: putstatic     #713                // Field CROSSHAIR_ATTACK_INDICATOR_FULL_SPRITE:Lnet/minecraft/resources/Identifier;
        18: ldc_w         #1793               // String hud/crosshair_attack_indicator_background
        21: invokestatic  #1788               // Method net/minecraft/resources/Identifier.withDefaultNamespace:(Ljava/lang/String;)Lnet/minecraft/resources/Identifier;
        24: putstatic     #717                // Field CROSSHAIR_ATTACK_INDICATOR_BACKGROUND_SPRITE:Lnet/minecraft/resources/Identifier;
        27: ldc_w         #1795               // String hud/crosshair_attack_indicator_progress
        30: invokestatic  #1788               // Method net/minecraft/resources/Identifier.withDefaultNamespace:(Ljava/lang/String;)Lnet/minecraft/resources/Identifier;
        33: putstatic     #720                // Field CROSSHAIR_ATTACK_INDICATOR_PROGRESS_SPRITE:Lnet/minecraft/resources/Identifier;
        36: ldc_w         #1797               // String hud/effect_background_ambient
        39: invokestatic  #1788               // Method net/minecraft/resources/Identifier.withDefaultNamespace:(Ljava/lang/String;)Lnet/minecraft/resources/Identifier;
        42: putstatic     #828                // Field EFFECT_BACKGROUND_AMBIENT_SPRITE:Lnet/minecraft/resources/Identifier;
        45: ldc_w         #1799               // String hud/effect_background
        48: invokestatic  #1788               // Method net/minecraft/resources/Identifier.withDefaultNamespace:(Ljava/lang/String;)Lnet/minecraft/resources/Identifier;
        51: putstatic     #831                // Field EFFECT_BACKGROUND_SPRITE:Lnet/minecraft/resources/Identifier;
        54: ldc_w         #1801               // String hud/hotbar
        57: invokestatic  #1788               // Method net/minecraft/resources/Identifier.withDefaultNamespace:(Ljava/lang/String;)Lnet/minecraft/resources/Identifier;
        60: putstatic     #952                // Field HOTBAR_SPRITE:Lnet/minecraft/resources/Identifier;
        63: ldc_w         #1803               // String hud/hotbar_selection
        66: invokestatic  #1788               // Method net/minecraft/resources/Identifier.withDefaultNamespace:(Ljava/lang/String;)Lnet/minecraft/resources/Identifier;
        69: putstatic     #955                // Field HOTBAR_SELECTION_SPRITE:Lnet/minecraft/resources/Identifier;
        72: ldc_w         #1805               // String hud/hotbar_offhand_left
        75: invokestatic  #1788               // Method net/minecraft/resources/Identifier.withDefaultNamespace:(Ljava/lang/String;)Lnet/minecraft/resources/Identifier;
        78: putstatic     #972                // Field HOTBAR_OFFHAND_LEFT_SPRITE:Lnet/minecraft/resources/Identifier;
        81: ldc_w         #1807               // String hud/hotbar_offhand_right
        84: invokestatic  #1788               // Method net/minecraft/resources/Identifier.withDefaultNamespace:(Ljava/lang/String;)Lnet/minecraft/resources/Identifier;
        87: putstatic     #975                // Field HOTBAR_OFFHAND_RIGHT_SPRITE:Lnet/minecraft/resources/Identifier;
        90: ldc_w         #1809               // String hud/hotbar_attack_indicator_background
        93: invokestatic  #1788               // Method net/minecraft/resources/Identifier.withDefaultNamespace:(Ljava/lang/String;)Lnet/minecraft/resources/Identifier;
        96: putstatic     #993                // Field HOTBAR_ATTACK_INDICATOR_BACKGROUND_SPRITE:Lnet/minecraft/resources/Identifier;
        99: ldc_w         #1811               // String hud/hotbar_attack_indicator_progress
       102: invokestatic  #1788               // Method net/minecraft/resources/Identifier.withDefaultNamespace:(Ljava/lang/String;)Lnet/minecraft/resources/Identifier;
       105: putstatic     #996                // Field HOTBAR_ATTACK_INDICATOR_PROGRESS_SPRITE:Lnet/minecraft/resources/Identifier;
       108: ldc_w         #1813               // String hud/armor_empty
       111: invokestatic  #1788               // Method net/minecraft/resources/Identifier.withDefaultNamespace:(Ljava/lang/String;)Lnet/minecraft/resources/Identifier;
       114: putstatic     #1298               // Field ARMOR_EMPTY_SPRITE:Lnet/minecraft/resources/Identifier;
       117: ldc_w         #1815               // String hud/armor_half
       120: invokestatic  #1788               // Method net/minecraft/resources/Identifier.withDefaultNamespace:(Ljava/lang/String;)Lnet/minecraft/resources/Identifier;
       123: putstatic     #1295               // Field ARMOR_HALF_SPRITE:Lnet/minecraft/resources/Identifier;
       126: ldc_w         #1817               // String hud/armor_full
       129: invokestatic  #1788               // Method net/minecraft/resources/Identifier.withDefaultNamespace:(Ljava/lang/String;)Lnet/minecraft/resources/Identifier;
       132: putstatic     #1292               // Field ARMOR_FULL_SPRITE:Lnet/minecraft/resources/Identifier;
       135: ldc_w         #1819               // String hud/food_empty_hunger
       138: invokestatic  #1788               // Method net/minecraft/resources/Identifier.withDefaultNamespace:(Ljava/lang/String;)Lnet/minecraft/resources/Identifier;
       141: putstatic     #1417               // Field FOOD_EMPTY_HUNGER_SPRITE:Lnet/minecraft/resources/Identifier;
       144: ldc_w         #1821               // String hud/food_half_hunger
       147: invokestatic  #1788               // Method net/minecraft/resources/Identifier.withDefaultNamespace:(Ljava/lang/String;)Lnet/minecraft/resources/Identifier;
       150: putstatic     #1420               // Field FOOD_HALF_HUNGER_SPRITE:Lnet/minecraft/resources/Identifier;
       153: ldc_w         #1823               // String hud/food_full_hunger
       156: invokestatic  #1788               // Method net/minecraft/resources/Identifier.withDefaultNamespace:(Ljava/lang/String;)Lnet/minecraft/resources/Identifier;
       159: putstatic     #1423               // Field FOOD_FULL_HUNGER_SPRITE:Lnet/minecraft/resources/Identifier;
       162: ldc_w         #1825               // String hud/food_empty
       165: invokestatic  #1788               // Method net/minecraft/resources/Identifier.withDefaultNamespace:(Ljava/lang/String;)Lnet/minecraft/resources/Identifier;
       168: putstatic     #1426               // Field FOOD_EMPTY_SPRITE:Lnet/minecraft/resources/Identifier;
       171: ldc_w         #1827               // String hud/food_half
       174: invokestatic  #1788               // Method net/minecraft/resources/Identifier.withDefaultNamespace:(Ljava/lang/String;)Lnet/minecraft/resources/Identifier;
       177: putstatic     #1429               // Field FOOD_HALF_SPRITE:Lnet/minecraft/resources/Identifier;
       180: ldc_w         #1829               // String hud/food_full
       183: invokestatic  #1788               // Method net/minecraft/resources/Identifier.withDefaultNamespace:(Ljava/lang/String;)Lnet/minecraft/resources/Identifier;
       186: putstatic     #1432               // Field FOOD_FULL_SPRITE:Lnet/minecraft/resources/Identifier;
       189: ldc_w         #1831               // String hud/air
       192: invokestatic  #1788               // Method net/minecraft/resources/Identifier.withDefaultNamespace:(Ljava/lang/String;)Lnet/minecraft/resources/Identifier;
       195: putstatic     #1376               // Field AIR_SPRITE:Lnet/minecraft/resources/Identifier;
       198: ldc_w         #1833               // String hud/air_bursting
       201: invokestatic  #1788               // Method net/minecraft/resources/Identifier.withDefaultNamespace:(Ljava/lang/String;)Lnet/minecraft/resources/Identifier;
       204: putstatic     #1379               // Field AIR_POPPING_SPRITE:Lnet/minecraft/resources/Identifier;
       207: ldc_w         #1835               // String hud/air_empty
       210: invokestatic  #1788               // Method net/minecraft/resources/Identifier.withDefaultNamespace:(Ljava/lang/String;)Lnet/minecraft/resources/Identifier;
       213: putstatic     #1386               // Field AIR_EMPTY_SPRITE:Lnet/minecraft/resources/Identifier;
       216: ldc_w         #1837               // String hud/heart/vehicle_container
       219: invokestatic  #1788               // Method net/minecraft/resources/Identifier.withDefaultNamespace:(Ljava/lang/String;)Lnet/minecraft/resources/Identifier;
       222: putstatic     #1444               // Field HEART_VEHICLE_CONTAINER_SPRITE:Lnet/minecraft/resources/Identifier;
       225: ldc_w         #1839               // String hud/heart/vehicle_full
       228: invokestatic  #1788               // Method net/minecraft/resources/Identifier.withDefaultNamespace:(Ljava/lang/String;)Lnet/minecraft/resources/Identifier;
       231: putstatic     #1447               // Field HEART_VEHICLE_FULL_SPRITE:Lnet/minecraft/resources/Identifier;
       234: ldc_w         #1841               // String hud/heart/vehicle_half
       237: invokestatic  #1788               // Method net/minecraft/resources/Identifier.withDefaultNamespace:(Ljava/lang/String;)Lnet/minecraft/resources/Identifier;
       240: putstatic     #1450               // Field HEART_VEHICLE_HALF_SPRITE:Lnet/minecraft/resources/Identifier;
       243: ldc_w         #1843               // String textures/misc/vignette.png
       246: invokestatic  #1788               // Method net/minecraft/resources/Identifier.withDefaultNamespace:(Ljava/lang/String;)Lnet/minecraft/resources/Identifier;
       249: putstatic     #1546               // Field VIGNETTE_LOCATION:Lnet/minecraft/resources/Identifier;
       252: ldc_w         #1845               // String textures/misc/nausea.png
       255: invokestatic  #1788               // Method net/minecraft/resources/Identifier.withDefaultNamespace:(Ljava/lang/String;)Lnet/minecraft/resources/Identifier;
       258: putstatic     #1591               // Field NAUSEA_LOCATION:Lnet/minecraft/resources/Identifier;
       261: ldc_w         #1847               // String textures/misc/spyglass_scope.png
       264: invokestatic  #1788               // Method net/minecraft/resources/Identifier.withDefaultNamespace:(Ljava/lang/String;)Lnet/minecraft/resources/Identifier;
       267: putstatic     #1461               // Field SPYGLASS_SCOPE_LOCATION:Lnet/minecraft/resources/Identifier;
       270: ldc_w         #1849               // String textures/misc/powder_snow_outline.png
       273: invokestatic  #1788               // Method net/minecraft/resources/Identifier.withDefaultNamespace:(Ljava/lang/String;)Lnet/minecraft/resources/Identifier;
       276: putstatic     #346                // Field POWDER_SNOW_OUTLINE_LOCATION:Lnet/minecraft/resources/Identifier;
       279: invokedynamic #1851,  0           // InvokeDynamic #14:apply:()Ljava/util/function/Function;
       284: invokestatic  #1852               // InterfaceMethod java/util/Comparator.comparing:(Ljava/util/function/Function;)Ljava/util/Comparator;
       287: invokeinterface #1858,  1         // InterfaceMethod java/util/Comparator.reversed:()Ljava/util/Comparator;
       292: invokedynamic #1862,  0           // InvokeDynamic #15:apply:()Ljava/util/function/Function;
       297: getstatic     #1863               // Field java/lang/String.CASE_INSENSITIVE_ORDER:Ljava/util/Comparator;
       300: invokeinterface #1868,  3         // InterfaceMethod java/util/Comparator.thenComparing:(Ljava/util/function/Function;Ljava/util/Comparator;)Ljava/util/Comparator;
       305: putstatic     #1112               // Field SCORE_DISPLAY_ORDER:Ljava/util/Comparator;
       308: ldc_w         #1872               // String demo.demoExpired
       311: invokestatic  #1874               // InterfaceMethod net/minecraft/network/chat/Component.translatable:(Ljava/lang/String;)Lnet/minecraft/network/chat/MutableComponent;
       314: putstatic     #1055               // Field DEMO_EXPIRED_TEXT:Lnet/minecraft/network/chat/Component;
       317: ldc_w         #1877               // String menu.savingLevel
       320: invokestatic  #1874               // InterfaceMethod net/minecraft/network/chat/Component.translatable:(Ljava/lang/String;)Lnet/minecraft/network/chat/MutableComponent;
       323: putstatic     #1698               // Field SAVING_TEXT:Lnet/minecraft/network/chat/Component;
       326: return
}
